Workbook
Name StartMonth: Inputs!$B$5
Name InitInvest: Inputs!$B$6
Name LotValue0: Inputs!$B$7
Name LotGrowth: Inputs!$B$8
Name NYears: Inputs!$B$9
Name RateA: Inputs!$B$13
Name RateB: Inputs!$B$14
Name RateC: Inputs!$B$15
Name RateD: Inputs!$B$16
Name WdrPct: Inputs!$B$19
Name WdrCap: Inputs!$B$20
Name WdrBase: Inputs!$B$21
Name TaxFreq: Inputs!$B$25
Name TaxLower: Inputs!$B$28:$B$32
Name TaxRate: Inputs!$D$28:$D$32

Sheet Inputs
A1: Straddle Income — Investment Growth Analysis
A2: Yellow cells are inputs. Everything else is a live formula — change any input and the whole workbook recomputes.
A4: 1 · CAPITAL & TIME
A5: Starting month | B5: 46266 | C5: First month of deployment (Mon-YYYY)
A6: Initial investment (INR) | B6: 500000 | C6: Corpus at the starting month
A7: Value of 1 lot at start (INR) | B7: 83333 | C7: ₹5,00,000 / 6 lots ≈ ₹83,333
A8: Lot value increase — year on year | B8: 0.05 | C8: Margin per lot rises as NIFTY/premium grow
A9: Number of years to model | B9: 10 | C9: 1 to 30
C10: → Starting lots (derived): | E10: =INT(Inputs!$B$6/Inputs!$B$7)
A12: 2 · MONTHLY RETURN SCENARIOS — enter returns NET of brokerage, STT and slippage
A13: Scenario A — monthly return | B13: 0.05
A14: Scenario B — monthly return | B14: 0.08
A15: Scenario C — monthly return | B15: 0.1
A16: Scenario D — monthly return (your own) | B16: 0.0425 | C16: 2-decimal precision, e.g. 4.25%
A17: Earned on DEPLOYED capital only (lots × lot value); idle cash earns nothing. These % are assumed ALREADY NET of transaction costs — the only further deductions are govt tax and withdrawals.
A18: 3 · ANNUAL WITHDRAWAL
A19: Withdrawal — % of that year's profit | B19: 0.1
A20: Withdrawal — absolute cap (INR) | B20: 10000000 | C20: ₹1 crore
A21: Withdrawal calculated on | B21: Post-tax profit | C21: Whichever is LOWER of the % and the cap is withdrawn
A22: Withdrawn each year = MIN( % × profit , cap )
A24: 4 · GOVERNMENT TAX (New Regime — 30% base slab already included)
A25: Tax deducted | B25: Quarterly | C25: Quarterly = advance tax leaves the corpus 4×/yr, so it compounds less
A27: Income range | B27: Lower bound (INR) | C27: Surcharge | D27: Effective rate — NEW ← USED | E27: Effective rate — OLD (reference only)
A28: Up to ₹50 Lakh | B28: 0 | C28: 0 | D28: 0.312 | E28: 0.312
A29: ₹50 Lakh – ₹1 Crore | B29: 5000000 | C29: 0.1 | D29: 0.3432 | E29: 0.3432
A30: ₹1 Crore – ₹2 Crore | B30: 10000000 | C30: 0.15 | D30: 0.3588 | E30: 0.3588
A31: ₹2 Crore – ₹5 Crore | B31: 20000000 | C31: 0.25 | D31: 0.39 | E31: 0.39
A32: Above ₹5 Crore | B32: 50000000 | C32: 0.25 | D32: 0.39 | E32: 0.42744
A34: Slab is chosen from ANNUALISED profit, so a growing book climbs into higher surcharge bands over time. Only the NEW-regime column drives the maths.

Sheet Summary
A1: Annual Summary — one row per year, per scenario
A2: =TEXT(StartMonth,"mmm-yyyy")&" to "&TEXT(EDATE(StartMonth,NYears*12-1),"mmm-yyyy")&" · "&TEXT(NYears,"0")&" years · initial "&TEXT(InitInvest,"₹##\,##\,##0")&" = "&TEXT(INT(InitInvest/LotValue0),"0")&" lots"
A4: HEADLINE — where each scenario ends up
A5: Scenario | B5: Monthly return | C5: Final corpus | D5: Final lots | E5: Lots growth × | F5: Total tax paid | G5: Total withdrawn | H5: Corpus ×
A6: Scenario A | B6: =RateA | C6: =INDEX($M$14:$M$43,NYears) | D6: =INDEX($F$14:$F$43,NYears) | E6: =INDEX($F$14:$F$43,NYears)/INT(InitInvest/LotValue0) | F6: =SUM($J$14:$J$43) | G6: =SUM($K$14:$K$43) | H6: =(INDEX($M$14:$M$43,NYears)+SUM($K$14:$K$43))/InitInvest
A7: Scenario B | B7: =RateB | C7: =INDEX($M$47:$M$76,NYears) | D7: =INDEX($F$47:$F$76,NYears) | E7: =INDEX($F$47:$F$76,NYears)/INT(InitInvest/LotValue0) | F7: =SUM($J$47:$J$76) | G7: =SUM($K$47:$K$76) | H7: =(INDEX($M$47:$M$76,NYears)+SUM($K$47:$K$76))/InitInvest
A8: Scenario C | B8: =RateC | C8: =INDEX($M$80:$M$109,NYears) | D8: =INDEX($F$80:$F$109,NYears) | E8: =INDEX($F$80:$F$109,NYears)/INT(InitInvest/LotValue0) | F8: =SUM($J$80:$J$109) | G8: =SUM($K$80:$K$109) | H8: =(INDEX($M$80:$M$109,NYears)+SUM($K$80:$K$109))/InitInvest
A9: Scenario D | B9: =RateD | C9: =INDEX($M$113:$M$142,NYears) | D9: =INDEX($F$113:$F$142,NYears) | E9: =INDEX($F$113:$F$142,NYears)/INT(InitInvest/LotValue0) | F9: =SUM($J$113:$J$142) | G9: =SUM($K$113:$K$142) | H9: =(INDEX($M$113:$M$142,NYears)+SUM($K$113:$K$142))/InitInvest
A10: "Corpus ×" counts money taken out as well as money still invested — otherwise a big withdrawal looks like worse performance. Lots growth is the honest measure of deployed scale.
A12: SCENARIO A | B12: =RateA | C12: per month
A13: Year | B13: Year ending | C13: Lot value | D13: Opening corpus | E13: Lots start | F13: Lots end | G13: Lots added | H13: Deployed capital | I13: TRADING PROFIT (net of charges, pre-tax) | J13: Govt tax | K13: Withdrawal | L13: REAL PROFIT (post tax & withdrawal) | M13: Closing corpus
A14: =1 | B14: =IF($A14>NYears,"",EDATE(StartMonth,$A14*12-1)) | C14: =IF($A14>NYears,"",'Engine A'!$E16) | D14: =IF($A14>NYears,"",'Engine A'!$F5) | E14: =IF($A14>NYears,"",'Engine A'!$G5) | F14: =IF($A14>NYears,"",'Engine A'!$S16) | G14: =IF($A14>NYears,"",'Engine A'!$S16-'Engine A'!$G5) | H14: =IF($A14>NYears,"",'Engine A'!$S16*'Engine A'!$E16) | I14: =IF($A14>NYears,"",'Engine A'!$K16) | J14: =IF($A14>NYears,"",'Engine A'!$P16) | K14: =IF($A14>NYears,"",'Engine A'!$Q16) | L14: =IF($A14>NYears,"",'Engine A'!$K16-'Engine A'!$P16-'Engine A'!$Q16) | M14: =IF($A14>NYears,"",'Engine A'!$R16)
A15: =2 | B15: =IF($A15>NYears,"",EDATE(StartMonth,$A15*12-1)) | C15: =IF($A15>NYears,"",'Engine A'!$E28) | D15: =IF($A15>NYears,"",'Engine A'!$F17) | E15: =IF($A15>NYears,"",'Engine A'!$G17) | F15: =IF($A15>NYears,"",'Engine A'!$S28) | G15: =IF($A15>NYears,"",'Engine A'!$S28-'Engine A'!$G17) | H15: =IF($A15>NYears,"",'Engine A'!$S28*'Engine A'!$E28) | I15: =IF($A15>NYears,"",'Engine A'!$K28) | J15: =IF($A15>NYears,"",'Engine A'!$P28) | K15: =IF($A15>NYears,"",'Engine A'!$Q28) | L15: =IF($A15>NYears,"",'Engine A'!$K28-'Engine A'!$P28-'Engine A'!$Q28) | M15: =IF($A15>NYears,"",'Engine A'!$R28)
A16: =3 | B16: =IF($A16>NYears,"",EDATE(StartMonth,$A16*12-1)) | C16: =IF($A16>NYears,"",'Engine A'!$E40) | D16: =IF($A16>NYears,"",'Engine A'!$F29) | E16: =IF($A16>NYears,"",'Engine A'!$G29) | F16: =IF($A16>NYears,"",'Engine A'!$S40) | G16: =IF($A16>NYears,"",'Engine A'!$S40-'Engine A'!$G29) | H16: =IF($A16>NYears,"",'Engine A'!$S40*'Engine A'!$E40) | I16: =IF($A16>NYears,"",'Engine A'!$K40) | J16: =IF($A16>NYears,"",'Engine A'!$P40) | K16: =IF($A16>NYears,"",'Engine A'!$Q40) | L16: =IF($A16>NYears,"",'Engine A'!$K40-'Engine A'!$P40-'Engine A'!$Q40) | M16: =IF($A16>NYears,"",'Engine A'!$R40)
A17: =4 | B17: =IF($A17>NYears,"",EDATE(StartMonth,$A17*12-1)) | C17: =IF($A17>NYears,"",'Engine A'!$E52) | D17: =IF($A17>NYears,"",'Engine A'!$F41) | E17: =IF($A17>NYears,"",'Engine A'!$G41) | F17: =IF($A17>NYears,"",'Engine A'!$S52) | G17: =IF($A17>NYears,"",'Engine A'!$S52-'Engine A'!$G41) | H17: =IF($A17>NYears,"",'Engine A'!$S52*'Engine A'!$E52) | I17: =IF($A17>NYears,"",'Engine A'!$K52) | J17: =IF($A17>NYears,"",'Engine A'!$P52) | K17: =IF($A17>NYears,"",'Engine A'!$Q52) | L17: =IF($A17>NYears,"",'Engine A'!$K52-'Engine A'!$P52-'Engine A'!$Q52) | M17: =IF($A17>NYears,"",'Engine A'!$R52)
A18: =5 | B18: =IF($A18>NYears,"",EDATE(StartMonth,$A18*12-1)) | C18: =IF($A18>NYears,"",'Engine A'!$E64) | D18: =IF($A18>NYears,"",'Engine A'!$F53) | E18: =IF($A18>NYears,"",'Engine A'!$G53) | F18: =IF($A18>NYears,"",'Engine A'!$S64) | G18: =IF($A18>NYears,"",'Engine A'!$S64-'Engine A'!$G53) | H18: =IF($A18>NYears,"",'Engine A'!$S64*'Engine A'!$E64) | I18: =IF($A18>NYears,"",'Engine A'!$K64) | J18: =IF($A18>NYears,"",'Engine A'!$P64) | K18: =IF($A18>NYears,"",'Engine A'!$Q64) | L18: =IF($A18>NYears,"",'Engine A'!$K64-'Engine A'!$P64-'Engine A'!$Q64) | M18: =IF($A18>NYears,"",'Engine A'!$R64)
A19: =6 | B19: =IF($A19>NYears,"",EDATE(StartMonth,$A19*12-1)) | C19: =IF($A19>NYears,"",'Engine A'!$E76) | D19: =IF($A19>NYears,"",'Engine A'!$F65) | E19: =IF($A19>NYears,"",'Engine A'!$G65) | F19: =IF($A19>NYears,"",'Engine A'!$S76) | G19: =IF($A19>NYears,"",'Engine A'!$S76-'Engine A'!$G65) | H19: =IF($A19>NYears,"",'Engine A'!$S76*'Engine A'!$E76) | I19: =IF($A19>NYears,"",'Engine A'!$K76) | J19: =IF($A19>NYears,"",'Engine A'!$P76) | K19: =IF($A19>NYears,"",'Engine A'!$Q76) | L19: =IF($A19>NYears,"",'Engine A'!$K76-'Engine A'!$P76-'Engine A'!$Q76) | M19: =IF($A19>NYears,"",'Engine A'!$R76)
A20: =7 | B20: =IF($A20>NYears,"",EDATE(StartMonth,$A20*12-1)) | C20: =IF($A20>NYears,"",'Engine A'!$E88) | D20: =IF($A20>NYears,"",'Engine A'!$F77) | E20: =IF($A20>NYears,"",'Engine A'!$G77) | F20: =IF($A20>NYears,"",'Engine A'!$S88) | G20: =IF($A20>NYears,"",'Engine A'!$S88-'Engine A'!$G77) | H20: =IF($A20>NYears,"",'Engine A'!$S88*'Engine A'!$E88) | I20: =IF($A20>NYears,"",'Engine A'!$K88) | J20: =IF($A20>NYears,"",'Engine A'!$P88) | K20: =IF($A20>NYears,"",'Engine A'!$Q88) | L20: =IF($A20>NYears,"",'Engine A'!$K88-'Engine A'!$P88-'Engine A'!$Q88) | M20: =IF($A20>NYears,"",'Engine A'!$R88)
A21: =8 | B21: =IF($A21>NYears,"",EDATE(StartMonth,$A21*12-1)) | C21: =IF($A21>NYears,"",'Engine A'!$E100) | D21: =IF($A21>NYears,"",'Engine A'!$F89) | E21: =IF($A21>NYears,"",'Engine A'!$G89) | F21: =IF($A21>NYears,"",'Engine A'!$S100) | G21: =IF($A21>NYears,"",'Engine A'!$S100-'Engine A'!$G89) | H21: =IF($A21>NYears,"",'Engine A'!$S100*'Engine A'!$E100) | I21: =IF($A21>NYears,"",'Engine A'!$K100) | J21: =IF($A21>NYears,"",'Engine A'!$P100) | K21: =IF($A21>NYears,"",'Engine A'!$Q100) | L21: =IF($A21>NYears,"",'Engine A'!$K100-'Engine A'!$P100-'Engine A'!$Q100) | M21: =IF($A21>NYears,"",'Engine A'!$R100)
A22: =9 | B22: =IF($A22>NYears,"",EDATE(StartMonth,$A22*12-1)) | C22: =IF($A22>NYears,"",'Engine A'!$E112) | D22: =IF($A22>NYears,"",'Engine A'!$F101) | E22: =IF($A22>NYears,"",'Engine A'!$G101) | F22: =IF($A22>NYears,"",'Engine A'!$S112) | G22: =IF($A22>NYears,"",'Engine A'!$S112-'Engine A'!$G101) | H22: =IF($A22>NYears,"",'Engine A'!$S112*'Engine A'!$E112) | I22: =IF($A22>NYears,"",'Engine A'!$K112) | J22: =IF($A22>NYears,"",'Engine A'!$P112) | K22: =IF($A22>NYears,"",'Engine A'!$Q112) | L22: =IF($A22>NYears,"",'Engine A'!$K112-'Engine A'!$P112-'Engine A'!$Q112) | M22: =IF($A22>NYears,"",'Engine A'!$R112)
A23: =10 | B23: =IF($A23>NYears,"",EDATE(StartMonth,$A23*12-1)) | C23: =IF($A23>NYears,"",'Engine A'!$E124) | D23: =IF($A23>NYears,"",'Engine A'!$F113) | E23: =IF($A23>NYears,"",'Engine A'!$G113) | F23: =IF($A23>NYears,"",'Engine A'!$S124) | G23: =IF($A23>NYears,"",'Engine A'!$S124-'Engine A'!$G113) | H23: =IF($A23>NYears,"",'Engine A'!$S124*'Engine A'!$E124) | I23: =IF($A23>NYears,"",'Engine A'!$K124) | J23: =IF($A23>NYears,"",'Engine A'!$P124) | K23: =IF($A23>NYears,"",'Engine A'!$Q124) | L23: =IF($A23>NYears,"",'Engine A'!$K124-'Engine A'!$P124-'Engine A'!$Q124) | M23: =IF($A23>NYears,"",'Engine A'!$R124)
A24: =11 | B24: =IF($A24>NYears,"",EDATE(StartMonth,$A24*12-1)) | C24: =IF($A24>NYears,"",'Engine A'!$E136) | D24: =IF($A24>NYears,"",'Engine A'!$F125) | E24: =IF($A24>NYears,"",'Engine A'!$G125) | F24: =IF($A24>NYears,"",'Engine A'!$S136) | G24: =IF($A24>NYears,"",'Engine A'!$S136-'Engine A'!$G125) | H24: =IF($A24>NYears,"",'Engine A'!$S136*'Engine A'!$E136) | I24: =IF($A24>NYears,"",'Engine A'!$K136) | J24: =IF($A24>NYears,"",'Engine A'!$P136) | K24: =IF($A24>NYears,"",'Engine A'!$Q136) | L24: =IF($A24>NYears,"",'Engine A'!$K136-'Engine A'!$P136-'Engine A'!$Q136) | M24: =IF($A24>NYears,"",'Engine A'!$R136)
A25: =12 | B25: =IF($A25>NYears,"",EDATE(StartMonth,$A25*12-1)) | C25: =IF($A25>NYears,"",'Engine A'!$E148) | D25: =IF($A25>NYears,"",'Engine A'!$F137) | E25: =IF($A25>NYears,"",'Engine A'!$G137) | F25: =IF($A25>NYears,"",'Engine A'!$S148) | G25: =IF($A25>NYears,"",'Engine A'!$S148-'Engine A'!$G137) | H25: =IF($A25>NYears,"",'Engine A'!$S148*'Engine A'!$E148) | I25: =IF($A25>NYears,"",'Engine A'!$K148) | J25: =IF($A25>NYears,"",'Engine A'!$P148) | K25: =IF($A25>NYears,"",'Engine A'!$Q148) | L25: =IF($A25>NYears,"",'Engine A'!$K148-'Engine A'!$P148-'Engine A'!$Q148) | M25: =IF($A25>NYears,"",'Engine A'!$R148)
A26: =13 | B26: =IF($A26>NYears,"",EDATE(StartMonth,$A26*12-1)) | C26: =IF($A26>NYears,"",'Engine A'!$E160) | D26: =IF($A26>NYears,"",'Engine A'!$F149) | E26: =IF($A26>NYears,"",'Engine A'!$G149) | F26: =IF($A26>NYears,"",'Engine A'!$S160) | G26: =IF($A26>NYears,"",'Engine A'!$S160-'Engine A'!$G149) | H26: =IF($A26>NYears,"",'Engine A'!$S160*'Engine A'!$E160) | I26: =IF($A26>NYears,"",'Engine A'!$K160) | J26: =IF($A26>NYears,"",'Engine A'!$P160) | K26: =IF($A26>NYears,"",'Engine A'!$Q160) | L26: =IF($A26>NYears,"",'Engine A'!$K160-'Engine A'!$P160-'Engine A'!$Q160) | M26: =IF($A26>NYears,"",'Engine A'!$R160)
A27: =14 | B27: =IF($A27>NYears,"",EDATE(StartMonth,$A27*12-1)) | C27: =IF($A27>NYears,"",'Engine A'!$E172) | D27: =IF($A27>NYears,"",'Engine A'!$F161) | E27: =IF($A27>NYears,"",'Engine A'!$G161) | F27: =IF($A27>NYears,"",'Engine A'!$S172) | G27: =IF($A27>NYears,"",'Engine A'!$S172-'Engine A'!$G161) | H27: =IF($A27>NYears,"",'Engine A'!$S172*'Engine A'!$E172) | I27: =IF($A27>NYears,"",'Engine A'!$K172) | J27: =IF($A27>NYears,"",'Engine A'!$P172) | K27: =IF($A27>NYears,"",'Engine A'!$Q172) | L27: =IF($A27>NYears,"",'Engine A'!$K172-'Engine A'!$P172-'Engine A'!$Q172) | M27: =IF($A27>NYears,"",'Engine A'!$R172)
A28: =15 | B28: =IF($A28>NYears,"",EDATE(StartMonth,$A28*12-1)) | C28: =IF($A28>NYears,"",'Engine A'!$E184) | D28: =IF($A28>NYears,"",'Engine A'!$F173) | E28: =IF($A28>NYears,"",'Engine A'!$G173) | F28: =IF($A28>NYears,"",'Engine A'!$S184) | G28: =IF($A28>NYears,"",'Engine A'!$S184-'Engine A'!$G173) | H28: =IF($A28>NYears,"",'Engine A'!$S184*'Engine A'!$E184) | I28: =IF($A28>NYears,"",'Engine A'!$K184) | J28: =IF($A28>NYears,"",'Engine A'!$P184) | K28: =IF($A28>NYears,"",'Engine A'!$Q184) | L28: =IF($A28>NYears,"",'Engine A'!$K184-'Engine A'!$P184-'Engine A'!$Q184) | M28: =IF($A28>NYears,"",'Engine A'!$R184)
A29: =16 | B29: =IF($A29>NYears,"",EDATE(StartMonth,$A29*12-1)) | C29: =IF($A29>NYears,"",'Engine A'!$E196) | D29: =IF($A29>NYears,"",'Engine A'!$F185) | E29: =IF($A29>NYears,"",'Engine A'!$G185) | F29: =IF($A29>NYears,"",'Engine A'!$S196) | G29: =IF($A29>NYears,"",'Engine A'!$S196-'Engine A'!$G185) | H29: =IF($A29>NYears,"",'Engine A'!$S196*'Engine A'!$E196) | I29: =IF($A29>NYears,"",'Engine A'!$K196) | J29: =IF($A29>NYears,"",'Engine A'!$P196) | K29: =IF($A29>NYears,"",'Engine A'!$Q196) | L29: =IF($A29>NYears,"",'Engine A'!$K196-'Engine A'!$P196-'Engine A'!$Q196) | M29: =IF($A29>NYears,"",'Engine A'!$R196)
A30: =17 | B30: =IF($A30>NYears,"",EDATE(StartMonth,$A30*12-1)) | C30: =IF($A30>NYears,"",'Engine A'!$E208) | D30: =IF($A30>NYears,"",'Engine A'!$F197) | E30: =IF($A30>NYears,"",'Engine A'!$G197) | F30: =IF($A30>NYears,"",'Engine A'!$S208) | G30: =IF($A30>NYears,"",'Engine A'!$S208-'Engine A'!$G197) | H30: =IF($A30>NYears,"",'Engine A'!$S208*'Engine A'!$E208) | I30: =IF($A30>NYears,"",'Engine A'!$K208) | J30: =IF($A30>NYears,"",'Engine A'!$P208) | K30: =IF($A30>NYears,"",'Engine A'!$Q208) | L30: =IF($A30>NYears,"",'Engine A'!$K208-'Engine A'!$P208-'Engine A'!$Q208) | M30: =IF($A30>NYears,"",'Engine A'!$R208)
A31: =18 | B31: =IF($A31>NYears,"",EDATE(StartMonth,$A31*12-1)) | C31: =IF($A31>NYears,"",'Engine A'!$E220) | D31: =IF($A31>NYears,"",'Engine A'!$F209) | E31: =IF($A31>NYears,"",'Engine A'!$G209) | F31: =IF($A31>NYears,"",'Engine A'!$S220) | G31: =IF($A31>NYears,"",'Engine A'!$S220-'Engine A'!$G209) | H31: =IF($A31>NYears,"",'Engine A'!$S220*'Engine A'!$E220) | I31: =IF($A31>NYears,"",'Engine A'!$K220) | J31: =IF($A31>NYears,"",'Engine A'!$P220) | K31: =IF($A31>NYears,"",'Engine A'!$Q220) | L31: =IF($A31>NYears,"",'Engine A'!$K220-'Engine A'!$P220-'Engine A'!$Q220) | M31: =IF($A31>NYears,"",'Engine A'!$R220)
A32: =19 | B32: =IF($A32>NYears,"",EDATE(StartMonth,$A32*12-1)) | C32: =IF($A32>NYears,"",'Engine A'!$E232) | D32: =IF($A32>NYears,"",'Engine A'!$F221) | E32: =IF($A32>NYears,"",'Engine A'!$G221) | F32: =IF($A32>NYears,"",'Engine A'!$S232) | G32: =IF($A32>NYears,"",'Engine A'!$S232-'Engine A'!$G221) | H32: =IF($A32>NYears,"",'Engine A'!$S232*'Engine A'!$E232) | I32: =IF($A32>NYears,"",'Engine A'!$K232) | J32: =IF($A32>NYears,"",'Engine A'!$P232) | K32: =IF($A32>NYears,"",'Engine A'!$Q232) | L32: =IF($A32>NYears,"",'Engine A'!$K232-'Engine A'!$P232-'Engine A'!$Q232) | M32: =IF($A32>NYears,"",'Engine A'!$R232)
A33: =20 | B33: =IF($A33>NYears,"",EDATE(StartMonth,$A33*12-1)) | C33: =IF($A33>NYears,"",'Engine A'!$E244) | D33: =IF($A33>NYears,"",'Engine A'!$F233) | E33: =IF($A33>NYears,"",'Engine A'!$G233) | F33: =IF($A33>NYears,"",'Engine A'!$S244) | G33: =IF($A33>NYears,"",'Engine A'!$S244-'Engine A'!$G233) | H33: =IF($A33>NYears,"",'Engine A'!$S244*'Engine A'!$E244) | I33: =IF($A33>NYears,"",'Engine A'!$K244) | J33: =IF($A33>NYears,"",'Engine A'!$P244) | K33: =IF($A33>NYears,"",'Engine A'!$Q244) | L33: =IF($A33>NYears,"",'Engine A'!$K244-'Engine A'!$P244-'Engine A'!$Q244) | M33: =IF($A33>NYears,"",'Engine A'!$R244)
A34: =21 | B34: =IF($A34>NYears,"",EDATE(StartMonth,$A34*12-1)) | C34: =IF($A34>NYears,"",'Engine A'!$E256) | D34: =IF($A34>NYears,"",'Engine A'!$F245) | E34: =IF($A34>NYears,"",'Engine A'!$G245) | F34: =IF($A34>NYears,"",'Engine A'!$S256) | G34: =IF($A34>NYears,"",'Engine A'!$S256-'Engine A'!$G245) | H34: =IF($A34>NYears,"",'Engine A'!$S256*'Engine A'!$E256) | I34: =IF($A34>NYears,"",'Engine A'!$K256) | J34: =IF($A34>NYears,"",'Engine A'!$P256) | K34: =IF($A34>NYears,"",'Engine A'!$Q256) | L34: =IF($A34>NYears,"",'Engine A'!$K256-'Engine A'!$P256-'Engine A'!$Q256) | M34: =IF($A34>NYears,"",'Engine A'!$R256)
A35: =22 | B35: =IF($A35>NYears,"",EDATE(StartMonth,$A35*12-1)) | C35: =IF($A35>NYears,"",'Engine A'!$E268) | D35: =IF($A35>NYears,"",'Engine A'!$F257) | E35: =IF($A35>NYears,"",'Engine A'!$G257) | F35: =IF($A35>NYears,"",'Engine A'!$S268) | G35: =IF($A35>NYears,"",'Engine A'!$S268-'Engine A'!$G257) | H35: =IF($A35>NYears,"",'Engine A'!$S268*'Engine A'!$E268) | I35: =IF($A35>NYears,"",'Engine A'!$K268) | J35: =IF($A35>NYears,"",'Engine A'!$P268) | K35: =IF($A35>NYears,"",'Engine A'!$Q268) | L35: =IF($A35>NYears,"",'Engine A'!$K268-'Engine A'!$P268-'Engine A'!$Q268) | M35: =IF($A35>NYears,"",'Engine A'!$R268)
A36: =23 | B36: =IF($A36>NYears,"",EDATE(StartMonth,$A36*12-1)) | C36: =IF($A36>NYears,"",'Engine A'!$E280) | D36: =IF($A36>NYears,"",'Engine A'!$F269) | E36: =IF($A36>NYears,"",'Engine A'!$G269) | F36: =IF($A36>NYears,"",'Engine A'!$S280) | G36: =IF($A36>NYears,"",'Engine A'!$S280-'Engine A'!$G269) | H36: =IF($A36>NYears,"",'Engine A'!$S280*'Engine A'!$E280) | I36: =IF($A36>NYears,"",'Engine A'!$K280) | J36: =IF($A36>NYears,"",'Engine A'!$P280) | K36: =IF($A36>NYears,"",'Engine A'!$Q280) | L36: =IF($A36>NYears,"",'Engine A'!$K280-'Engine A'!$P280-'Engine A'!$Q280) | M36: =IF($A36>NYears,"",'Engine A'!$R280)
A37: =24 | B37: =IF($A37>NYears,"",EDATE(StartMonth,$A37*12-1)) | C37: =IF($A37>NYears,"",'Engine A'!$E292) | D37: =IF($A37>NYears,"",'Engine A'!$F281) | E37: =IF($A37>NYears,"",'Engine A'!$G281) | F37: =IF($A37>NYears,"",'Engine A'!$S292) | G37: =IF($A37>NYears,"",'Engine A'!$S292-'Engine A'!$G281) | H37: =IF($A37>NYears,"",'Engine A'!$S292*'Engine A'!$E292) | I37: =IF($A37>NYears,"",'Engine A'!$K292) | J37: =IF($A37>NYears,"",'Engine A'!$P292) | K37: =IF($A37>NYears,"",'Engine A'!$Q292) | L37: =IF($A37>NYears,"",'Engine A'!$K292-'Engine A'!$P292-'Engine A'!$Q292) | M37: =IF($A37>NYears,"",'Engine A'!$R292)
A38: =25 | B38: =IF($A38>NYears,"",EDATE(StartMonth,$A38*12-1)) | C38: =IF($A38>NYears,"",'Engine A'!$E304) | D38: =IF($A38>NYears,"",'Engine A'!$F293) | E38: =IF($A38>NYears,"",'Engine A'!$G293) | F38: =IF($A38>NYears,"",'Engine A'!$S304) | G38: =IF($A38>NYears,"",'Engine A'!$S304-'Engine A'!$G293) | H38: =IF($A38>NYears,"",'Engine A'!$S304*'Engine A'!$E304) | I38: =IF($A38>NYears,"",'Engine A'!$K304) | J38: =IF($A38>NYears,"",'Engine A'!$P304) | K38: =IF($A38>NYears,"",'Engine A'!$Q304) | L38: =IF($A38>NYears,"",'Engine A'!$K304-'Engine A'!$P304-'Engine A'!$Q304) | M38: =IF($A38>NYears,"",'Engine A'!$R304)
A39: =26 | B39: =IF($A39>NYears,"",EDATE(StartMonth,$A39*12-1)) | C39: =IF($A39>NYears,"",'Engine A'!$E316) | D39: =IF($A39>NYears,"",'Engine A'!$F305) | E39: =IF($A39>NYears,"",'Engine A'!$G305) | F39: =IF($A39>NYears,"",'Engine A'!$S316) | G39: =IF($A39>NYears,"",'Engine A'!$S316-'Engine A'!$G305) | H39: =IF($A39>NYears,"",'Engine A'!$S316*'Engine A'!$E316) | I39: =IF($A39>NYears,"",'Engine A'!$K316) | J39: =IF($A39>NYears,"",'Engine A'!$P316) | K39: =IF($A39>NYears,"",'Engine A'!$Q316) | L39: =IF($A39>NYears,"",'Engine A'!$K316-'Engine A'!$P316-'Engine A'!$Q316) | M39: =IF($A39>NYears,"",'Engine A'!$R316)
A40: =27 | B40: =IF($A40>NYears,"",EDATE(StartMonth,$A40*12-1)) | C40: =IF($A40>NYears,"",'Engine A'!$E328) | D40: =IF($A40>NYears,"",'Engine A'!$F317) | E40: =IF($A40>NYears,"",'Engine A'!$G317) | F40: =IF($A40>NYears,"",'Engine A'!$S328) | G40: =IF($A40>NYears,"",'Engine A'!$S328-'Engine A'!$G317) | H40: =IF($A40>NYears,"",'Engine A'!$S328*'Engine A'!$E328) | I40: =IF($A40>NYears,"",'Engine A'!$K328) | J40: =IF($A40>NYears,"",'Engine A'!$P328) | K40: =IF($A40>NYears,"",'Engine A'!$Q328) | L40: =IF($A40>NYears,"",'Engine A'!$K328-'Engine A'!$P328-'Engine A'!$Q328) | M40: =IF($A40>NYears,"",'Engine A'!$R328)
A41: =28 | B41: =IF($A41>NYears,"",EDATE(StartMonth,$A41*12-1)) | C41: =IF($A41>NYears,"",'Engine A'!$E340) | D41: =IF($A41>NYears,"",'Engine A'!$F329) | E41: =IF($A41>NYears,"",'Engine A'!$G329) | F41: =IF($A41>NYears,"",'Engine A'!$S340) | G41: =IF($A41>NYears,"",'Engine A'!$S340-'Engine A'!$G329) | H41: =IF($A41>NYears,"",'Engine A'!$S340*'Engine A'!$E340) | I41: =IF($A41>NYears,"",'Engine A'!$K340) | J41: =IF($A41>NYears,"",'Engine A'!$P340) | K41: =IF($A41>NYears,"",'Engine A'!$Q340) | L41: =IF($A41>NYears,"",'Engine A'!$K340-'Engine A'!$P340-'Engine A'!$Q340) | M41: =IF($A41>NYears,"",'Engine A'!$R340)
A42: =29 | B42: =IF($A42>NYears,"",EDATE(StartMonth,$A42*12-1)) | C42: =IF($A42>NYears,"",'Engine A'!$E352) | D42: =IF($A42>NYears,"",'Engine A'!$F341) | E42: =IF($A42>NYears,"",'Engine A'!$G341) | F42: =IF($A42>NYears,"",'Engine A'!$S352) | G42: =IF($A42>NYears,"",'Engine A'!$S352-'Engine A'!$G341) | H42: =IF($A42>NYears,"",'Engine A'!$S352*'Engine A'!$E352) | I42: =IF($A42>NYears,"",'Engine A'!$K352) | J42: =IF($A42>NYears,"",'Engine A'!$P352) | K42: =IF($A42>NYears,"",'Engine A'!$Q352) | L42: =IF($A42>NYears,"",'Engine A'!$K352-'Engine A'!$P352-'Engine A'!$Q352) | M42: =IF($A42>NYears,"",'Engine A'!$R352)
A43: =30 | B43: =IF($A43>NYears,"",EDATE(StartMonth,$A43*12-1)) | C43: =IF($A43>NYears,"",'Engine A'!$E364) | D43: =IF($A43>NYears,"",'Engine A'!$F353) | E43: =IF($A43>NYears,"",'Engine A'!$G353) | F43: =IF($A43>NYears,"",'Engine A'!$S364) | G43: =IF($A43>NYears,"",'Engine A'!$S364-'Engine A'!$G353) | H43: =IF($A43>NYears,"",'Engine A'!$S364*'Engine A'!$E364) | I43: =IF($A43>NYears,"",'Engine A'!$K364) | J43: =IF($A43>NYears,"",'Engine A'!$P364) | K43: =IF($A43>NYears,"",'Engine A'!$Q364) | L43: =IF($A43>NYears,"",'Engine A'!$K364-'Engine A'!$P364-'Engine A'!$Q364) | M43: =IF($A43>NYears,"",'Engine A'!$R364)
A45: SCENARIO B | B45: =RateB | C45: per month
A46: Year | B46: Year ending | C46: Lot value | D46: Opening corpus | E46: Lots start | F46: Lots end | G46: Lots added | H46: Deployed capital | I46: TRADING PROFIT (net of charges, pre-tax) | J46: Govt tax | K46: Withdrawal | L46: REAL PROFIT (post tax & withdrawal) | M46: Closing corpus
A47: =1 | B47: =IF($A47>NYears,"",EDATE(StartMonth,$A47*12-1)) | C47: =IF($A47>NYears,"",'Engine B'!$E16) | D47: =IF($A47>NYears,"",'Engine B'!$F5) | E47: =IF($A47>NYears,"",'Engine B'!$G5) | F47: =IF($A47>NYears,"",'Engine B'!$S16) | G47: =IF($A47>NYears,"",'Engine B'!$S16-'Engine B'!$G5) | H47: =IF($A47>NYears,"",'Engine B'!$S16*'Engine B'!$E16) | I47: =IF($A47>NYears,"",'Engine B'!$K16) | J47: =IF($A47>NYears,"",'Engine B'!$P16) | K47: =IF($A47>NYears,"",'Engine B'!$Q16) | L47: =IF($A47>NYears,"",'Engine B'!$K16-'Engine B'!$P16-'Engine B'!$Q16) | M47: =IF($A47>NYears,"",'Engine B'!$R16)
A48: =2 | B48: =IF($A48>NYears,"",EDATE(StartMonth,$A48*12-1)) | C48: =IF($A48>NYears,"",'Engine B'!$E28) | D48: =IF($A48>NYears,"",'Engine B'!$F17) | E48: =IF($A48>NYears,"",'Engine B'!$G17) | F48: =IF($A48>NYears,"",'Engine B'!$S28) | G48: =IF($A48>NYears,"",'Engine B'!$S28-'Engine B'!$G17) | H48: =IF($A48>NYears,"",'Engine B'!$S28*'Engine B'!$E28) | I48: =IF($A48>NYears,"",'Engine B'!$K28) | J48: =IF($A48>NYears,"",'Engine B'!$P28) | K48: =IF($A48>NYears,"",'Engine B'!$Q28) | L48: =IF($A48>NYears,"",'Engine B'!$K28-'Engine B'!$P28-'Engine B'!$Q28) | M48: =IF($A48>NYears,"",'Engine B'!$R28)
A49: =3 | B49: =IF($A49>NYears,"",EDATE(StartMonth,$A49*12-1)) | C49: =IF($A49>NYears,"",'Engine B'!$E40) | D49: =IF($A49>NYears,"",'Engine B'!$F29) | E49: =IF($A49>NYears,"",'Engine B'!$G29) | F49: =IF($A49>NYears,"",'Engine B'!$S40) | G49: =IF($A49>NYears,"",'Engine B'!$S40-'Engine B'!$G29) | H49: =IF($A49>NYears,"",'Engine B'!$S40*'Engine B'!$E40) | I49: =IF($A49>NYears,"",'Engine B'!$K40) | J49: =IF($A49>NYears,"",'Engine B'!$P40) | K49: =IF($A49>NYears,"",'Engine B'!$Q40) | L49: =IF($A49>NYears,"",'Engine B'!$K40-'Engine B'!$P40-'Engine B'!$Q40) | M49: =IF($A49>NYears,"",'Engine B'!$R40)
A50: =4 | B50: =IF($A50>NYears,"",EDATE(StartMonth,$A50*12-1)) | C50: =IF($A50>NYears,"",'Engine B'!$E52) | D50: =IF($A50>NYears,"",'Engine B'!$F41) | E50: =IF($A50>NYears,"",'Engine B'!$G41) | F50: =IF($A50>NYears,"",'Engine B'!$S52) | G50: =IF($A50>NYears,"",'Engine B'!$S52-'Engine B'!$G41) | H50: =IF($A50>NYears,"",'Engine B'!$S52*'Engine B'!$E52) | I50: =IF($A50>NYears,"",'Engine B'!$K52) | J50: =IF($A50>NYears,"",'Engine B'!$P52) | K50: =IF($A50>NYears,"",'Engine B'!$Q52) | L50: =IF($A50>NYears,"",'Engine B'!$K52-'Engine B'!$P52-'Engine B'!$Q52) | M50: =IF($A50>NYears,"",'Engine B'!$R52)
A51: =5 | B51: =IF($A51>NYears,"",EDATE(StartMonth,$A51*12-1)) | C51: =IF($A51>NYears,"",'Engine B'!$E64) | D51: =IF($A51>NYears,"",'Engine B'!$F53) | E51: =IF($A51>NYears,"",'Engine B'!$G53) | F51: =IF($A51>NYears,"",'Engine B'!$S64) | G51: =IF($A51>NYears,"",'Engine B'!$S64-'Engine B'!$G53) | H51: =IF($A51>NYears,"",'Engine B'!$S64*'Engine B'!$E64) | I51: =IF($A51>NYears,"",'Engine B'!$K64) | J51: =IF($A51>NYears,"",'Engine B'!$P64) | K51: =IF($A51>NYears,"",'Engine B'!$Q64) | L51: =IF($A51>NYears,"",'Engine B'!$K64-'Engine B'!$P64-'Engine B'!$Q64) | M51: =IF($A51>NYears,"",'Engine B'!$R64)
A52: =6 | B52: =IF($A52>NYears,"",EDATE(StartMonth,$A52*12-1)) | C52: =IF($A52>NYears,"",'Engine B'!$E76) | D52: =IF($A52>NYears,"",'Engine B'!$F65) | E52: =IF($A52>NYears,"",'Engine B'!$G65) | F52: =IF($A52>NYears,"",'Engine B'!$S76) | G52: =IF($A52>NYears,"",'Engine B'!$S76-'Engine B'!$G65) | H52: =IF($A52>NYears,"",'Engine B'!$S76*'Engine B'!$E76) | I52: =IF($A52>NYears,"",'Engine B'!$K76) | J52: =IF($A52>NYears,"",'Engine B'!$P76) | K52: =IF($A52>NYears,"",'Engine B'!$Q76) | L52: =IF($A52>NYears,"",'Engine B'!$K76-'Engine B'!$P76-'Engine B'!$Q76) | M52: =IF($A52>NYears,"",'Engine B'!$R76)
A53: =7 | B53: =IF($A53>NYears,"",EDATE(StartMonth,$A53*12-1)) | C53: =IF($A53>NYears,"",'Engine B'!$E88) | D53: =IF($A53>NYears,"",'Engine B'!$F77) | E53: =IF($A53>NYears,"",'Engine B'!$G77) | F53: =IF($A53>NYears,"",'Engine B'!$S88) | G53: =IF($A53>NYears,"",'Engine B'!$S88-'Engine B'!$G77) | H53: =IF($A53>NYears,"",'Engine B'!$S88*'Engine B'!$E88) | I53: =IF($A53>NYears,"",'Engine B'!$K88) | J53: =IF($A53>NYears,"",'Engine B'!$P88) | K53: =IF($A53>NYears,"",'Engine B'!$Q88) | L53: =IF($A53>NYears,"",'Engine B'!$K88-'Engine B'!$P88-'Engine B'!$Q88) | M53: =IF($A53>NYears,"",'Engine B'!$R88)
A54: =8 | B54: =IF($A54>NYears,"",EDATE(StartMonth,$A54*12-1)) | C54: =IF($A54>NYears,"",'Engine B'!$E100) | D54: =IF($A54>NYears,"",'Engine B'!$F89) | E54: =IF($A54>NYears,"",'Engine B'!$G89) | F54: =IF($A54>NYears,"",'Engine B'!$S100) | G54: =IF($A54>NYears,"",'Engine B'!$S100-'Engine B'!$G89) | H54: =IF($A54>NYears,"",'Engine B'!$S100*'Engine B'!$E100) | I54: =IF($A54>NYears,"",'Engine B'!$K100) | J54: =IF($A54>NYears,"",'Engine B'!$P100) | K54: =IF($A54>NYears,"",'Engine B'!$Q100) | L54: =IF($A54>NYears,"",'Engine B'!$K100-'Engine B'!$P100-'Engine B'!$Q100) | M54: =IF($A54>NYears,"",'Engine B'!$R100)
A55: =9 | B55: =IF($A55>NYears,"",EDATE(StartMonth,$A55*12-1)) | C55: =IF($A55>NYears,"",'Engine B'!$E112) | D55: =IF($A55>NYears,"",'Engine B'!$F101) | E55: =IF($A55>NYears,"",'Engine B'!$G101) | F55: =IF($A55>NYears,"",'Engine B'!$S112) | G55: =IF($A55>NYears,"",'Engine B'!$S112-'Engine B'!$G101) | H55: =IF($A55>NYears,"",'Engine B'!$S112*'Engine B'!$E112) | I55: =IF($A55>NYears,"",'Engine B'!$K112) | J55: =IF($A55>NYears,"",'Engine B'!$P112) | K55: =IF($A55>NYears,"",'Engine B'!$Q112) | L55: =IF($A55>NYears,"",'Engine B'!$K112-'Engine B'!$P112-'Engine B'!$Q112) | M55: =IF($A55>NYears,"",'Engine B'!$R112)
A56: =10 | B56: =IF($A56>NYears,"",EDATE(StartMonth,$A56*12-1)) | C56: =IF($A56>NYears,"",'Engine B'!$E124) | D56: =IF($A56>NYears,"",'Engine B'!$F113) | E56: =IF($A56>NYears,"",'Engine B'!$G113) | F56: =IF($A56>NYears,"",'Engine B'!$S124) | G56: =IF($A56>NYears,"",'Engine B'!$S124-'Engine B'!$G113) | H56: =IF($A56>NYears,"",'Engine B'!$S124*'Engine B'!$E124) | I56: =IF($A56>NYears,"",'Engine B'!$K124) | J56: =IF($A56>NYears,"",'Engine B'!$P124) | K56: =IF($A56>NYears,"",'Engine B'!$Q124) | L56: =IF($A56>NYears,"",'Engine B'!$K124-'Engine B'!$P124-'Engine B'!$Q124) | M56: =IF($A56>NYears,"",'Engine B'!$R124)
A57: =11 | B57: =IF($A57>NYears,"",EDATE(StartMonth,$A57*12-1)) | C57: =IF($A57>NYears,"",'Engine B'!$E136) | D57: =IF($A57>NYears,"",'Engine B'!$F125) | E57: =IF($A57>NYears,"",'Engine B'!$G125) | F57: =IF($A57>NYears,"",'Engine B'!$S136) | G57: =IF($A57>NYears,"",'Engine B'!$S136-'Engine B'!$G125) | H57: =IF($A57>NYears,"",'Engine B'!$S136*'Engine B'!$E136) | I57: =IF($A57>NYears,"",'Engine B'!$K136) | J57: =IF($A57>NYears,"",'Engine B'!$P136) | K57: =IF($A57>NYears,"",'Engine B'!$Q136) | L57: =IF($A57>NYears,"",'Engine B'!$K136-'Engine B'!$P136-'Engine B'!$Q136) | M57: =IF($A57>NYears,"",'Engine B'!$R136)
A58: =12 | B58: =IF($A58>NYears,"",EDATE(StartMonth,$A58*12-1)) | C58: =IF($A58>NYears,"",'Engine B'!$E148) | D58: =IF($A58>NYears,"",'Engine B'!$F137) | E58: =IF($A58>NYears,"",'Engine B'!$G137) | F58: =IF($A58>NYears,"",'Engine B'!$S148) | G58: =IF($A58>NYears,"",'Engine B'!$S148-'Engine B'!$G137) | H58: =IF($A58>NYears,"",'Engine B'!$S148*'Engine B'!$E148) | I58: =IF($A58>NYears,"",'Engine B'!$K148) | J58: =IF($A58>NYears,"",'Engine B'!$P148) | K58: =IF($A58>NYears,"",'Engine B'!$Q148) | L58: =IF($A58>NYears,"",'Engine B'!$K148-'Engine B'!$P148-'Engine B'!$Q148) | M58: =IF($A58>NYears,"",'Engine B'!$R148)
A59: =13 | B59: =IF($A59>NYears,"",EDATE(StartMonth,$A59*12-1)) | C59: =IF($A59>NYears,"",'Engine B'!$E160) | D59: =IF($A59>NYears,"",'Engine B'!$F149) | E59: =IF($A59>NYears,"",'Engine B'!$G149) | F59: =IF($A59>NYears,"",'Engine B'!$S160) | G59: =IF($A59>NYears,"",'Engine B'!$S160-'Engine B'!$G149) | H59: =IF($A59>NYears,"",'Engine B'!$S160*'Engine B'!$E160) | I59: =IF($A59>NYears,"",'Engine B'!$K160) | J59: =IF($A59>NYears,"",'Engine B'!$P160) | K59: =IF($A59>NYears,"",'Engine B'!$Q160) | L59: =IF($A59>NYears,"",'Engine B'!$K160-'Engine B'!$P160-'Engine B'!$Q160) | M59: =IF($A59>NYears,"",'Engine B'!$R160)
A60: =14 | B60: =IF($A60>NYears,"",EDATE(StartMonth,$A60*12-1)) | C60: =IF($A60>NYears,"",'Engine B'!$E172) | D60: =IF($A60>NYears,"",'Engine B'!$F161) | E60: =IF($A60>NYears,"",'Engine B'!$G161) | F60: =IF($A60>NYears,"",'Engine B'!$S172) | G60: =IF($A60>NYears,"",'Engine B'!$S172-'Engine B'!$G161) | H60: =IF($A60>NYears,"",'Engine B'!$S172*'Engine B'!$E172) | I60: =IF($A60>NYears,"",'Engine B'!$K172) | J60: =IF($A60>NYears,"",'Engine B'!$P172) | K60: =IF($A60>NYears,"",'Engine B'!$Q172) | L60: =IF($A60>NYears,"",'Engine B'!$K172-'Engine B'!$P172-'Engine B'!$Q172) | M60: =IF($A60>NYears,"",'Engine B'!$R172)
A61: =15 | B61: =IF($A61>NYears,"",EDATE(StartMonth,$A61*12-1)) | C61: =IF($A61>NYears,"",'Engine B'!$E184) | D61: =IF($A61>NYears,"",'Engine B'!$F173) | E61: =IF($A61>NYears,"",'Engine B'!$G173) | F61: =IF($A61>NYears,"",'Engine B'!$S184) | G61: =IF($A61>NYears,"",'Engine B'!$S184-'Engine B'!$G173) | H61: =IF($A61>NYears,"",'Engine B'!$S184*'Engine B'!$E184) | I61: =IF($A61>NYears,"",'Engine B'!$K184) | J61: =IF($A61>NYears,"",'Engine B'!$P184) | K61: =IF($A61>NYears,"",'Engine B'!$Q184) | L61: =IF($A61>NYears,"",'Engine B'!$K184-'Engine B'!$P184-'Engine B'!$Q184) | M61: =IF($A61>NYears,"",'Engine B'!$R184)
A62: =16 | B62: =IF($A62>NYears,"",EDATE(StartMonth,$A62*12-1)) | C62: =IF($A62>NYears,"",'Engine B'!$E196) | D62: =IF($A62>NYears,"",'Engine B'!$F185) | E62: =IF($A62>NYears,"",'Engine B'!$G185) | F62: =IF($A62>NYears,"",'Engine B'!$S196) | G62: =IF($A62>NYears,"",'Engine B'!$S196-'Engine B'!$G185) | H62: =IF($A62>NYears,"",'Engine B'!$S196*'Engine B'!$E196) | I62: =IF($A62>NYears,"",'Engine B'!$K196) | J62: =IF($A62>NYears,"",'Engine B'!$P196) | K62: =IF($A62>NYears,"",'Engine B'!$Q196) | L62: =IF($A62>NYears,"",'Engine B'!$K196-'Engine B'!$P196-'Engine B'!$Q196) | M62: =IF($A62>NYears,"",'Engine B'!$R196)
A63: =17 | B63: =IF($A63>NYears,"",EDATE(StartMonth,$A63*12-1)) | C63: =IF($A63>NYears,"",'Engine B'!$E208) | D63: =IF($A63>NYears,"",'Engine B'!$F197) | E63: =IF($A63>NYears,"",'Engine B'!$G197) | F63: =IF($A63>NYears,"",'Engine B'!$S208) | G63: =IF($A63>NYears,"",'Engine B'!$S208-'Engine B'!$G197) | H63: =IF($A63>NYears,"",'Engine B'!$S208*'Engine B'!$E208) | I63: =IF($A63>NYears,"",'Engine B'!$K208) | J63: =IF($A63>NYears,"",'Engine B'!$P208) | K63: =IF($A63>NYears,"",'Engine B'!$Q208) | L63: =IF($A63>NYears,"",'Engine B'!$K208-'Engine B'!$P208-'Engine B'!$Q208) | M63: =IF($A63>NYears,"",'Engine B'!$R208)
A64: =18 | B64: =IF($A64>NYears,"",EDATE(StartMonth,$A64*12-1)) | C64: =IF($A64>NYears,"",'Engine B'!$E220) | D64: =IF($A64>NYears,"",'Engine B'!$F209) | E64: =IF($A64>NYears,"",'Engine B'!$G209) | F64: =IF($A64>NYears,"",'Engine B'!$S220) | G64: =IF($A64>NYears,"",'Engine B'!$S220-'Engine B'!$G209) | H64: =IF($A64>NYears,"",'Engine B'!$S220*'Engine B'!$E220) | I64: =IF($A64>NYears,"",'Engine B'!$K220) | J64: =IF($A64>NYears,"",'Engine B'!$P220) | K64: =IF($A64>NYears,"",'Engine B'!$Q220) | L64: =IF($A64>NYears,"",'Engine B'!$K220-'Engine B'!$P220-'Engine B'!$Q220) | M64: =IF($A64>NYears,"",'Engine B'!$R220)
A65: =19 | B65: =IF($A65>NYears,"",EDATE(StartMonth,$A65*12-1)) | C65: =IF($A65>NYears,"",'Engine B'!$E232) | D65: =IF($A65>NYears,"",'Engine B'!$F221) | E65: =IF($A65>NYears,"",'Engine B'!$G221) | F65: =IF($A65>NYears,"",'Engine B'!$S232) | G65: =IF($A65>NYears,"",'Engine B'!$S232-'Engine B'!$G221) | H65: =IF($A65>NYears,"",'Engine B'!$S232*'Engine B'!$E232) | I65: =IF($A65>NYears,"",'Engine B'!$K232) | J65: =IF($A65>NYears,"",'Engine B'!$P232) | K65: =IF($A65>NYears,"",'Engine B'!$Q232) | L65: =IF($A65>NYears,"",'Engine B'!$K232-'Engine B'!$P232-'Engine B'!$Q232) | M65: =IF($A65>NYears,"",'Engine B'!$R232)
A66: =20 | B66: =IF($A66>NYears,"",EDATE(StartMonth,$A66*12-1)) | C66: =IF($A66>NYears,"",'Engine B'!$E244) | D66: =IF($A66>NYears,"",'Engine B'!$F233) | E66: =IF($A66>NYears,"",'Engine B'!$G233) | F66: =IF($A66>NYears,"",'Engine B'!$S244) | G66: =IF($A66>NYears,"",'Engine B'!$S244-'Engine B'!$G233) | H66: =IF($A66>NYears,"",'Engine B'!$S244*'Engine B'!$E244) | I66: =IF($A66>NYears,"",'Engine B'!$K244) | J66: =IF($A66>NYears,"",'Engine B'!$P244) | K66: =IF($A66>NYears,"",'Engine B'!$Q244) | L66: =IF($A66>NYears,"",'Engine B'!$K244-'Engine B'!$P244-'Engine B'!$Q244) | M66: =IF($A66>NYears,"",'Engine B'!$R244)
A67: =21 | B67: =IF($A67>NYears,"",EDATE(StartMonth,$A67*12-1)) | C67: =IF($A67>NYears,"",'Engine B'!$E256) | D67: =IF($A67>NYears,"",'Engine B'!$F245) | E67: =IF($A67>NYears,"",'Engine B'!$G245) | F67: =IF($A67>NYears,"",'Engine B'!$S256) | G67: =IF($A67>NYears,"",'Engine B'!$S256-'Engine B'!$G245) | H67: =IF($A67>NYears,"",'Engine B'!$S256*'Engine B'!$E256) | I67: =IF($A67>NYears,"",'Engine B'!$K256) | J67: =IF($A67>NYears,"",'Engine B'!$P256) | K67: =IF($A67>NYears,"",'Engine B'!$Q256) | L67: =IF($A67>NYears,"",'Engine B'!$K256-'Engine B'!$P256-'Engine B'!$Q256) | M67: =IF($A67>NYears,"",'Engine B'!$R256)
A68: =22 | B68: =IF($A68>NYears,"",EDATE(StartMonth,$A68*12-1)) | C68: =IF($A68>NYears,"",'Engine B'!$E268) | D68: =IF($A68>NYears,"",'Engine B'!$F257) | E68: =IF($A68>NYears,"",'Engine B'!$G257) | F68: =IF($A68>NYears,"",'Engine B'!$S268) | G68: =IF($A68>NYears,"",'Engine B'!$S268-'Engine B'!$G257) | H68: =IF($A68>NYears,"",'Engine B'!$S268*'Engine B'!$E268) | I68: =IF($A68>NYears,"",'Engine B'!$K268) | J68: =IF($A68>NYears,"",'Engine B'!$P268) | K68: =IF($A68>NYears,"",'Engine B'!$Q268) | L68: =IF($A68>NYears,"",'Engine B'!$K268-'Engine B'!$P268-'Engine B'!$Q268) | M68: =IF($A68>NYears,"",'Engine B'!$R268)
A69: =23 | B69: =IF($A69>NYears,"",EDATE(StartMonth,$A69*12-1)) | C69: =IF($A69>NYears,"",'Engine B'!$E280) | D69: =IF($A69>NYears,"",'Engine B'!$F269) | E69: =IF($A69>NYears,"",'Engine B'!$G269) | F69: =IF($A69>NYears,"",'Engine B'!$S280) | G69: =IF($A69>NYears,"",'Engine B'!$S280-'Engine B'!$G269) | H69: =IF($A69>NYears,"",'Engine B'!$S280*'Engine B'!$E280) | I69: =IF($A69>NYears,"",'Engine B'!$K280) | J69: =IF($A69>NYears,"",'Engine B'!$P280) | K69: =IF($A69>NYears,"",'Engine B'!$Q280) | L69: =IF($A69>NYears,"",'Engine B'!$K280-'Engine B'!$P280-'Engine B'!$Q280) | M69: =IF($A69>NYears,"",'Engine B'!$R280)
A70: =24 | B70: =IF($A70>NYears,"",EDATE(StartMonth,$A70*12-1)) | C70: =IF($A70>NYears,"",'Engine B'!$E292) | D70: =IF($A70>NYears,"",'Engine B'!$F281) | E70: =IF($A70>NYears,"",'Engine B'!$G281) | F70: =IF($A70>NYears,"",'Engine B'!$S292) | G70: =IF($A70>NYears,"",'Engine B'!$S292-'Engine B'!$G281) | H70: =IF($A70>NYears,"",'Engine B'!$S292*'Engine B'!$E292) | I70: =IF($A70>NYears,"",'Engine B'!$K292) | J70: =IF($A70>NYears,"",'Engine B'!$P292) | K70: =IF($A70>NYears,"",'Engine B'!$Q292) | L70: =IF($A70>NYears,"",'Engine B'!$K292-'Engine B'!$P292-'Engine B'!$Q292) | M70: =IF($A70>NYears,"",'Engine B'!$R292)
A71: =25 | B71: =IF($A71>NYears,"",EDATE(StartMonth,$A71*12-1)) | C71: =IF($A71>NYears,"",'Engine B'!$E304) | D71: =IF($A71>NYears,"",'Engine B'!$F293) | E71: =IF($A71>NYears,"",'Engine B'!$G293) | F71: =IF($A71>NYears,"",'Engine B'!$S304) | G71: =IF($A71>NYears,"",'Engine B'!$S304-'Engine B'!$G293) | H71: =IF($A71>NYears,"",'Engine B'!$S304*'Engine B'!$E304) | I71: =IF($A71>NYears,"",'Engine B'!$K304) | J71: =IF($A71>NYears,"",'Engine B'!$P304) | K71: =IF($A71>NYears,"",'Engine B'!$Q304) | L71: =IF($A71>NYears,"",'Engine B'!$K304-'Engine B'!$P304-'Engine B'!$Q304) | M71: =IF($A71>NYears,"",'Engine B'!$R304)
A72: =26 | B72: =IF($A72>NYears,"",EDATE(StartMonth,$A72*12-1)) | C72: =IF($A72>NYears,"",'Engine B'!$E316) | D72: =IF($A72>NYears,"",'Engine B'!$F305) | E72: =IF($A72>NYears,"",'Engine B'!$G305) | F72: =IF($A72>NYears,"",'Engine B'!$S316) | G72: =IF($A72>NYears,"",'Engine B'!$S316-'Engine B'!$G305) | H72: =IF($A72>NYears,"",'Engine B'!$S316*'Engine B'!$E316) | I72: =IF($A72>NYears,"",'Engine B'!$K316) | J72: =IF($A72>NYears,"",'Engine B'!$P316) | K72: =IF($A72>NYears,"",'Engine B'!$Q316) | L72: =IF($A72>NYears,"",'Engine B'!$K316-'Engine B'!$P316-'Engine B'!$Q316) | M72: =IF($A72>NYears,"",'Engine B'!$R316)
A73: =27 | B73: =IF($A73>NYears,"",EDATE(StartMonth,$A73*12-1)) | C73: =IF($A73>NYears,"",'Engine B'!$E328) | D73: =IF($A73>NYears,"",'Engine B'!$F317) | E73: =IF($A73>NYears,"",'Engine B'!$G317) | F73: =IF($A73>NYears,"",'Engine B'!$S328) | G73: =IF($A73>NYears,"",'Engine B'!$S328-'Engine B'!$G317) | H73: =IF($A73>NYears,"",'Engine B'!$S328*'Engine B'!$E328) | I73: =IF($A73>NYears,"",'Engine B'!$K328) | J73: =IF($A73>NYears,"",'Engine B'!$P328) | K73: =IF($A73>NYears,"",'Engine B'!$Q328) | L73: =IF($A73>NYears,"",'Engine B'!$K328-'Engine B'!$P328-'Engine B'!$Q328) | M73: =IF($A73>NYears,"",'Engine B'!$R328)
A74: =28 | B74: =IF($A74>NYears,"",EDATE(StartMonth,$A74*12-1)) | C74: =IF($A74>NYears,"",'Engine B'!$E340) | D74: =IF($A74>NYears,"",'Engine B'!$F329) | E74: =IF($A74>NYears,"",'Engine B'!$G329) | F74: =IF($A74>NYears,"",'Engine B'!$S340) | G74: =IF($A74>NYears,"",'Engine B'!$S340-'Engine B'!$G329) | H74: =IF($A74>NYears,"",'Engine B'!$S340*'Engine B'!$E340) | I74: =IF($A74>NYears,"",'Engine B'!$K340) | J74: =IF($A74>NYears,"",'Engine B'!$P340) | K74: =IF($A74>NYears,"",'Engine B'!$Q340) | L74: =IF($A74>NYears,"",'Engine B'!$K340-'Engine B'!$P340-'Engine B'!$Q340) | M74: =IF($A74>NYears,"",'Engine B'!$R340)
A75: =29 | B75: =IF($A75>NYears,"",EDATE(StartMonth,$A75*12-1)) | C75: =IF($A75>NYears,"",'Engine B'!$E352) | D75: =IF($A75>NYears,"",'Engine B'!$F341) | E75: =IF($A75>NYears,"",'Engine B'!$G341) | F75: =IF($A75>NYears,"",'Engine B'!$S352) | G75: =IF($A75>NYears,"",'Engine B'!$S352-'Engine B'!$G341) | H75: =IF($A75>NYears,"",'Engine B'!$S352*'Engine B'!$E352) | I75: =IF($A75>NYears,"",'Engine B'!$K352) | J75: =IF($A75>NYears,"",'Engine B'!$P352) | K75: =IF($A75>NYears,"",'Engine B'!$Q352) | L75: =IF($A75>NYears,"",'Engine B'!$K352-'Engine B'!$P352-'Engine B'!$Q352) | M75: =IF($A75>NYears,"",'Engine B'!$R352)
A76: =30 | B76: =IF($A76>NYears,"",EDATE(StartMonth,$A76*12-1)) | C76: =IF($A76>NYears,"",'Engine B'!$E364) | D76: =IF($A76>NYears,"",'Engine B'!$F353) | E76: =IF($A76>NYears,"",'Engine B'!$G353) | F76: =IF($A76>NYears,"",'Engine B'!$S364) | G76: =IF($A76>NYears,"",'Engine B'!$S364-'Engine B'!$G353) | H76: =IF($A76>NYears,"",'Engine B'!$S364*'Engine B'!$E364) | I76: =IF($A76>NYears,"",'Engine B'!$K364) | J76: =IF($A76>NYears,"",'Engine B'!$P364) | K76: =IF($A76>NYears,"",'Engine B'!$Q364) | L76: =IF($A76>NYears,"",'Engine B'!$K364-'Engine B'!$P364-'Engine B'!$Q364) | M76: =IF($A76>NYears,"",'Engine B'!$R364)
A78: SCENARIO C | B78: =RateC | C78: per month
A79: Year | B79: Year ending | C79: Lot value | D79: Opening corpus | E79: Lots start | F79: Lots end | G79: Lots added | H79: Deployed capital | I79: TRADING PROFIT (net of charges, pre-tax) | J79: Govt tax | K79: Withdrawal | L79: REAL PROFIT (post tax & withdrawal) | M79: Closing corpus
A80: =1 | B80: =IF($A80>NYears,"",EDATE(StartMonth,$A80*12-1)) | C80: =IF($A80>NYears,"",'Engine C'!$E16) | D80: =IF($A80>NYears,"",'Engine C'!$F5) | E80: =IF($A80>NYears,"",'Engine C'!$G5) | F80: =IF($A80>NYears,"",'Engine C'!$S16) | G80: =IF($A80>NYears,"",'Engine C'!$S16-'Engine C'!$G5) | H80: =IF($A80>NYears,"",'Engine C'!$S16*'Engine C'!$E16) | I80: =IF($A80>NYears,"",'Engine C'!$K16) | J80: =IF($A80>NYears,"",'Engine C'!$P16) | K80: =IF($A80>NYears,"",'Engine C'!$Q16) | L80: =IF($A80>NYears,"",'Engine C'!$K16-'Engine C'!$P16-'Engine C'!$Q16) | M80: =IF($A80>NYears,"",'Engine C'!$R16)
A81: =2 | B81: =IF($A81>NYears,"",EDATE(StartMonth,$A81*12-1)) | C81: =IF($A81>NYears,"",'Engine C'!$E28) | D81: =IF($A81>NYears,"",'Engine C'!$F17) | E81: =IF($A81>NYears,"",'Engine C'!$G17) | F81: =IF($A81>NYears,"",'Engine C'!$S28) | G81: =IF($A81>NYears,"",'Engine C'!$S28-'Engine C'!$G17) | H81: =IF($A81>NYears,"",'Engine C'!$S28*'Engine C'!$E28) | I81: =IF($A81>NYears,"",'Engine C'!$K28) | J81: =IF($A81>NYears,"",'Engine C'!$P28) | K81: =IF($A81>NYears,"",'Engine C'!$Q28) | L81: =IF($A81>NYears,"",'Engine C'!$K28-'Engine C'!$P28-'Engine C'!$Q28) | M81: =IF($A81>NYears,"",'Engine C'!$R28)
A82: =3 | B82: =IF($A82>NYears,"",EDATE(StartMonth,$A82*12-1)) | C82: =IF($A82>NYears,"",'Engine C'!$E40) | D82: =IF($A82>NYears,"",'Engine C'!$F29) | E82: =IF($A82>NYears,"",'Engine C'!$G29) | F82: =IF($A82>NYears,"",'Engine C'!$S40) | G82: =IF($A82>NYears,"",'Engine C'!$S40-'Engine C'!$G29) | H82: =IF($A82>NYears,"",'Engine C'!$S40*'Engine C'!$E40) | I82: =IF($A82>NYears,"",'Engine C'!$K40) | J82: =IF($A82>NYears,"",'Engine C'!$P40) | K82: =IF($A82>NYears,"",'Engine C'!$Q40) | L82: =IF($A82>NYears,"",'Engine C'!$K40-'Engine C'!$P40-'Engine C'!$Q40) | M82: =IF($A82>NYears,"",'Engine C'!$R40)
A83: =4 | B83: =IF($A83>NYears,"",EDATE(StartMonth,$A83*12-1)) | C83: =IF($A83>NYears,"",'Engine C'!$E52) | D83: =IF($A83>NYears,"",'Engine C'!$F41) | E83: =IF($A83>NYears,"",'Engine C'!$G41) | F83: =IF($A83>NYears,"",'Engine C'!$S52) | G83: =IF($A83>NYears,"",'Engine C'!$S52-'Engine C'!$G41) | H83: =IF($A83>NYears,"",'Engine C'!$S52*'Engine C'!$E52) | I83: =IF($A83>NYears,"",'Engine C'!$K52) | J83: =IF($A83>NYears,"",'Engine C'!$P52) | K83: =IF($A83>NYears,"",'Engine C'!$Q52) | L83: =IF($A83>NYears,"",'Engine C'!$K52-'Engine C'!$P52-'Engine C'!$Q52) | M83: =IF($A83>NYears,"",'Engine C'!$R52)
A84: =5 | B84: =IF($A84>NYears,"",EDATE(StartMonth,$A84*12-1)) | C84: =IF($A84>NYears,"",'Engine C'!$E64) | D84: =IF($A84>NYears,"",'Engine C'!$F53) | E84: =IF($A84>NYears,"",'Engine C'!$G53) | F84: =IF($A84>NYears,"",'Engine C'!$S64) | G84: =IF($A84>NYears,"",'Engine C'!$S64-'Engine C'!$G53) | H84: =IF($A84>NYears,"",'Engine C'!$S64*'Engine C'!$E64) | I84: =IF($A84>NYears,"",'Engine C'!$K64) | J84: =IF($A84>NYears,"",'Engine C'!$P64) | K84: =IF($A84>NYears,"",'Engine C'!$Q64) | L84: =IF($A84>NYears,"",'Engine C'!$K64-'Engine C'!$P64-'Engine C'!$Q64) | M84: =IF($A84>NYears,"",'Engine C'!$R64)
A85: =6 | B85: =IF($A85>NYears,"",EDATE(StartMonth,$A85*12-1)) | C85: =IF($A85>NYears,"",'Engine C'!$E76) | D85: =IF($A85>NYears,"",'Engine C'!$F65) | E85: =IF($A85>NYears,"",'Engine C'!$G65) | F85: =IF($A85>NYears,"",'Engine C'!$S76) | G85: =IF($A85>NYears,"",'Engine C'!$S76-'Engine C'!$G65) | H85: =IF($A85>NYears,"",'Engine C'!$S76*'Engine C'!$E76) | I85: =IF($A85>NYears,"",'Engine C'!$K76) | J85: =IF($A85>NYears,"",'Engine C'!$P76) | K85: =IF($A85>NYears,"",'Engine C'!$Q76) | L85: =IF($A85>NYears,"",'Engine C'!$K76-'Engine C'!$P76-'Engine C'!$Q76) | M85: =IF($A85>NYears,"",'Engine C'!$R76)
A86: =7 | B86: =IF($A86>NYears,"",EDATE(StartMonth,$A86*12-1)) | C86: =IF($A86>NYears,"",'Engine C'!$E88) | D86: =IF($A86>NYears,"",'Engine C'!$F77) | E86: =IF($A86>NYears,"",'Engine C'!$G77) | F86: =IF($A86>NYears,"",'Engine C'!$S88) | G86: =IF($A86>NYears,"",'Engine C'!$S88-'Engine C'!$G77) | H86: =IF($A86>NYears,"",'Engine C'!$S88*'Engine C'!$E88) | I86: =IF($A86>NYears,"",'Engine C'!$K88) | J86: =IF($A86>NYears,"",'Engine C'!$P88) | K86: =IF($A86>NYears,"",'Engine C'!$Q88) | L86: =IF($A86>NYears,"",'Engine C'!$K88-'Engine C'!$P88-'Engine C'!$Q88) | M86: =IF($A86>NYears,"",'Engine C'!$R88)
A87: =8 | B87: =IF($A87>NYears,"",EDATE(StartMonth,$A87*12-1)) | C87: =IF($A87>NYears,"",'Engine C'!$E100) | D87: =IF($A87>NYears,"",'Engine C'!$F89) | E87: =IF($A87>NYears,"",'Engine C'!$G89) | F87: =IF($A87>NYears,"",'Engine C'!$S100) | G87: =IF($A87>NYears,"",'Engine C'!$S100-'Engine C'!$G89) | H87: =IF($A87>NYears,"",'Engine C'!$S100*'Engine C'!$E100) | I87: =IF($A87>NYears,"",'Engine C'!$K100) | J87: =IF($A87>NYears,"",'Engine C'!$P100) | K87: =IF($A87>NYears,"",'Engine C'!$Q100) | L87: =IF($A87>NYears,"",'Engine C'!$K100-'Engine C'!$P100-'Engine C'!$Q100) | M87: =IF($A87>NYears,"",'Engine C'!$R100)
A88: =9 | B88: =IF($A88>NYears,"",EDATE(StartMonth,$A88*12-1)) | C88: =IF($A88>NYears,"",'Engine C'!$E112) | D88: =IF($A88>NYears,"",'Engine C'!$F101) | E88: =IF($A88>NYears,"",'Engine C'!$G101) | F88: =IF($A88>NYears,"",'Engine C'!$S112) | G88: =IF($A88>NYears,"",'Engine C'!$S112-'Engine C'!$G101) | H88: =IF($A88>NYears,"",'Engine C'!$S112*'Engine C'!$E112) | I88: =IF($A88>NYears,"",'Engine C'!$K112) | J88: =IF($A88>NYears,"",'Engine C'!$P112) | K88: =IF($A88>NYears,"",'Engine C'!$Q112) | L88: =IF($A88>NYears,"",'Engine C'!$K112-'Engine C'!$P112-'Engine C'!$Q112) | M88: =IF($A88>NYears,"",'Engine C'!$R112)
A89: =10 | B89: =IF($A89>NYears,"",EDATE(StartMonth,$A89*12-1)) | C89: =IF($A89>NYears,"",'Engine C'!$E124) | D89: =IF($A89>NYears,"",'Engine C'!$F113) | E89: =IF($A89>NYears,"",'Engine C'!$G113) | F89: =IF($A89>NYears,"",'Engine C'!$S124) | G89: =IF($A89>NYears,"",'Engine C'!$S124-'Engine C'!$G113) | H89: =IF($A89>NYears,"",'Engine C'!$S124*'Engine C'!$E124) | I89: =IF($A89>NYears,"",'Engine C'!$K124) | J89: =IF($A89>NYears,"",'Engine C'!$P124) | K89: =IF($A89>NYears,"",'Engine C'!$Q124) | L89: =IF($A89>NYears,"",'Engine C'!$K124-'Engine C'!$P124-'Engine C'!$Q124) | M89: =IF($A89>NYears,"",'Engine C'!$R124)
A90: =11 | B90: =IF($A90>NYears,"",EDATE(StartMonth,$A90*12-1)) | C90: =IF($A90>NYears,"",'Engine C'!$E136) | D90: =IF($A90>NYears,"",'Engine C'!$F125) | E90: =IF($A90>NYears,"",'Engine C'!$G125) | F90: =IF($A90>NYears,"",'Engine C'!$S136) | G90: =IF($A90>NYears,"",'Engine C'!$S136-'Engine C'!$G125) | H90: =IF($A90>NYears,"",'Engine C'!$S136*'Engine C'!$E136) | I90: =IF($A90>NYears,"",'Engine C'!$K136) | J90: =IF($A90>NYears,"",'Engine C'!$P136) | K90: =IF($A90>NYears,"",'Engine C'!$Q136) | L90: =IF($A90>NYears,"",'Engine C'!$K136-'Engine C'!$P136-'Engine C'!$Q136) | M90: =IF($A90>NYears,"",'Engine C'!$R136)
A91: =12 | B91: =IF($A91>NYears,"",EDATE(StartMonth,$A91*12-1)) | C91: =IF($A91>NYears,"",'Engine C'!$E148) | D91: =IF($A91>NYears,"",'Engine C'!$F137) | E91: =IF($A91>NYears,"",'Engine C'!$G137) | F91: =IF($A91>NYears,"",'Engine C'!$S148) | G91: =IF($A91>NYears,"",'Engine C'!$S148-'Engine C'!$G137) | H91: =IF($A91>NYears,"",'Engine C'!$S148*'Engine C'!$E148) | I91: =IF($A91>NYears,"",'Engine C'!$K148) | J91: =IF($A91>NYears,"",'Engine C'!$P148) | K91: =IF($A91>NYears,"",'Engine C'!$Q148) | L91: =IF($A91>NYears,"",'Engine C'!$K148-'Engine C'!$P148-'Engine C'!$Q148) | M91: =IF($A91>NYears,"",'Engine C'!$R148)
A92: =13 | B92: =IF($A92>NYears,"",EDATE(StartMonth,$A92*12-1)) | C92: =IF($A92>NYears,"",'Engine C'!$E160) | D92: =IF($A92>NYears,"",'Engine C'!$F149) | E92: =IF($A92>NYears,"",'Engine C'!$G149) | F92: =IF($A92>NYears,"",'Engine C'!$S160) | G92: =IF($A92>NYears,"",'Engine C'!$S160-'Engine C'!$G149) | H92: =IF($A92>NYears,"",'Engine C'!$S160*'Engine C'!$E160) | I92: =IF($A92>NYears,"",'Engine C'!$K160) | J92: =IF($A92>NYears,"",'Engine C'!$P160) | K92: =IF($A92>NYears,"",'Engine C'!$Q160) | L92: =IF($A92>NYears,"",'Engine C'!$K160-'Engine C'!$P160-'Engine C'!$Q160) | M92: =IF($A92>NYears,"",'Engine C'!$R160)
A93: =14 | B93: =IF($A93>NYears,"",EDATE(StartMonth,$A93*12-1)) | C93: =IF($A93>NYears,"",'Engine C'!$E172) | D93: =IF($A93>NYears,"",'Engine C'!$F161) | E93: =IF($A93>NYears,"",'Engine C'!$G161) | F93: =IF($A93>NYears,"",'Engine C'!$S172) | G93: =IF($A93>NYears,"",'Engine C'!$S172-'Engine C'!$G161) | H93: =IF($A93>NYears,"",'Engine C'!$S172*'Engine C'!$E172) | I93: =IF($A93>NYears,"",'Engine C'!$K172) | J93: =IF($A93>NYears,"",'Engine C'!$P172) | K93: =IF($A93>NYears,"",'Engine C'!$Q172) | L93: =IF($A93>NYears,"",'Engine C'!$K172-'Engine C'!$P172-'Engine C'!$Q172) | M93: =IF($A93>NYears,"",'Engine C'!$R172)
A94: =15 | B94: =IF($A94>NYears,"",EDATE(StartMonth,$A94*12-1)) | C94: =IF($A94>NYears,"",'Engine C'!$E184) | D94: =IF($A94>NYears,"",'Engine C'!$F173) | E94: =IF($A94>NYears,"",'Engine C'!$G173) | F94: =IF($A94>NYears,"",'Engine C'!$S184) | G94: =IF($A94>NYears,"",'Engine C'!$S184-'Engine C'!$G173) | H94: =IF($A94>NYears,"",'Engine C'!$S184*'Engine C'!$E184) | I94: =IF($A94>NYears,"",'Engine C'!$K184) | J94: =IF($A94>NYears,"",'Engine C'!$P184) | K94: =IF($A94>NYears,"",'Engine C'!$Q184) | L94: =IF($A94>NYears,"",'Engine C'!$K184-'Engine C'!$P184-'Engine C'!$Q184) | M94: =IF($A94>NYears,"",'Engine C'!$R184)
A95: =16 | B95: =IF($A95>NYears,"",EDATE(StartMonth,$A95*12-1)) | C95: =IF($A95>NYears,"",'Engine C'!$E196) | D95: =IF($A95>NYears,"",'Engine C'!$F185) | E95: =IF($A95>NYears,"",'Engine C'!$G185) | F95: =IF($A95>NYears,"",'Engine C'!$S196) | G95: =IF($A95>NYears,"",'Engine C'!$S196-'Engine C'!$G185) | H95: =IF($A95>NYears,"",'Engine C'!$S196*'Engine C'!$E196) | I95: =IF($A95>NYears,"",'Engine C'!$K196) | J95: =IF($A95>NYears,"",'Engine C'!$P196) | K95: =IF($A95>NYears,"",'Engine C'!$Q196) | L95: =IF($A95>NYears,"",'Engine C'!$K196-'Engine C'!$P196-'Engine C'!$Q196) | M95: =IF($A95>NYears,"",'Engine C'!$R196)
A96: =17 | B96: =IF($A96>NYears,"",EDATE(StartMonth,$A96*12-1)) | C96: =IF($A96>NYears,"",'Engine C'!$E208) | D96: =IF($A96>NYears,"",'Engine C'!$F197) | E96: =IF($A96>NYears,"",'Engine C'!$G197) | F96: =IF($A96>NYears,"",'Engine C'!$S208) | G96: =IF($A96>NYears,"",'Engine C'!$S208-'Engine C'!$G197) | H96: =IF($A96>NYears,"",'Engine C'!$S208*'Engine C'!$E208) | I96: =IF($A96>NYears,"",'Engine C'!$K208) | J96: =IF($A96>NYears,"",'Engine C'!$P208) | K96: =IF($A96>NYears,"",'Engine C'!$Q208) | L96: =IF($A96>NYears,"",'Engine C'!$K208-'Engine C'!$P208-'Engine C'!$Q208) | M96: =IF($A96>NYears,"",'Engine C'!$R208)
A97: =18 | B97: =IF($A97>NYears,"",EDATE(StartMonth,$A97*12-1)) | C97: =IF($A97>NYears,"",'Engine C'!$E220) | D97: =IF($A97>NYears,"",'Engine C'!$F209) | E97: =IF($A97>NYears,"",'Engine C'!$G209) | F97: =IF($A97>NYears,"",'Engine C'!$S220) | G97: =IF($A97>NYears,"",'Engine C'!$S220-'Engine C'!$G209) | H97: =IF($A97>NYears,"",'Engine C'!$S220*'Engine C'!$E220) | I97: =IF($A97>NYears,"",'Engine C'!$K220) | J97: =IF($A97>NYears,"",'Engine C'!$P220) | K97: =IF($A97>NYears,"",'Engine C'!$Q220) | L97: =IF($A97>NYears,"",'Engine C'!$K220-'Engine C'!$P220-'Engine C'!$Q220) | M97: =IF($A97>NYears,"",'Engine C'!$R220)
A98: =19 | B98: =IF($A98>NYears,"",EDATE(StartMonth,$A98*12-1)) | C98: =IF($A98>NYears,"",'Engine C'!$E232) | D98: =IF($A98>NYears,"",'Engine C'!$F221) | E98: =IF($A98>NYears,"",'Engine C'!$G221) | F98: =IF($A98>NYears,"",'Engine C'!$S232) | G98: =IF($A98>NYears,"",'Engine C'!$S232-'Engine C'!$G221) | H98: =IF($A98>NYears,"",'Engine C'!$S232*'Engine C'!$E232) | I98: =IF($A98>NYears,"",'Engine C'!$K232) | J98: =IF($A98>NYears,"",'Engine C'!$P232) | K98: =IF($A98>NYears,"",'Engine C'!$Q232) | L98: =IF($A98>NYears,"",'Engine C'!$K232-'Engine C'!$P232-'Engine C'!$Q232) | M98: =IF($A98>NYears,"",'Engine C'!$R232)
A99: =20 | B99: =IF($A99>NYears,"",EDATE(StartMonth,$A99*12-1)) | C99: =IF($A99>NYears,"",'Engine C'!$E244) | D99: =IF($A99>NYears,"",'Engine C'!$F233) | E99: =IF($A99>NYears,"",'Engine C'!$G233) | F99: =IF($A99>NYears,"",'Engine C'!$S244) | G99: =IF($A99>NYears,"",'Engine C'!$S244-'Engine C'!$G233) | H99: =IF($A99>NYears,"",'Engine C'!$S244*'Engine C'!$E244) | I99: =IF($A99>NYears,"",'Engine C'!$K244) | J99: =IF($A99>NYears,"",'Engine C'!$P244) | K99: =IF($A99>NYears,"",'Engine C'!$Q244) | L99: =IF($A99>NYears,"",'Engine C'!$K244-'Engine C'!$P244-'Engine C'!$Q244) | M99: =IF($A99>NYears,"",'Engine C'!$R244)
A100: =21 | B100: =IF($A100>NYears,"",EDATE(StartMonth,$A100*12-1)) | C100: =IF($A100>NYears,"",'Engine C'!$E256) | D100: =IF($A100>NYears,"",'Engine C'!$F245) | E100: =IF($A100>NYears,"",'Engine C'!$G245) | F100: =IF($A100>NYears,"",'Engine C'!$S256) | G100: =IF($A100>NYears,"",'Engine C'!$S256-'Engine C'!$G245) | H100: =IF($A100>NYears,"",'Engine C'!$S256*'Engine C'!$E256) | I100: =IF($A100>NYears,"",'Engine C'!$K256) | J100: =IF($A100>NYears,"",'Engine C'!$P256) | K100: =IF($A100>NYears,"",'Engine C'!$Q256) | L100: =IF($A100>NYears,"",'Engine C'!$K256-'Engine C'!$P256-'Engine C'!$Q256) | M100: =IF($A100>NYears,"",'Engine C'!$R256)
A101: =22 | B101: =IF($A101>NYears,"",EDATE(StartMonth,$A101*12-1)) | C101: =IF($A101>NYears,"",'Engine C'!$E268) | D101: =IF($A101>NYears,"",'Engine C'!$F257) | E101: =IF($A101>NYears,"",'Engine C'!$G257) | F101: =IF($A101>NYears,"",'Engine C'!$S268) | G101: =IF($A101>NYears,"",'Engine C'!$S268-'Engine C'!$G257) | H101: =IF($A101>NYears,"",'Engine C'!$S268*'Engine C'!$E268) | I101: =IF($A101>NYears,"",'Engine C'!$K268) | J101: =IF($A101>NYears,"",'Engine C'!$P268) | K101: =IF($A101>NYears,"",'Engine C'!$Q268) | L101: =IF($A101>NYears,"",'Engine C'!$K268-'Engine C'!$P268-'Engine C'!$Q268) | M101: =IF($A101>NYears,"",'Engine C'!$R268)
A102: =23 | B102: =IF($A102>NYears,"",EDATE(StartMonth,$A102*12-1)) | C102: =IF($A102>NYears,"",'Engine C'!$E280) | D102: =IF($A102>NYears,"",'Engine C'!$F269) | E102: =IF($A102>NYears,"",'Engine C'!$G269) | F102: =IF($A102>NYears,"",'Engine C'!$S280) | G102: =IF($A102>NYears,"",'Engine C'!$S280-'Engine C'!$G269) | H102: =IF($A102>NYears,"",'Engine C'!$S280*'Engine C'!$E280) | I102: =IF($A102>NYears,"",'Engine C'!$K280) | J102: =IF($A102>NYears,"",'Engine C'!$P280) | K102: =IF($A102>NYears,"",'Engine C'!$Q280) | L102: =IF($A102>NYears,"",'Engine C'!$K280-'Engine C'!$P280-'Engine C'!$Q280) | M102: =IF($A102>NYears,"",'Engine C'!$R280)
A103: =24 | B103: =IF($A103>NYears,"",EDATE(StartMonth,$A103*12-1)) | C103: =IF($A103>NYears,"",'Engine C'!$E292) | D103: =IF($A103>NYears,"",'Engine C'!$F281) | E103: =IF($A103>NYears,"",'Engine C'!$G281) | F103: =IF($A103>NYears,"",'Engine C'!$S292) | G103: =IF($A103>NYears,"",'Engine C'!$S292-'Engine C'!$G281) | H103: =IF($A103>NYears,"",'Engine C'!$S292*'Engine C'!$E292) | I103: =IF($A103>NYears,"",'Engine C'!$K292) | J103: =IF($A103>NYears,"",'Engine C'!$P292) | K103: =IF($A103>NYears,"",'Engine C'!$Q292) | L103: =IF($A103>NYears,"",'Engine C'!$K292-'Engine C'!$P292-'Engine C'!$Q292) | M103: =IF($A103>NYears,"",'Engine C'!$R292)
A104: =25 | B104: =IF($A104>NYears,"",EDATE(StartMonth,$A104*12-1)) | C104: =IF($A104>NYears,"",'Engine C'!$E304) | D104: =IF($A104>NYears,"",'Engine C'!$F293) | E104: =IF($A104>NYears,"",'Engine C'!$G293) | F104: =IF($A104>NYears,"",'Engine C'!$S304) | G104: =IF($A104>NYears,"",'Engine C'!$S304-'Engine C'!$G293) | H104: =IF($A104>NYears,"",'Engine C'!$S304*'Engine C'!$E304) | I104: =IF($A104>NYears,"",'Engine C'!$K304) | J104: =IF($A104>NYears,"",'Engine C'!$P304) | K104: =IF($A104>NYears,"",'Engine C'!$Q304) | L104: =IF($A104>NYears,"",'Engine C'!$K304-'Engine C'!$P304-'Engine C'!$Q304) | M104: =IF($A104>NYears,"",'Engine C'!$R304)
...

Sheet Engine A
A1: Monthly engine — Scenario A
A2: Monthly return: | B2: =RateA | D2: One row per month. Returns accrue on DEPLOYED capital only; idle cash earns nothing until it funds a whole lot.
A4: Month # | B4: Month | C4: Yr | D4: M-in-yr | E4: Lot value | F4: Opening corpus | G4: Lots | H4: Deployed capital | I4: Idle cash | J4: Profit (month) | K4: Profit YTD | L4: Profit this qtr | M4: Slab income | N4: Tax rate | O4: Tax deducted | P4: Tax YTD | Q4: Withdrawal | R4: Closing corpus | S4: Lots at close
A5: =1 | B5: =IF($A5>NYears*12,"",EDATE(StartMonth,$A5-1)) | C5: =IF($A5>NYears*12,"",INT(($A5-1)/12)+1) | D5: =IF($A5>NYears*12,"",MOD($A5-1,12)+1) | E5: =IF($A5>NYears*12,"",LotValue0*(1+LotGrowth)^($C5-1)) | F5: =IF($A5>NYears*12,"",IF($A5=1,InitInvest,$R4)) | G5: =IF($A5>NYears*12,"",INT($F5/$E5)) | H5: =IF($A5>NYears*12,"",$G5*$E5) | I5: =IF($A5>NYears*12,"",$F5-$H5) | J5: =IF($A5>NYears*12,"",$H5*RateA) | K5: =IF($A5>NYears*12,"",IF($D5=1,$J5,$K4+$J5)) | L5: =IF($A5>NYears*12,"",IF(MOD($D5,3)=0,SUM($J3:$J5),0)) | M5: =IF($A5>NYears*12,"",IF(TaxFreq="Quarterly",$K5*12/$D5,$K5)) | N5: =IF($A5>NYears*12,"",LOOKUP($M5,TaxLower,TaxRate)) | O5: =IF($A5>NYears*12,"",IF(TaxFreq="Quarterly",IF(MOD($D5,3)=0,$L5*$N5,0),IF($D5=12,$K5*$N5,0))) | P5: =IF($A5>NYears*12,"",IF($D5=1,$O5,$P4+$O5)) | Q5: =IF($A5>NYears*12,"",IF($D5=12,MIN(WdrPct*IF(WdrBase="Post-tax profit",$K5-$P5,$K5),WdrCap),0)) | R5: =IF($A5>NYears*12,"",$F5+$J5-$O5-$Q5) | S5: =IF($A5>NYears*12,"",INT($R5/$E5))
A6: =2 | B6: =IF($A6>NYears*12,"",EDATE(StartMonth,$A6-1)) | C6: =IF($A6>NYears*12,"",INT(($A6-1)/12)+1) | D6: =IF($A6>NYears*12,"",MOD($A6-1,12)+1) | E6: =IF($A6>NYears*12,"",LotValue0*(1+LotGrowth)^($C6-1)) | F6: =IF($A6>NYears*12,"",IF($A6=1,InitInvest,$R5)) | G6: =IF($A6>NYears*12,"",INT($F6/$E6)) | H6: =IF($A6>NYears*12,"",$G6*$E6) | I6: =IF($A6>NYears*12,"",$F6-$H6) | J6: =IF($A6>NYears*12,"",$H6*RateA) | K6: =IF($A6>NYears*12,"",IF($D6=1,$J6,$K5+$J6)) | L6: =IF($A6>NYears*12,"",IF(MOD($D6,3)=0,SUM($J4:$J6),0)) | M6: =IF($A6>NYears*12,"",IF(TaxFreq="Quarterly",$K6*12/$D6,$K6)) | N6: =IF($A6>NYears*12,"",LOOKUP($M6,TaxLower,TaxRate)) | O6: =IF($A6>NYears*12,"",IF(TaxFreq="Quarterly",IF(MOD($D6,3)=0,$L6*$N6,0),IF($D6=12,$K6*$N6,0))) | P6: =IF($A6>NYears*12,"",IF($D6=1,$O6,$P5+$O6)) | Q6: =IF($A6>NYears*12,"",IF($D6=12,MIN(WdrPct*IF(WdrBase="Post-tax profit",$K6-$P6,$K6),WdrCap),0)) | R6: =IF($A6>NYears*12,"",$F6+$J6-$O6-$Q6) | S6: =IF($A6>NYears*12,"",INT($R6/$E6))
A7: =3 | B7: =IF($A7>NYears*12,"",EDATE(StartMonth,$A7-1)) | C7: =IF($A7>NYears*12,"",INT(($A7-1)/12)+1) | D7: =IF($A7>NYears*12,"",MOD($A7-1,12)+1) | E7: =IF($A7>NYears*12,"",LotValue0*(1+LotGrowth)^($C7-1)) | F7: =IF($A7>NYears*12,"",IF($A7=1,InitInvest,$R6)) | G7: =IF($A7>NYears*12,"",INT($F7/$E7)) | H7: =IF($A7>NYears*12,"",$G7*$E7) | I7: =IF($A7>NYears*12,"",$F7-$H7) | J7: =IF($A7>NYears*12,"",$H7*RateA) | K7: =IF($A7>NYears*12,"",IF($D7=1,$J7,$K6+$J7)) | L7: =IF($A7>NYears*12,"",IF(MOD($D7,3)=0,SUM($J5:$J7),0)) | M7: =IF($A7>NYears*12,"",IF(TaxFreq="Quarterly",$K7*12/$D7,$K7)) | N7: =IF($A7>NYears*12,"",LOOKUP($M7,TaxLower,TaxRate)) | O7: =IF($A7>NYears*12,"",IF(TaxFreq="Quarterly",IF(MOD($D7,3)=0,$L7*$N7,0),IF($D7=12,$K7*$N7,0))) | P7: =IF($A7>NYears*12,"",IF($D7=1,$O7,$P6+$O7)) | Q7: =IF($A7>NYears*12,"",IF($D7=12,MIN(WdrPct*IF(WdrBase="Post-tax profit",$K7-$P7,$K7),WdrCap),0)) | R7: =IF($A7>NYears*12,"",$F7+$J7-$O7-$Q7) | S7: =IF($A7>NYears*12,"",INT($R7/$E7))
A8: =4 | B8: =IF($A8>NYears*12,"",EDATE(StartMonth,$A8-1)) | C8: =IF($A8>NYears*12,"",INT(($A8-1)/12)+1) | D8: =IF($A8>NYears*12,"",MOD($A8-1,12)+1) | E8: =IF($A8>NYears*12,"",LotValue0*(1+LotGrowth)^($C8-1)) | F8: =IF($A8>NYears*12,"",IF($A8=1,InitInvest,$R7)) | G8: =IF($A8>NYears*12,"",INT($F8/$E8)) | H8: =IF($A8>NYears*12,"",$G8*$E8) | I8: =IF($A8>NYears*12,"",$F8-$H8) | J8: =IF($A8>NYears*12,"",$H8*RateA) | K8: =IF($A8>NYears*12,"",IF($D8=1,$J8,$K7+$J8)) | L8: =IF($A8>NYears*12,"",IF(MOD($D8,3)=0,SUM($J6:$J8),0)) | M8: =IF($A8>NYears*12,"",IF(TaxFreq="Quarterly",$K8*12/$D8,$K8)) | N8: =IF($A8>NYears*12,"",LOOKUP($M8,TaxLower,TaxRate)) | O8: =IF($A8>NYears*12,"",IF(TaxFreq="Quarterly",IF(MOD($D8,3)=0,$L8*$N8,0),IF($D8=12,$K8*$N8,0))) | P8: =IF($A8>NYears*12,"",IF($D8=1,$O8,$P7+$O8)) | Q8: =IF($A8>NYears*12,"",IF($D8=12,MIN(WdrPct*IF(WdrBase="Post-tax profit",$K8-$P8,$K8),WdrCap),0)) | R8: =IF($A8>NYears*12,"",$F8+$J8-$O8-$Q8) | S8: =IF($A8>NYears*12,"",INT($R8/$E8))
A9: =5 | B9: =IF($A9>NYears*12,"",EDATE(StartMonth,$A9-1)) | C9: =IF($A9>NYears*12,"",INT(($A9-1)/12)+1) | D9: =IF($A9>NYears*12,"",MOD($A9-1,12)+1) | E9: =IF($A9>NYears*12,"",LotValue0*(1+LotGrowth)^($C9-1)) | F9: =IF($A9>NYears*12,"",IF($A9=1,InitInvest,$R8)) | G9: =IF($A9>NYears*12,"",INT($F9/$E9)) | H9: =IF($A9>NYears*12,"",$G9*$E9) | I9: =IF($A9>NYears*12,"",$F9-$H9) | J9: =IF($A9>NYears*12,"",$H9*RateA) | K9: =IF($A9>NYears*12,"",IF($D9=1,$J9,$K8+$J9)) | L9: =IF($A9>NYears*12,"",IF(MOD($D9,3)=0,SUM($J7:$J9),0)) | M9: =IF($A9>NYears*12,"",IF(TaxFreq="Quarterly",$K9*12/$D9,$K9)) | N9: =IF($A9>NYears*12,"",LOOKUP($M9,TaxLower,TaxRate)) | O9: =IF($A9>NYears*12,"",IF(TaxFreq="Quarterly",IF(MOD($D9,3)=0,$L9*$N9,0),IF($D9=12,$K9*$N9,0))) | P9: =IF($A9>NYears*12,"",IF($D9=1,$O9,$P8+$O9)) | Q9: =IF($A9>NYears*12,"",IF($D9=12,MIN(WdrPct*IF(WdrBase="Post-tax profit",$K9-$P9,$K9),WdrCap),0)) | R9: =IF($A9>NYears*12,"",$F9+$J9-$O9-$Q9) | S9: =IF($A9>NYears*12,"",INT($R9/$E9))
A10: =6 | B10: =IF($A10>NYears*12,"",EDATE(StartMonth,$A10-1)) | C10: =IF($A10>NYears*12,"",INT(($A10-1)/12)+1) | D10: =IF($A10>NYears*12,"",MOD($A10-1,12)+1) | E10: =IF($A10>NYears*12,"",LotValue0*(1+LotGrowth)^($C10-1)) | F10: =IF($A10>NYears*12,"",IF($A10=1,InitInvest,$R9)) | G10: =IF($A10>NYears*12,"",INT($F10/$E10)) | H10: =IF($A10>NYears*12,"",$G10*$E10) | I10: =IF($A10>NYears*12,"",$F10-$H10) | J10: =IF($A10>NYears*12,"",$H10*RateA) | K10: =IF($A10>NYears*12,"",IF($D10=1,$J10,$K9+$J10)) | L10: =IF($A10>NYears*12,"",IF(MOD($D10,3)=0,SUM($J8:$J10),0)) | M10: =IF($A10>NYears*12,"",IF(TaxFreq="Quarterly",$K10*12/$D10,$K10)) | N10: =IF($A10>NYears*12,"",LOOKUP($M10,TaxLower,TaxRate)) | O10: =IF($A10>NYears*12,"",IF(TaxFreq="Quarterly",IF(MOD($D10,3)=0,$L10*$N10,0),IF($D10=12,$K10*$N10,0))) | P10: =IF($A10>NYears*12,"",IF($D10=1,$O10,$P9+$O10)) | Q10: =IF($A10>NYears*12,"",IF($D10=12,MIN(WdrPct*IF(WdrBase="Post-tax profit",$K10-$P10,$K10),WdrCap),0)) | R10: =IF($A10>NYears*12,"",$F10+$J10-$O10-$Q10) | S10: =IF($A10>NYears*12,"",INT($R10/$E10))
A11: =7 | B11: =IF($A11>NYears*12,"",EDATE(StartMonth,$A11-1)) | C11: =IF($A11>NYears*12,"",INT(($A11-1)/12)+1) | D11: =IF($A11>NYears*12,"",MOD($A11-1,12)+1) | E11: =IF($A11>NYears*12,"",LotValue0*(1+LotGrowth)^($C11-1)) | F11: =IF($A11>NYears*12,"",IF($A11=1,InitInvest,$R10)) | G11: =IF($A11>NYears*12,"",INT($F11/$E11)) | H11: =IF($A11>NYears*12,"",$G11*$E11) | I11: =IF($A11>NYears*12,"",$F11-$H11) | J11: =IF($A11>NYears*12,"",$H11*RateA) | K11: =IF($A11>NYears*12,"",IF($D11=1,$J11,$K10+$J11)) | L11: =IF($A11>NYears*12,"",IF(MOD($D11,3)=0,SUM($J9:$J11),0)) | M11: =IF($A11>NYears*12,"",IF(TaxFreq="Quarterly",$K11*12/$D11,$K11)) | N11: =IF($A11>NYears*12,"",LOOKUP($M11,TaxLower,TaxRate)) | O11: =IF($A11>NYears*12,"",IF(TaxFreq="Quarterly",IF(MOD($D11,3)=0,$L11*$N11,0),IF($D11=12,$K11*$N11,0))) | P11: =IF($A11>NYears*12,"",IF($D11=1,$O11,$P10+$O11)) | Q11: =IF($A11>NYears*12,"",IF($D11=12,MIN(WdrPct*IF(WdrBase="Post-tax profit",$K11-$P11,$K11),WdrCap),0)) | R11: =IF($A11>NYears*12,"",$F11+$J11-$O11-$Q11) | S11: =IF($A11>NYears*12,"",INT($R11/$E11))
A12: =8 | B12: =IF($A12>NYears*12,"",EDATE(StartMonth,$A12-1)) | C12: =IF($A12>NYears*12,"",INT(($A12-1)/12)+1) | D12: =IF($A12>NYears*12,"",MOD($A12-1,12)+1) | E12: =IF($A12>NYears*12,"",LotValue0*(1+LotGrowth)^($C12-1)) | F12: =IF($A12>NYears*12,"",IF($A12=1,InitInvest,$R11)) | G12: =IF($A12>NYears*12,"",INT($F12/$E12)) | H12: =IF($A12>NYears*12,"",$G12*$E12) | I12: =IF($A12>NYears*12,"",$F12-$H12) | J12: =IF($A12>NYears*12,"",$H12*RateA) | K12: =IF($A12>NYears*12,"",IF($D12=1,$J12,$K11+$J12)) | L12: =IF($A12>NYears*12,"",IF(MOD($D12,3)=0,SUM($J10:$J12),0)) | M12: =IF($A12>NYears*12,"",IF(TaxFreq="Quarterly",$K12*12/$D12,$K12)) | N12: =IF($A12>NYears*12,"",LOOKUP($M12,TaxLower,TaxRate)) | O12: =IF($A12>NYears*12,"",IF(TaxFreq="Quarterly",IF(MOD($D12,3)=0,$L12*$N12,0),IF($D12=12,$K12*$N12,0))) | P12: =IF($A12>NYears*12,"",IF($D12=1,$O12,$P11+$O12)) | Q12: =IF($A12>NYears*12,"",IF($D12=12,MIN(WdrPct*IF(WdrBase="Post-tax profit",$K12-$P12,$K12),WdrCap),0)) | R12: =IF($A12>NYears*12,"",$F12+$J12-$O12-$Q12) | S12: =IF($A12>NYears*12,"",INT($R12/$E12))
A13: =9 | B13: =IF($A13>NYears*12,"",EDATE(StartMonth,$A13-1)) | C13: =IF($A13>NYears*12,"",INT(($A13-1)/12)+1) | D13: =IF($A13>NYears*12,"",MOD($A13-1,12)+1) | E13: =IF($A13>NYears*12,"",LotValue0*(1+LotGrowth)^($C13-1)) | F13: =IF($A13>NYears*12,"",IF($A13=1,InitInvest,$R12)) | G13: =IF($A13>NYears*12,"",INT($F13/$E13)) | H13: =IF($A13>NYears*12,"",$G13*$E13) | I13: =IF($A13>NYears*12,"",$F13-$H13) | J13: =IF($A13>NYears*12,"",$H13*RateA) | K13: =IF($A13>NYears*12,"",IF($D13=1,$J13,$K12+$J13)) | L13: =IF($A13>NYears*12,"",IF(MOD($D13,3)=0,SUM($J11:$J13),0)) | M13: =IF($A13>NYears*12,"",IF(TaxFreq="Quarterly",$K13*12/$D13,$K13)) | N13: =IF($A13>NYears*12,"",LOOKUP($M13,TaxLower,TaxRate)) | O13: =IF($A13>NYears*12,"",IF(TaxFreq="Quarterly",IF(MOD($D13,3)=0,$L13*$N13,0),IF($D13=12,$K13*$N13,0))) | P13: =IF($A13>NYears*12,"",IF($D13=1,$O13,$P12+$O13)) | Q13: =IF($A13>NYears*12,"",IF($D13=12,MIN(WdrPct*IF(WdrBase="Post-tax profit",$K13-$P13,$K13),WdrCap),0)) | R13: =IF($A13>NYears*12,"",$F13+$J13-$O13-$Q13) | S13: =IF($A13>NYears*12,"",INT($R13/$E13))
A14: =10 | B14: =IF($A14>NYears*12,"",EDATE(StartMonth,$A14-1)) | C14: =IF($A14>NYears*12,"",INT(($A14-1)/12)+1) | D14: =IF($A14>NYears*12,"",MOD($A14-1,12)+1) | E14: =IF($A14>NYears*12,"",LotValue0*(1+LotGrowth)^($C14-1)) | F14: =IF($A14>NYears*12,"",IF($A14=1,InitInvest,$R13)) | G14: =IF($A14>NYears*12,"",INT($F14/$E14)) | H14: =IF($A14>NYears*12,"",$G14*$E14) | I14: =IF($A14>NYears*12,"",$F14-$H14) | J14: =IF($A14>NYears*12,"",$H14*RateA) | K14: =IF($A14>NYears*12,"",IF($D14=1,$J14,$K13+$J14)) | L14: =IF($A14>NYears*12,"",IF(MOD($D14,3)=0,SUM($J12:$J14),0)) | M14: =IF($A14>NYears*12,"",IF(TaxFreq="Quarterly",$K14*12/$D14,$K14)) | N14: =IF($A14>NYears*12,"",LOOKUP($M14,TaxLower,TaxRate)) | O14: =IF($A14>NYears*12,"",IF(TaxFreq="Quarterly",IF(MOD($D14,3)=0,$L14*$N14,0),IF($D14=12,$K14*$N14,0))) | P14: =IF($A14>NYears*12,"",IF($D14=1,$O14,$P13+$O14)) | Q14: =IF($A14>NYears*12,"",IF($D14=12,MIN(WdrPct*IF(WdrBase="Post-tax profit",$K14-$P14,$K14),WdrCap),0)) | R14: =IF($A14>NYears*12,"",$F14+$J14-$O14-$Q14) | S14: =IF($A14>NYears*12,"",INT($R14/$E14))
A15: =11 | B15: =IF($A15>NYears*12,"",EDATE(StartMonth,$A15-1)) | C15: =IF($A15>NYears*12,"",INT(($A15-1)/12)+1) | D15: =IF($A15>NYears*12,"",MOD($A15-1,12)+1) | E15: =IF($A15>NYears*12,"",LotValue0*(1+LotGrowth)^($C15-1)) | F15: =IF($A15>NYears*12,"",IF($A15=1,InitInvest,$R14)) | G15: =IF($A15>NYears*12,"",INT($F15/$E15)) | H15: =IF($A15>NYears*12,"",$G15*$E15) | I15: =IF($A15>NYears*12,"",$F15-$H15) | J15: =IF($A15>NYears*12,"",$H15*RateA) | K15: =IF($A15>NYears*12,"",IF($D15=1,$J15,$K14+$J15)) | L15: =IF($A15>NYears*12,"",IF(MOD($D15,3)=0,SUM($J13:$J15),0)) | M15: =IF($A15>NYears*12,"",IF(TaxFreq="Quarterly",$K15*12/$D15,$K15)) | N15: =IF($A15>NYears*12,"",LOOKUP($M15,TaxLower,TaxRate)) | O15: =IF($A15>NYears*12,"",IF(TaxFreq="Quarterly",IF(MOD($D15,3)=0,$L15*$N15,0),IF($D15=12,$K15*$N15,0))) | P15: =IF($A15>NYears*12,"",IF($D15=1,$O15,$P14+$O15)) | Q15: =IF($A15>NYears*12,"",IF($D15=12,MIN(WdrPct*IF(WdrBase="Post-tax profit",$K15-$P15,$K15),WdrCap),0)) | R15: =IF($A15>NYears*12,"",$F15+$J15-$O15-$Q15) | S15: =IF($A15>NYears*12,"",INT($R15/$E15))
A16: =12 | B16: =IF($A16>NYears*12,"",EDATE(StartMonth,$A16-1)) | C16: =IF($A16>NYears*12,"",INT(($A16-1)/12)+1) | D16: =IF($A16>NYears*12,"",MOD($A16-1,12)+1) | E16: =IF($A16>NYears*12,"",LotValue0*(1+LotGrowth)^($C16-1)) | F16: =IF($A16>NYears*12,"",IF($A16=1,InitInvest,$R15)) | G16: =IF($A16>NYears*12,"",INT($F16/$E16)) | H16: =IF($A16>NYears*12,"",$G16*$E16) | I16: =IF($A16>NYears*12,"",$F16-$H16) | J16: =IF($A16>NYears*12,"",$H16*RateA) | K16: =IF($A16>NYears*12,"",IF($D16=1,$J16,$K15+$J16)) | L16: =IF($A16>NYears*12,"",IF(MOD($D16,3)=0,SUM($J14:$J16),0)) | M16: =IF($A16>NYears*12,"",IF(TaxFreq="Quarterly",$K16*12/$D16,$K16)) | N16: =IF($A16>NYears*12,"",LOOKUP($M16,TaxLower,TaxRate)) | O16: =IF($A16>NYears*12,"",IF(TaxFreq="Quarterly",IF(MOD($D16,3)=0,$L16*$N16,0),IF($D16=12,$K16*$N16,0))) | P16: =IF($A16>NYears*12,"",IF($D16=1,$O16,$P15+$O16)) | Q16: =IF($A16>NYears*12,"",IF($D16=12,MIN(WdrPct*IF(WdrBase="Post-tax profit",$K16-$P16,$K16),WdrCap),0)) | R16: =IF($A16>NYears*12,"",$F16+$J16-$O16-$Q16) | S16: =IF($A16>NYears*12,"",INT($R16/$E16))
A17: =13 | B17: =IF($A17>NYears*12,"",EDATE(StartMonth,$A17-1)) | C17: =IF($A17>NYears*12,"",INT(($A17-1)/12)+1) | D17: =IF($A17>NYears*12,"",MOD($A17-1,12)+1) | E17: =IF($A17>NYears*12,"",LotValue0*(1+LotGrowth)^($C17-1)) | F17: =IF($A17>NYears*12,"",IF($A17=1,InitInvest,$R16)) | G17: =IF($A17>NYears*12,"",INT($F17/$E17)) | H17: =IF($A17>NYears*12,"",$G17*$E17) | I17: =IF($A17>NYears*12,"",$F17-$H17) | J17: =IF($A17>NYears*12,"",$H17*RateA) | K17: =IF($A17>NYears*12,"",IF($D17=1,$J17,$K16+$J17)) | L17: =IF($A17>NYears*12,"",IF(MOD($D17,3)=0,SUM($J15:$J17),0)) | M17: =IF($A17>NYears*12,"",IF(TaxFreq="Quarterly",$K17*12/$D17,$K17)) | N17: =IF($A17>NYears*12,"",LOOKUP($M17,TaxLower,TaxRate)) | O17: =IF($A17>NYears*12,"",IF(TaxFreq="Quarterly",IF(MOD($D17,3)=0,$L17*$N17,0),IF($D17=12,$K17*$N17,0))) | P17: =IF($A17>NYears*12,"",IF($D17=1,$O17,$P16+$O17)) | Q17: =IF($A17>NYears*12,"",IF($D17=12,MIN(WdrPct*IF(WdrBase="Post-tax profit",$K17-$P17,$K17),WdrCap),0)) | R17: =IF($A17>NYears*12,"",$F17+$J17-$O17-$Q17) | S17: =IF($A17>NYears*12,"",INT($R17/$E17))
A18: =14 | B18: =IF($A18>NYears*12,"",EDATE(StartMonth,$A18-1)) | C18: =IF($A18>NYears*12,"",INT(($A18-1)/12)+1) | D18: =IF($A18>NYears*12,"",MOD($A18-1,12)+1) | E18: =IF($A18>NYears*12,"",LotValue0*(1+LotGrowth)^($C18-1)) | F18: =IF($A18>NYears*12,"",IF($A18=1,InitInvest,$R17)) | G18: =IF($A18>NYears*12,"",INT($F18/$E18)) | H18: =IF($A18>NYears*12,"",$G18*$E18) | I18: =IF($A18>NYears*12,"",$F18-$H18) | J18: =IF($A18>NYears*12,"",$H18*RateA) | K18: =IF($A18>NYears*12,"",IF($D18=1,$J18,$K17+$J18)) | L18: =IF($A18>NYears*12,"",IF(MOD($D18,3)=0,SUM($J16:$J18),0)) | M18: =IF($A18>NYears*12,"",IF(TaxFreq="Quarterly",$K18*12/$D18,$K18)) | N18: =IF($A18>NYears*12,"",LOOKUP($M18,TaxLower,TaxRate)) | O18: =IF($A18>NYears*12,"",IF(TaxFreq="Quarterly",IF(MOD($D18,3)=0,$L18*$N18,0),IF($D18=12,$K18*$N18,0))) | P18: =IF($A18>NYears*12,"",IF($D18=1,$O18,$P17+$O18)) | Q18: =IF($A18>NYears*12,"",IF($D18=12,MIN(WdrPct*IF(WdrBase="Post-tax profit",$K18-$P18,$K18),WdrCap),0)) | R18: =IF($A18>NYears*12,"",$F18+$J18-$O18-$Q18) | S18: =IF($A18>NYears*12,"",INT($R18/$E18))
A19: =15 | B19: =IF($A19>NYears*12,"",EDATE(StartMonth,$A19-1)) | C19: =IF($A19>NYears*12,"",INT(($A19-1)/12)+1) | D19: =IF($A19>NYears*12,"",MOD($A19-1,12)+1) | E19: =IF($A19>NYears*12,"",LotValue0*(1+LotGrowth)^($C19-1)) | F19: =IF($A19>NYears*12,"",IF($A19=1,InitInvest,$R18)) | G19: =IF($A19>NYears*12,"",INT($F19/$E19)) | H19: =IF($A19>NYears*12,"",$G19*$E19) | I19: =IF($A19>NYears*12,"",$F19-$H19) | J19: =IF($A19>NYears*12,"",$H19*RateA) | K19: =IF($A19>NYears*12,"",IF($D19=1,$J19,$K18+$J19)) | L19: =IF($A19>NYears*12,"",IF(MOD($D19,3)=0,SUM($J17:$J19),0)) | M19: =IF($A19>NYears*12,"",IF(TaxFreq="Quarterly",$K19*12/$D19,$K19)) | N19: =IF($A19>NYears*12,"",LOOKUP($M19,TaxLower,TaxRate)) | O19: =IF($A19>NYears*12,"",IF(TaxFreq="Quarterly",IF(MOD($D19,3)=0,$L19*$N19,0),IF($D19=12,$K19*$N19,0))) | P19: =IF($A19>NYears*12,"",IF($D19=1,$O19,$P18+$O19)) | Q19: =IF($A19>NYears*12,"",IF($D19=12,MIN(WdrPct*IF(WdrBase="Post-tax profit",$K19-$P19,$K19),WdrCap),0)) | R19: =IF($A19>NYears*12,"",$F19+$J19-$O19-$Q19) | S19: =IF($A19>NYears*12,"",INT($R19/$E19))
A20: =16 | B20: =IF($A20>NYears*12,"",EDATE(StartMonth,$A20-1)) | C20: =IF($A20>NYears*12,"",INT(($A20-1)/12)+1) | D20: =IF($A20>NYears*12,"",MOD($A20-1,12)+1) | E20: =IF($A20>NYears*12,"",LotValue0*(1+LotGrowth)^($C20-1)) | F20: =IF($A20>NYears*12,"",IF($A20=1,InitInvest,$R19)) | G20: =IF($A20>NYears*12,"",INT($F20/$E20)) | H20: =IF($A20>NYears*12,"",$G20*$E20) | I20: =IF($A20>NYears*12,"",$F20-$H20) | J20: =IF($A20>NYears*12,"",$H20*RateA) | K20: =IF($A20>NYears*12,"",IF($D20=1,$J20,$K19+$J20)) | L20: =IF($A20>NYears*12,"",IF(MOD($D20,3)=0,SUM($J18:$J20),0)) | M20: =IF($A20>NYears*12,"",IF(TaxFreq="Quarterly",$K20*12/$D20,$K20)) | N20: =IF($A20>NYears*12,"",LOOKUP($M20,TaxLower,TaxRate)) | O20: =IF($A20>NYears*12,"",IF(TaxFreq="Quarterly",IF(MOD($D20,3)=0,$L20*$N20,0),IF($D20=12,$K20*$N20,0))) | P20: =IF($A20>NYears*12,"",IF($D20=1,$O20,$P19+$O20)) | Q20: =IF($A20>NYears*12,"",IF($D20=12,MIN(WdrPct*IF(WdrBase="Post-tax profit",$K20-$P20,$K20),WdrCap),0)) | R20: =IF($A20>NYears*12,"",$F20+$J20-$O20-$Q20) | S20: =IF($A20>NYears*12,"",INT($R20/$E20))
A21: =17 | B21: =IF($A21>NYears*12,"",EDATE(StartMonth,$A21-1)) | C21: =IF($A21>NYears*12,"",INT(($A21-1)/12)+1) | D21: =IF($A21>NYears*12,"",MOD($A21-1,12)+1) | E21: =IF($A21>NYears*12,"",LotValue0*(1+LotGrowth)^($C21-1)) | F21: =IF($A21>NYears*12,"",IF($A21=1,InitInvest,$R20)) | G21: =IF($A21>NYears*12,"",INT($F21/$E21)) | H21: =IF($A21>NYears*12,"",$G21*$E21) | I21: =IF($A21>NYears*12,"",$F21-$H21) | J21: =IF($A21>NYears*12,"",$H21*RateA) | K21: =IF($A21>NYears*12,"",IF($D21=1,$J21,$K20+$J21)) | L21: =IF($A21>NYears*12,"",IF(MOD($D21,3)=0,SUM($J19:$J21),0)) | M21: =IF($A21>NYears*12,"",IF(TaxFreq="Quarterly",$K21*12/$D21,$K21)) | N21: =IF($A21>NYears*12,"",LOOKUP($M21,TaxLower,TaxRate)) | O21: =IF($A21>NYears*12,"",IF(TaxFreq="Quarterly",IF(MOD($D21,3)=0,$L21*$N21,0),IF($D21=12,$K21*$N21,0))) | P21: =IF($A21>NYears*12,"",IF($D21=1,$O21,$P20+$O21)) | Q21: =IF($A21>NYears*12,"",IF($D21=12,MIN(WdrPct*IF(WdrBase="Post-tax profit",$K21-$P21,$K21),WdrCap),0)) | R21: =IF($A21>NYears*12,"",$F21+$J21-$O21-$Q21) | S21: =IF($A21>NYears*12,"",INT($R21/$E21))
A22: =18 | B22: =IF($A22>NYears*12,"",EDATE(StartMonth,$A22-1)) | C22: =IF($A22>NYears*12,"",INT(($A22-1)/12)+1) | D22: =IF($A22>NYears*12,"",MOD($A22-1,12)+1) | E22: =IF($A22>NYears*12,"",LotValue0*(1+LotGrowth)^($C22-1)) | F22: =IF($A22>NYears*12,"",IF($A22=1,InitInvest,$R21)) | G22: =IF($A22>NYears*12,"",INT($F22/$E22)) | H22: =IF($A22>NYears*12,"",$G22*$E22) | I22: =IF($A22>NYears*12,"",$F22-$H22) | J22: =IF($A22>NYears*12,"",$H22*RateA) | K22: =IF($A22>NYears*12,"",IF($D22=1,$J22,$K21+$J22)) | L22: =IF($A22>NYears*12,"",IF(MOD($D22,3)=0,SUM($J20:$J22),0)) | M22: =IF($A22>NYears*12,"",IF(TaxFreq="Quarterly",$K22*12/$D22,$K22)) | N22: =IF($A22>NYears*12,"",LOOKUP($M22,TaxLower,TaxRate)) | O22: =IF($A22>NYears*12,"",IF(TaxFreq="Quarterly",IF(MOD($D22,3)=0,$L22*$N22,0),IF($D22=12,$K22*$N22,0))) | P22: =IF($A22>NYears*12,"",IF($D22=1,$O22,$P21+$O22)) | Q22: =IF($A22>NYears*12,"",IF($D22=12,MIN(WdrPct*IF(WdrBase="Post-tax profit",$K22-$P22,$K22),WdrCap),0)) | R22: =IF($A22>NYears*12,"",$F22+$J22-$O22-$Q22) | S22: =IF($A22>NYears*12,"",INT($R22/$E22))
A23: =19 | B23: =IF($A23>NYears*12,"",EDATE(StartMonth,$A23-1)) | C23: =IF($A23>NYears*12,"",INT(($A23-1)/12)+1) | D23: =IF($A23>NYears*12,"",MOD($A23-1,12)+1) | E23: =IF($A23>NYears*12,"",LotValue0*(1+LotGrowth)^($C23-1)) | F23: =IF($A23>NYears*12,"",IF($A23=1,InitInvest,$R22)) | G23: =IF($A23>NYears*12,"",INT($F23/$E23)) | H23: =IF($A23>NYears*12,"",$G23*$E23) | I23: =IF($A23>NYears*12,"",$F23-$H23) | J23: =IF($A23>NYears*12,"",$H23*RateA) | K23: =IF($A23>NYears*12,"",IF($D23=1,$J23,$K22+$J23)) | L23: =IF($A23>NYears*12,"",IF(MOD($D23,3)=0,SUM($J21:$J23),0)) | M23: =IF($A23>NYears*12,"",IF(TaxFreq="Quarterly",$K23*12/$D23,$K23)) | N23: =IF($A23>NYears*12,"",LOOKUP($M23,TaxLower,TaxRate)) | O23: =IF($A23>NYears*12,"",IF(TaxFreq="Quarterly",IF(MOD($D23,3)=0,$L23*$N23,0),IF($D23=12,$K23*$N23,0))) | P23: =IF($A23>NYears*12,"",IF($D23=1,$O23,$P22+$O23)) | Q23: =IF($A23>NYears*12,"",IF($D23=12,MIN(WdrPct*IF(WdrBase="Post-tax profit",$K23-$P23,$K23),WdrCap),0)) | R23: =IF($A23>NYears*12,"",$F23+$J23-$O23-$Q23) | S23: =IF($A23>NYears*12,"",INT($R23/$E23))
A24: =20 | B24: =IF($A24>NYears*12,"",EDATE(StartMonth,$A24-1)) | C24: =IF($A24>NYears*12,"",INT(($A24-1)/12)+1) | D24: =IF($A24>NYears*12,"",MOD($A24-1,12)+1) | E24: =IF($A24>NYears*12,"",LotValue0*(1+LotGrowth)^($C24-1)) | F24: =IF($A24>NYears*12,"",IF($A24=1,InitInvest,$R23)) | G24: =IF($A24>NYears*12,"",INT($F24/$E24)) | H24: =IF($A24>NYears*12,"",$G24*$E24) | I24: =IF($A24>NYears*12,"",$F24-$H24) | J24: =IF($A24>NYears*12,"",$H24*RateA) | K24: =IF($A24>NYears*12,"",IF($D24=1,$J24,$K23+$J24)) | L24: =IF($A24>NYears*12,"",IF(MOD($D24,3)=0,SUM($J22:$J24),0)) | M24: =IF($A24>NYears*12,"",IF(TaxFreq="Quarterly",$K24*12/$D24,$K24)) | N24: =IF($A24>NYears*12,"",LOOKUP($M24,TaxLower,TaxRate)) | O24: =IF($A24>NYears*12,"",IF(TaxFreq="Quarterly",IF(MOD($D24,3)=0,$L24*$N24,0),IF($D24=12,$K24*$N24,0))) | P24: =IF($A24>NYears*12,"",IF($D24=1,$O24,$P23+$O24)) | Q24: =IF($A24>NYears*12,"",IF($D24=12,MIN(WdrPct*IF(WdrBase="Post-tax profit",$K24-$P24,$K24),WdrCap),0)) | R24: =IF($A24>NYears*12,"",$F24+$J24-$O24-$Q24) | S24: =IF($A24>NYears*12,"",INT($R24/$E24))
A25: =21 | B25: =IF($A25>NYears*12,"",EDATE(StartMonth,$A25-1)) | C25: =IF($A25>NYears*12,"",INT(($A25-1)/12)+1) | D25: =IF($A25>NYears*12,"",MOD($A25-1,12)+1) | E25: =IF($A25>NYears*12,"",LotValue0*(1+LotGrowth)^($C25-1)) | F25: =IF($A25>NYears*12,"",IF($A25=1,InitInvest,$R24)) | G25: =IF($A25>NYears*12,"",INT($F25/$E25)) | H25: =IF($A25>NYears*12,"",$G25*$E25) | I25: =IF($A25>NYears*12,"",$F25-$H25) | J25: =IF($A25>NYears*12,"",$H25*RateA) | K25: =IF($A25>NYears*12,"",IF($D25=1,$J25,$K24+$J25)) | L25: =IF($A25>NYears*12,"",IF(MOD($D25,3)=0,SUM($J23:$J25),0)) | M25: =IF($A25>NYears*12,"",IF(TaxFreq="Quarterly",$K25*12/$D25,$K25)) | N25: =IF($A25>NYears*12,"",LOOKUP($M25,TaxLower,TaxRate)) | O25: =IF($A25>NYears*12,"",IF(TaxFreq="Quarterly",IF(MOD($D25,3)=0,$L25*$N25,0),IF($D25=12,$K25*$N25,0))) | P25: =IF($A25>NYears*12,"",IF($D25=1,$O25,$P24+$O25)) | Q25: =IF($A25>NYears*12,"",IF($D25=12,MIN(WdrPct*IF(WdrBase="Post-tax profit",$K25-$P25,$K25),WdrCap),0)) | R25: =IF($A25>NYears*12,"",$F25+$J25-$O25-$Q25) | S25: =IF($A25>NYears*12,"",INT($R25/$E25))
A26: =22 | B26: =IF($A26>NYears*12,"",EDATE(StartMonth,$A26-1)) | C26: =IF($A26>NYears*12,"",INT(($A26-1)/12)+1) | D26: =IF($A26>NYears*12,"",MOD($A26-1,12)+1) | E26: =IF($A26>NYears*12,"",LotValue0*(1+LotGrowth)^($C26-1)) | F26: =IF($A26>NYears*12,"",IF($A26=1,InitInvest,$R25)) | G26: =IF($A26>NYears*12,"",INT($F26/$E26)) | H26: =IF($A26>NYears*12,"",$G26*$E26) | I26: =IF($A26>NYears*12,"",$F26-$H26) | J26: =IF($A26>NYears*12,"",$H26*RateA) | K26: =IF($A26>NYears*12,"",IF($D26=1,$J26,$K25+$J26)) | L26: =IF($A26>NYears*12,"",IF(MOD($D26,3)=0,SUM($J24:$J26),0)) | M26: =IF($A26>NYears*12,"",IF(TaxFreq="Quarterly",$K26*12/$D26,$K26)) | N26: =IF($A26>NYears*12,"",LOOKUP($M26,TaxLower,TaxRate)) | O26: =IF($A26>NYears*12,"",IF(TaxFreq="Quarterly",IF(MOD($D26,3)=0,$L26*$N26,0),IF($D26=12,$K26*$N26,0))) | P26: =IF($A26>NYears*12,"",IF($D26=1,$O26,$P25+$O26)) | Q26: =IF($A26>NYears*12,"",IF($D26=12,MIN(WdrPct*IF(WdrBase="Post-tax profit",$K26-$P26,$K26),WdrCap),0)) | R26: =IF($A26>NYears*12,"",$F26+$J26-$O26-$Q26) | S26: =IF($A26>NYears*12,"",INT($R26/$E26))
A27: =23 | B27: =IF($A27>NYears*12,"",EDATE(StartMonth,$A27-1)) | C27: =IF($A27>NYears*12,"",INT(($A27-1)/12)+1) | D27: =IF($A27>NYears*12,"",MOD($A27-1,12)+1) | E27: =IF($A27>NYears*12,"",LotValue0*(1+LotGrowth)^($C27-1)) | F27: =IF($A27>NYears*12,"",IF($A27=1,InitInvest,$R26)) | G27: =IF($A27>NYears*12,"",INT($F27/$E27)) | H27: =IF($A27>NYears*12,"",$G27*$E27) | I27: =IF($A27>NYears*12,"",$F27-$H27) | J27: =IF($A27>NYears*12,"",$H27*RateA) | K27: =IF($A27>NYears*12,"",IF($D27=1,$J27,$K26+$J27)) | L27: =IF($A27>NYears*12,"",IF(MOD($D27,3)=0,SUM($J25:$J27),0)) | M27: =IF($A27>NYears*12,"",IF(TaxFreq="Quarterly",$K27*12/$D27,$K27)) | N27: =IF($A27>NYears*12,"",LOOKUP($M27,TaxLower,TaxRate)) | O27: =IF($A27>NYears*12,"",IF(TaxFreq="Quarterly",IF(MOD($D27,3)=0,$L27*$N27,0),IF($D27=12,$K27*$N27,0))) | P27: =IF($A27>NYears*12,"",IF($D27=1,$O27,$P26+$O27)) | Q27: =IF($A27>NYears*12,"",IF($D27=12,MIN(WdrPct*IF(WdrBase="Post-tax profit",$K27-$P27,$K27),WdrCap),0)) | R27: =IF($A27>NYears*12,"",$F27+$J27-$O27-$Q27) | S27: =IF($A27>NYears*12,"",INT($R27/$E27))
A28: =24 | B28: =IF($A28>NYears*12,"",EDATE(StartMonth,$A28-1)) | C28: =IF($A28>NYears*12,"",INT(($A28-1)/12)+1) | D28: =IF($A28>NYears*12,"",MOD($A28-1,12)+1) | E28: =IF($A28>NYears*12,"",LotValue0*(1+LotGrowth)^($C28-1)) | F28: =IF($A28>NYears*12,"",IF($A28=1,InitInvest,$R27)) | G28: =IF($A28>NYears*12,"",INT($F28/$E28)) | H28: =IF($A28>NYears*12,"",$G28*$E28) | I28: =IF($A28>NYears*12,"",$F28-$H28) | J28: =IF($A28>NYears*12,"",$H28*RateA) | K28: =IF($A28>NYears*12,"",IF($D28=1,$J28,$K27+$J28)) | L28: =IF($A28>NYears*12,"",IF(MOD($D28,3)=0,SUM($J26:$J28),0)) | M28: =IF($A28>NYears*12,"",IF(TaxFreq="Quarterly",$K28*12/$D28,$K28)) | N28: =IF($A28>NYears*12,"",LOOKUP($M28,TaxLower,TaxRate)) | O28: =IF($A28>NYears*12,"",IF(TaxFreq="Quarterly",IF(MOD($D28,3)=0,$L28*$N28,0),IF($D28=12,$K28*$N28,0))) | P28: =IF($A28>NYears*12,"",IF($D28=1,$O28,$P27+$O28)) | Q28: =IF($A28>NYears*12,"",IF($D28=12,MIN(WdrPct*IF(WdrBase="Post-tax profit",$K28-$P28,$K28),WdrCap),0)) | R28: =IF($A28>NYears*12,"",$F28+$J28-$O28-$Q28) | S28: =IF($A28>NYears*12,"",INT($R28/$E28))
A29: =25 | B29: =IF($A29>NYears*12,"",EDATE(StartMonth,$A29-1)) | C29: =IF($A29>NYears*12,"",INT(($A29-1)/12)+1) | D29: =IF($A29>NYears*12,"",MOD($A29-1,12)+1) | E29: =IF($A29>NYears*12,"",LotValue0*(1+LotGrowth)^($C29-1)) | F29: =IF($A29>NYears*12,"",IF($A29=1,InitInvest,$R28)) | G29: =IF($A29>NYears*12,"",INT($F29/$E29)) | H29: =IF($A29>NYears*12,"",$G29*$E29) | I29: =IF($A29>NYears*12,"",$F29-$H29) | J29: =IF($A29>NYears*12,"",$H29*RateA) | K29: =IF($A29>NYears*12,"",IF($D29=1,$J29,$K28+$J29)) | L29: =IF($A29>NYears*12,"",IF(MOD($D29,3)=0,SUM($J27:$J29),0)) | M29: =IF($A29>NYears*12,"",IF(TaxFreq="Quarterly",$K29*12/$D29,$K29)) | N29: =IF($A29>NYears*12,"",LOOKUP($M29,TaxLower,TaxRate)) | O29: =IF($A29>NYears*12,"",IF(TaxFreq="Quarterly",IF(MOD($D29,3)=0,$L29*$N29,0),IF($D29=12,$K29*$N29,0))) | P29: =IF($A29>NYears*12,"",IF($D29=1,$O29,$P28+$O29)) | Q29: =IF($A29>NYears*12,"",IF($D29=12,MIN(WdrPct*IF(WdrBase="Post-tax profit",$K29-$P29,$K29),WdrCap),0)) | R29: =IF($A29>NYears*12,"",$F29+$J29-$O29-$Q29) | S29: =IF($A29>NYears*12,"",INT($R29/$E29))
A30: =26 | B30: =IF($A30>NYears*12,"",EDATE(StartMonth,$A30-1)) | C30: =IF($A30>NYears*12,"",INT(($A30-1)/12)+1) | D30: =IF($A30>NYears*12,"",MOD($A30-1,12)+1) | E30: =IF($A30>NYears*12,"",LotValue0*(1+LotGrowth)^($C30-1)) | F30: =IF($A30>NYears*12,"",IF($A30=1,InitInvest,$R29)) | G30: =IF($A30>NYears*12,"",INT($F30/$E30)) | H30: =IF($A30>NYears*12,"",$G30*$E30) | I30: =IF($A30>NYears*12,"",$F30-$H30) | J30: =IF($A30>NYears*12,"",$H30*RateA) | K30: =IF($A30>NYears*12,"",IF($D30=1,$J30,$K29+$J30)) | L30: =IF($A30>NYears*12,"",IF(MOD($D30,3)=0,SUM($J28:$J30),0)) | M30: =IF($A30>NYears*12,"",IF(TaxFreq="Quarterly",$K30*12/$D30,$K30)) | N30: =IF($A30>NYears*12,"",LOOKUP($M30,TaxLower,TaxRate)) | O30: =IF($A30>NYears*12,"",IF(TaxFreq="Quarterly",IF(MOD($D30,3)=0,$L30*$N30,0),IF($D30=12,$K30*$N30,0))) | P30: =IF($A30>NYears*12,"",IF($D30=1,$O30,$P29+$O30)) | Q30: =IF($A30>NYears*12,"",IF($D30=12,MIN(WdrPct*IF(WdrBase="Post-tax profit",$K30-$P30,$K30),WdrCap),0)) | R30: =IF($A30>NYears*12,"",$F30+$J30-$O30-$Q30) | S30: =IF($A30>NYears*12,"",INT($R30/$E30))
A31: =27 | B31: =IF($A31>NYears*12,"",EDATE(StartMonth,$A31-1)) | C31: =IF($A31>NYears*12,"",INT(($A31-1)/12)+1) | D31: =IF($A31>NYears*12,"",MOD($A31-1,12)+1) | E31: =IF($A31>NYears*12,"",LotValue0*(1+LotGrowth)^($C31-1)) | F31: =IF($A31>NYears*12,"",IF($A31=1,InitInvest,$R30)) | G31: =IF($A31>NYears*12,"",INT($F31/$E31)) | H31: =IF($A31>NYears*12,"",$G31*$E31) | I31: =IF($A31>NYears*12,"",$F31-$H31) | J31: =IF($A31>NYears*12,"",$H31*RateA) | K31: =IF($A31>NYears*12,"",IF($D31=1,$J31,$K30+$J31)) | L31: =IF($A31>NYears*12,"",IF(MOD($D31,3)=0,SUM($J29:$J31),0)) | M31: =IF($A31>NYears*12,"",IF(TaxFreq="Quarterly",$K31*12/$D31,$K31)) | N31: =IF($A31>NYears*12,"",LOOKUP($M31,TaxLower,TaxRate)) | O31: =IF($A31>NYears*12,"",IF(TaxFreq="Quarterly",IF(MOD($D31,3)=0,$L31*$N31,0),IF($D31=12,$K31*$N31,0))) | P31: =IF($A31>NYears*12,"",IF($D31=1,$O31,$P30+$O31)) | Q31: =IF($A31>NYears*12,"",IF($D31=12,MIN(WdrPct*IF(WdrBase="Post-tax profit",$K31-$P31,$K31),WdrCap),0)) | R31: =IF($A31>NYears*12,"",$F31+$J31-$O31-$Q31) | S31: =IF($A31>NYears*12,"",INT($R31/$E31))
A32: =28 | B32: =IF($A32>NYears*12,"",EDATE(StartMonth,$A32-1)) | C32: =IF($A32>NYears*12,"",INT(($A32-1)/12)+1) | D32: =IF($A32>NYears*12,"",MOD($A32-1,12)+1) | E32: =IF($A32>NYears*12,"",LotValue0*(1+LotGrowth)^($C32-1)) | F32: =IF($A32>NYears*12,"",IF($A32=1,InitInvest,$R31)) | G32: =IF($A32>NYears*12,"",INT($F32/$E32)) | H32: =IF($A32>NYears*12,"",$G32*$E32) | I32: =IF($A32>NYears*12,"",$F32-$H32) | J32: =IF($A32>NYears*12,"",$H32*RateA) | K32: =IF($A32>NYears*12,"",IF($D32=1,$J32,$K31+$J32)) | L32: =IF($A32>NYears*12,"",IF(MOD($D32,3)=0,SUM($J30:$J32),0)) | M32: =IF($A32>NYears*12,"",IF(TaxFreq="Quarterly",$K32*12/$D32,$K32)) | N32: =IF($A32>NYears*12,"",LOOKUP($M32,TaxLower,TaxRate)) | O32: =IF($A32>NYears*12,"",IF(TaxFreq="Quarterly",IF(MOD($D32,3)=0,$L32*$N32,0),IF($D32=12,$K32*$N32,0))) | P32: =IF($A32>NYears*12,"",IF($D32=1,$O32,$P31+$O32)) | Q32: =IF($A32>NYears*12,"",IF($D32=12,MIN(WdrPct*IF(WdrBase="Post-tax profit",$K32-$P32,$K32),WdrCap),0)) | R32: =IF($A32>NYears*12,"",$F32+$J32-$O32-$Q32) | S32: =IF($A32>NYears*12,"",INT($R32/$E32))
A33: =29 | B33: =IF($A33>NYears*12,"",EDATE(StartMonth,$A33-1)) | C33: =IF($A33>NYears*12,"",INT(($A33-1)/12)+1) | D33: =IF($A33>NYears*12,"",MOD($A33-1,12)+1) | E33: =IF($A33>NYears*12,"",LotValue0*(1+LotGrowth)^($C33-1)) | F33: =IF($A33>NYears*12,"",IF($A33=1,InitInvest,$R32)) | G33: =IF($A33>NYears*12,"",INT($F33/$E33)) | H33: =IF($A33>NYears*12,"",$G33*$E33) | I33: =IF($A33>NYears*12,"",$F33-$H33) | J33: =IF($A33>NYears*12,"",$H33*RateA) | K33: =IF($A33>NYears*12,"",IF($D33=1,$J33,$K32+$J33)) | L33: =IF($A33>NYears*12,"",IF(MOD($D33,3)=0,SUM($J31:$J33),0)) | M33: =IF($A33>NYears*12,"",IF(TaxFreq="Quarterly",$K33*12/$D33,$K33)) | N33: =IF($A33>NYears*12,"",LOOKUP($M33,TaxLower,TaxRate)) | O33: =IF($A33>NYears*12,"",IF(TaxFreq="Quarterly",IF(MOD($D33,3)=0,$L33*$N33,0),IF($D33=12,$K33*$N33,0))) | P33: =IF($A33>NYears*12,"",IF($D33=1,$O33,$P32+$O33)) | Q33: =IF($A33>NYears*12,"",IF($D33=12,MIN(WdrPct*IF(WdrBase="Post-tax profit",$K33-$P33,$K33),WdrCap),0)) | R33: =IF($A33>NYears*12,"",$F33+$J33-$O33-$Q33) | S33: =IF($A33>NYears*12,"",INT($R33/$E33))
A34: =30 | B34: =IF($A34>NYears*12,"",EDATE(StartMonth,$A34-1)) | C34: =IF($A34>NYears*12,"",INT(($A34-1)/12)+1) | D34: =IF($A34>NYears*12,"",MOD($A34-1,12)+1) | E34: =IF($A34>NYears*12,"",LotValue0*(1+LotGrowth)^($C34-1)) | F34: =IF($A34>NYears*12,"",IF($A34=1,InitInvest,$R33)) | G34: =IF($A34>NYears*12,"",INT($F34/$E34)) | H34: =IF($A34>NYears*12,"",$G34*$E34) | I34: =IF($A34>NYears*12,"",$F34-$H34) | J34: =IF($A34>NYears*12,"",$H34*RateA) | K34: =IF($A34>NYears*12,"",IF($D34=1,$J34,$K33+$J34)) | L34: =IF($A34>NYears*12,"",IF(MOD($D34,3)=0,SUM($J32:$J34),0)) | M34: =IF($A34>NYears*12,"",IF(TaxFreq="Quarterly",$K34*12/$D34,$K34)) | N34: =IF($A34>NYears*12,"",LOOKUP($M34,TaxLower,TaxRate)) | O34: =IF($A34>NYears*12,"",IF(TaxFreq="Quarterly",IF(MOD($D34,3)=0,$L34*$N34,0),IF($D34=12,$K34*$N34,0))) | P34: =IF($A34>NYears*12,"",IF($D34=1,$O34,$P33+$O34)) | Q34: =IF($A34>NYears*12,"",IF($D34=12,MIN(WdrPct*IF(WdrBase="Post-tax profit",$K34-$P34,$K34),WdrCap),0)) | R34: =IF($A34>NYears*12,"",$F34+$J34-$O34-$Q34) | S34: =IF($A34>NYears*12,"",INT($R34/$E34))
A35: =31 | B35: =IF($A35>NYears*12,"",EDATE(StartMonth,$A35-1)) | C35: =IF($A35>NYears*12,"",INT(($A35-1)/12)+1) | D35: =IF($A35>NYears*12,"",MOD($A35-1,12)+1) | E35: =IF($A35>NYears*12,"",LotValue0*(1+LotGrowth)^($C35-1)) | F35: =IF($A35>NYears*12,"",IF($A35=1,InitInvest,$R34)) | G35: =IF($A35>NYears*12,"",INT($F35/$E35)) | H35: =IF($A35>NYears*12,"",$G35*$E35) | I35: =IF($A35>NYears*12,"",$F35-$H35) | J35: =IF($A35>NYears*12,"",$H35*RateA) | K35: =IF($A35>NYears*12,"",IF($D35=1,$J35,$K34+$J35)) | L35: =IF($A35>NYears*12,"",IF(MOD($D35,3)=0,SUM($J33:$J35),0)) | M35: =IF($A35>NYears*12,"",IF(TaxFreq="Quarterly",$K35*12/$D35,$K35)) | N35: =IF($A35>NYears*12,"",LOOKUP($M35,TaxLower,TaxRate)) | O35: =IF($A35>NYears*12,"",IF(TaxFreq="Quarterly",IF(MOD($D35,3)=0,$L35*$N35,0),IF($D35=12,$K35*$N35,0))) | P35: =IF($A35>NYears*12,"",IF($D35=1,$O35,$P34+$O35)) | Q35: =IF($A35>NYears*12,"",IF($D35=12,MIN(WdrPct*IF(WdrBase="Post-tax profit",$K35-$P35,$K35),WdrCap),0)) | R35: =IF($A35>NYears*12,"",$F35+$J35-$O35-$Q35) | S35: =IF($A35>NYears*12,"",INT($R35/$E35))
A36: =32 | B36: =IF($A36>NYears*12,"",EDATE(StartMonth,$A36-1)) | C36: =IF($A36>NYears*12,"",INT(($A36-1)/12)+1) | D36: =IF($A36>NYears*12,"",MOD($A36-1,12)+1) | E36: =IF($A36>NYears*12,"",LotValue0*(1+LotGrowth)^($C36-1)) | F36: =IF($A36>NYears*12,"",IF($A36=1,InitInvest,$R35)) | G36: =IF($A36>NYears*12,"",INT($F36/$E36)) | H36: =IF($A36>NYears*12,"",$G36*$E36) | I36: =IF($A36>NYears*12,"",$F36-$H36) | J36: =IF($A36>NYears*12,"",$H36*RateA) | K36: =IF($A36>NYears*12,"",IF($D36=1,$J36,$K35+$J36)) | L36: =IF($A36>NYears*12,"",IF(MOD($D36,3)=0,SUM($J34:$J36),0)) | M36: =IF($A36>NYears*12,"",IF(TaxFreq="Quarterly",$K36*12/$D36,$K36)) | N36: =IF($A36>NYears*12,"",LOOKUP($M36,TaxLower,TaxRate)) | O36: =IF($A36>NYears*12,"",IF(TaxFreq="Quarterly",IF(MOD($D36,3)=0,$L36*$N36,0),IF($D36=12,$K36*$N36,0))) | P36: =IF($A36>NYears*12,"",IF($D36=1,$O36,$P35+$O36)) | Q36: =IF($A36>NYears*12,"",IF($D36=12,MIN(WdrPct*IF(WdrBase="Post-tax profit",$K36-$P36,$K36),WdrCap),0)) | R36: =IF($A36>NYears*12,"",$F36+$J36-$O36-$Q36) | S36: =IF($A36>NYears*12,"",INT($R36/$E36))
A37: =33 | B37: =IF($A37>NYears*12,"",EDATE(StartMonth,$A37-1)) | C37: =IF($A37>NYears*12,"",INT(($A37-1)/12)+1) | D37: =IF($A37>NYears*12,"",MOD($A37-1,12)+1) | E37: =IF($A37>NYears*12,"",LotValue0*(1+LotGrowth)^($C37-1)) | F37: =IF($A37>NYears*12,"",IF($A37=1,InitInvest,$R36)) | G37: =IF($A37>NYears*12,"",INT($F37/$E37)) | H37: =IF($A37>NYears*12,"",$G37*$E37) | I37: =IF($A37>NYears*12,"",$F37-$H37) | J37: =IF($A37>NYears*12,"",$H37*RateA) | K37: =IF($A37>NYears*12,"",IF($D37=1,$J37,$K36+$J37)) | L37: =IF($A37>NYears*12,"",IF(MOD($D37,3)=0,SUM($J35:$J37),0)) | M37: =IF($A37>NYears*12,"",IF(TaxFreq="Quarterly",$K37*12/$D37,$K37)) | N37: =IF($A37>NYears*12,"",LOOKUP($M37,TaxLower,TaxRate)) | O37: =IF($A37>NYears*12,"",IF(TaxFreq="Quarterly",IF(MOD($D37,3)=0,$L37*$N37,0),IF($D37=12,$K37*$N37,0))) | P37: =IF($A37>NYears*12,"",IF($D37=1,$O37,$P36+$O37)) | Q37: =IF($A37>NYears*12,"",IF($D37=12,MIN(WdrPct*IF(WdrBase="Post-tax profit",$K37-$P37,$K37),WdrCap),0)) | R37: =IF($A37>NYears*12,"",$F37+$J37-$O37-$Q37) | S37: =IF($A37>NYears*12,"",INT($R37/$E37))
A38: =34 | B38: =IF($A38>NYears*12,"",EDATE(StartMonth,$A38-1)) | C38: =IF($A38>NYears*12,"",INT(($A38-1)/12)+1) | D38: =IF($A38>NYears*12,"",MOD($A38-1,12)+1) | E38: =IF($A38>NYears*12,"",LotValue0*(1+LotGrowth)^($C38-1)) | F38: =IF($A38>NYears*12,"",IF($A38=1,InitInvest,$R37)) | G38: =IF($A38>NYears*12,"",INT($F38/$E38)) | H38: =IF($A38>NYears*12,"",$G38*$E38) | I38: =IF($A38>NYears*12,"",$F38-$H38) | J38: =IF($A38>NYears*12,"",$H38*RateA) | K38: =IF($A38>NYears*12,"",IF($D38=1,$J38,$K37+$J38)) | L38: =IF($A38>NYears*12,"",IF(MOD($D38,3)=0,SUM($J36:$J38),0)) | M38: =IF($A38>NYears*12,"",IF(TaxFreq="Quarterly",$K38*12/$D38,$K38)) | N38: =IF($A38>NYears*12,"",LOOKUP($M38,TaxLower,TaxRate)) | O38: =IF($A38>NYears*12,"",IF(TaxFreq="Quarterly",IF(MOD($D38,3)=0,$L38*$N38,0),IF($D38=12,$K38*$N38,0))) | P38: =IF($A38>NYears*12,"",IF($D38=1,$O38,$P37+$O38)) | Q38: =IF($A38>NYears*12,"",IF($D38=12,MIN(WdrPct*IF(WdrBase="Post-tax profit",$K38-$P38,$K38),WdrCap),0)) | R38: =IF($A38>NYears*12,"",$F38+$J38-$O38-$Q38) | S38: =IF($A38>NYears*12,"",INT($R38/$E38))
A39: =35 | B39: =IF($A39>NYears*12,"",EDATE(StartMonth,$A39-1)) | C39: =IF($A39>NYears*12,"",INT(($A39-1)/12)+1) | D39: =IF($A39>NYears*12,"",MOD($A39-1,12)+1) | E39: =IF($A39>NYears*12,"",LotValue0*(1+LotGrowth)^($C39-1)) | F39: =IF($A39>NYears*12,"",IF($A39=1,InitInvest,$R38)) | G39: =IF($A39>NYears*12,"",INT($F39/$E39)) | H39: =IF($A39>NYears*12,"",$G39*$E39) | I39: =IF($A39>NYears*12,"",$F39-$H39) | J39: =IF($A39>NYears*12,"",$H39*RateA) | K39: =IF($A39>NYears*12,"",IF($D39=1,$J39,$K38+$J39)) | L39: =IF($A39>NYears*12,"",IF(MOD($D39,3)=0,SUM($J37:$J39),0)) | M39: =IF($A39>NYears*12,"",IF(TaxFreq="Quarterly",$K39*12/$D39,$K39)) | N39: =IF($A39>NYears*12,"",LOOKUP($M39,TaxLower,TaxRate)) | O39: =IF($A39>NYears*12,"",IF(TaxFreq="Quarterly",IF(MOD($D39,3)=0,$L39*$N39,0),IF($D39=12,$K39*$N39,0))) | P39: =IF($A39>NYears*12,"",IF($D39=1,$O39,$P38+$O39)) | Q39: =IF($A39>NYears*12,"",IF($D39=12,MIN(WdrPct*IF(WdrBase="Post-tax profit",$K39-$P39,$K39),WdrCap),0)) | R39: =IF($A39>NYears*12,"",$F39+$J39-$O39-$Q39) | S39: =IF($A39>NYears*12,"",INT($R39/$E39))
A40: =36 | B40: =IF($A40>NYears*12,"",EDATE(StartMonth,$A40-1)) | C40: =IF($A40>NYears*12,"",INT(($A40-1)/12)+1) | D40: =IF($A40>NYears*12,"",MOD($A40-1,12)+1) | E40: =IF($A40>NYears*12,"",LotValue0*(1+LotGrowth)^($C40-1)) | F40: =IF($A40>NYears*12,"",IF($A40=1,InitInvest,$R39)) | G40: =IF($A40>NYears*12,"",INT($F40/$E40)) | H40: =IF($A40>NYears*12,"",$G40*$E40) | I40: =IF($A40>NYears*12,"",$F40-$H40) | J40: =IF($A40>NYears*12,"",$H40*RateA) | K40: =IF($A40>NYears*12,"",IF($D40=1,$J40,$K39+$J40)) | L40: =IF($A40>NYears*12,"",IF(MOD($D40,3)=0,SUM($J38:$J40),0)) | M40: =IF($A40>NYears*12,"",IF(TaxFreq="Quarterly",$K40*12/$D40,$K40)) | N40: =IF($A40>NYears*12,"",LOOKUP($M40,TaxLower,TaxRate)) | O40: =IF($A40>NYears*12,"",IF(TaxFreq="Quarterly",IF(MOD($D40,3)=0,$L40*$N40,0),IF($D40=12,$K40*$N40,0))) | P40: =IF($A40>NYears*12,"",IF($D40=1,$O40,$P39+$O40)) | Q40: =IF($A40>NYears*12,"",IF($D40=12,MIN(WdrPct*IF(WdrBase="Post-tax profit",$K40-$P40,$K40),WdrCap),0)) | R40: =IF($A40>NYears*12,"",$F40+$J40-$O40-$Q40) | S40: =IF($A40>NYears*12,"",INT($R40/$E40))
A41: =37 | B41: =IF($A41>NYears*12,"",EDATE(StartMonth,$A41-1)) | C41: =IF($A41>NYears*12,"",INT(($A41-1)/12)+1) | D41: =IF($A41>NYears*12,"",MOD($A41-1,12)+1) | E41: =IF($A41>NYears*12,"",LotValue0*(1+LotGrowth)^($C41-1)) | F41: =IF($A41>NYears*12,"",IF($A41=1,InitInvest,$R40)) | G41: =IF($A41>NYears*12,"",INT($F41/$E41)) | H41: =IF($A41>NYears*12,"",$G41*$E41) | I41: =IF($A41>NYears*12,"",$F41-$H41) | J41: =IF($A41>NYears*12,"",$H41*RateA) | K41: =IF($A41>NYears*12,"",IF($D41=1,$J41,$K40+$J41)) | L41: =IF($A41>NYears*12,"",IF(MOD($D41,3)=0,SUM($J39:$J41),0)) | M41: =IF($A41>NYears*12,"",IF(TaxFreq="Quarterly",$K41*12/$D41,$K41)) | N41: =IF($A41>NYears*12,"",LOOKUP($M41,TaxLower,TaxRate)) | O41: =IF($A41>NYears*12,"",IF(TaxFreq="Quarterly",IF(MOD($D41,3)=0,$L41*$N41,0),IF($D41=12,$K41*$N41,0))) | P41: =IF($A41>NYears*12,"",IF($D41=1,$O41,$P40+$O41)) | Q41: =IF($A41>NYears*12,"",IF($D41=12,MIN(WdrPct*IF(WdrBase="Post-tax profit",$K41-$P41,$K41),WdrCap),0)) | R41: =IF($A41>NYears*12,"",$F41+$J41-$O41-$Q41) | S41: =IF($A41>NYears*12,"",INT($R41/$E41))
A42: =38 | B42: =IF($A42>NYears*12,"",EDATE(StartMonth,$A42-1)) | C42: =IF($A42>NYears*12,"",INT(($A42-1)/12)+1) | D42: =IF($A42>NYears*12,"",MOD($A42-1,12)+1) | E42: =IF($A42>NYears*12,"",LotValue0*(1+LotGrowth)^($C42-1)) | F42: =IF($A42>NYears*12,"",IF($A42=1,InitInvest,$R41)) | G42: =IF($A42>NYears*12,"",INT($F42/$E42)) | H42: =IF($A42>NYears*12,"",$G42*$E42) | I42: =IF($A42>NYears*12,"",$F42-$H42) | J42: =IF($A42>NYears*12,"",$H42*RateA) | K42: =IF($A42>NYears*12,"",IF($D42=1,$J42,$K41+$J42)) | L42: =IF($A42>NYears*12,"",IF(MOD($D42,3)=0,SUM($J40:$J42),0)) | M42: =IF($A42>NYears*12,"",IF(TaxFreq="Quarterly",$K42*12/$D42,$K42)) | N42: =IF($A42>NYears*12,"",LOOKUP($M42,TaxLower,TaxRate)) | O42: =IF($A42>NYears*12,"",IF(TaxFreq="Quarterly",IF(MOD($D42,3)=0,$L42*$N42,0),IF($D42=12,$K42*$N42,0))) | P42: =IF($A42>NYears*12,"",IF($D42=1,$O42,$P41+$O42)) | Q42: =IF($A42>NYears*12,"",IF($D42=12,MIN(WdrPct*IF(WdrBase="Post-tax profit",$K42-$P42,$K42),WdrCap),0)) | R42: =IF($A42>NYears*12,"",$F42+$J42-$O42-$Q42) | S42: =IF($A42>NYears*12,"",INT($R42/$E42))
A43: =39 | B43: =IF($A43>NYears*12,"",EDATE(StartMonth,$A43-1)) | C43: =IF($A43>NYears*12,"",INT(($A43-1)/12)+1) | D43: =IF($A43>NYears*12,"",MOD($A43-1,12)+1) | E43: =IF($A43>NYears*12,"",LotValue0*(1+LotGrowth)^($C43-1)) | F43: =IF($A43>NYears*12,"",IF($A43=1,InitInvest,$R42)) | G43: =IF($A43>NYears*12,"",INT($F43/$E43)) | H43: =IF($A43>NYears*12,"",$G43*$E43) | I43: =IF($A43>NYears*12,"",$F43-$H43) | J43: =IF($A43>NYears*12,"",$H43*RateA) | K43: =IF($A43>NYears*12,"",IF($D43=1,$J43,$K42+$J43)) | L43: =IF($A43>NYears*12,"",IF(MOD($D43,3)=0,SUM($J41:$J43),0)) | M43: =IF($A43>NYears*12,"",IF(TaxFreq="Quarterly",$K43*12/$D43,$K43)) | N43: =IF($A43>NYears*12,"",LOOKUP($M43,TaxLower,TaxRate)) | O43: =IF($A43>NYears*12,"",IF(TaxFreq="Quarterly",IF(MOD($D43,3)=0,$L43*$N43,0),IF($D43=12,$K43*$N43,0))) | P43: =IF($A43>NYears*12,"",IF($D43=1,$O43,$P42+$O43)) | Q43: =IF($A43>NYears*12,"",IF($D43=12,MIN(WdrPct*IF(WdrBase="Post-tax profit",$K43-$P43,$K43),WdrCap),0)) | R43: =IF($A43>NYears*12,"",$F43+$J43-$O43-$Q43) | S43: =IF($A43>NYears*12,"",INT($R43/$E43))
A44: =40 | B44: =IF($A44>NYears*12,"",EDATE(StartMonth,$A44-1)) | C44: =IF($A44>NYears*12,"",INT(($A44-1)/12)+1) | D44: =IF($A44>NYears*12,"",MOD($A44-1,12)+1) | E44: =IF($A44>NYears*12,"",LotValue0*(1+LotGrowth)^($C44-1)) | F44: =IF($A44>NYears*12,"",IF($A44=1,InitInvest,$R43)) | G44: =IF($A44>NYears*12,"",INT($F44/$E44)) | H44: =IF($A44>NYears*12,"",$G44*$E44) | I44: =IF($A44>NYears*12,"",$F44-$H44) | J44: =IF($A44>NYears*12,"",$H44*RateA) | K44: =IF($A44>NYears*12,"",IF($D44=1,$J44,$K43+$J44)) | L44: =IF($A44>NYears*12,"",IF(MOD($D44,3)=0,SUM($J42:$J44),0)) | M44: =IF($A44>NYears*12,"",IF(TaxFreq="Quarterly",$K44*12/$D44,$K44)) | N44: =IF($A44>NYears*12,"",LOOKUP($M44,TaxLower,TaxRate)) | O44: =IF($A44>NYears*12,"",IF(TaxFreq="Quarterly",IF(MOD($D44,3)=0,$L44*$N44,0),IF($D44=12,$K44*$N44,0))) | P44: =IF($A44>NYears*12,"",IF($D44=1,$O44,$P43+$O44)) | Q44: =IF($A44>NYears*12,"",IF($D44=12,MIN(WdrPct*IF(WdrBase="Post-tax profit",$K44-$P44,$K44),WdrCap),0)) | R44: =IF($A44>NYears*12,"",$F44+$J44-$O44-$Q44) | S44: =IF($A44>NYears*12,"",INT($R44/$E44))
A45: =41 | B45: =IF($A45>NYears*12,"",EDATE(StartMonth,$A45-1)) | C45: =IF($A45>NYears*12,"",INT(($A45-1)/12)+1) | D45: =IF($A45>NYears*12,"",MOD($A45-1,12)+1) | E45: =IF($A45>NYears*12,"",LotValue0*(1+LotGrowth)^($C45-1)) | F45: =IF($A45>NYears*12,"",IF($A45=1,InitInvest,$R44)) | G45: =IF($A45>NYears*12,"",INT($F45/$E45)) | H45: =IF($A45>NYears*12,"",$G45*$E45) | I45: =IF($A45>NYears*12,"",$F45-$H45) | J45: =IF($A45>NYears*12,"",$H45*RateA) | K45: =IF($A45>NYears*12,"",IF($D45=1,$J45,$K44+$J45)) | L45: =IF($A45>NYears*12,"",IF(MOD($D45,3)=0,SUM($J43:$J45),0)) | M45: =IF($A45>NYears*12,"",IF(TaxFreq="Quarterly",$K45*12/$D45,$K45)) | N45: =IF($A45>NYears*12,"",LOOKUP($M45,TaxLower,TaxRate)) | O45: =IF($A45>NYears*12,"",IF(TaxFreq="Quarterly",IF(MOD($D45,3)=0,$L45*$N45,0),IF($D45=12,$K45*$N45,0))) | P45: =IF($A45>NYears*12,"",IF($D45=1,$O45,$P44+$O45)) | Q45: =IF($A45>NYears*12,"",IF($D45=12,MIN(WdrPct*IF(WdrBase="Post-tax profit",$K45-$P45,$K45),WdrCap),0)) | R45: =IF($A45>NYears*12,"",$F45+$J45-$O45-$Q45) | S45: =IF($A45>NYears*12,"",INT($R45/$E45))
A46: =42 | B46: =IF($A46>NYears*12,"",EDATE(StartMonth,$A46-1)) | C46: =IF($A46>NYears*12,"",INT(($A46-1)/12)+1) | D46: =IF($A46>NYears*12,"",MOD($A46-1,12)+1) | E46: =IF($A46>NYears*12,"",LotValue0*(1+LotGrowth)^($C46-1)) | F46: =IF($A46>NYears*12,"",IF($A46=1,InitInvest,$R45)) | G46: =IF($A46>NYears*12,"",INT($F46/$E46)) | H46: =IF($A46>NYears*12,"",$G46*$E46) | I46: =IF($A46>NYears*12,"",$F46-$H46) | J46: =IF($A46>NYears*12,"",$H46*RateA) | K46: =IF($A46>NYears*12,"",IF($D46=1,$J46,$K45+$J46)) | L46: =IF($A46>NYears*12,"",IF(MOD($D46,3)=0,SUM($J44:$J46),0)) | M46: =IF($A46>NYears*12,"",IF(TaxFreq="Quarterly",$K46*12/$D46,$K46)) | N46: =IF($A46>NYears*12,"",LOOKUP($M46,TaxLower,TaxRate)) | O46: =IF($A46>NYears*12,"",IF(TaxFreq="Quarterly",IF(MOD($D46,3)=0,$L46*$N46,0),IF($D46=12,$K46*$N46,0))) | P46: =IF($A46>NYears*12,"",IF($D46=1,$O46,$P45+$O46)) | Q46: =IF($A46>NYears*12,"",IF($D46=12,MIN(WdrPct*IF(WdrBase="Post-tax profit",$K46-$P46,$K46),WdrCap),0)) | R46: =IF($A46>NYears*12,"",$F46+$J46-$O46-$Q46) | S46: =IF($A46>NYears*12,"",INT($R46/$E46))
A47: =43 | B47: =IF($A47>NYears*12,"",EDATE(StartMonth,$A47-1)) | C47: =IF($A47>NYears*12,"",INT(($A47-1)/12)+1) | D47: =IF($A47>NYears*12,"",MOD($A47-1,12)+1) | E47: =IF($A47>NYears*12,"",LotValue0*(1+LotGrowth)^($C47-1)) | F47: =IF($A47>NYears*12,"",IF($A47=1,InitInvest,$R46)) | G47: =IF($A47>NYears*12,"",INT($F47/$E47)) | H47: =IF($A47>NYears*12,"",$G47*$E47) | I47: =IF($A47>NYears*12,"",$F47-$H47) | J47: =IF($A47>NYears*12,"",$H47*RateA) | K47: =IF($A47>NYears*12,"",IF($D47=1,$J47,$K46+$J47)) | L47: =IF($A47>NYears*12,"",IF(MOD($D47,3)=0,SUM($J45:$J47),0)) | M47: =IF($A47>NYears*12,"",IF(TaxFreq="Quarterly",$K47*12/$D47,$K47)) | N47: =IF($A47>NYears*12,"",LOOKUP($M47,TaxLower,TaxRate)) | O47: =IF($A47>NYears*12,"",IF(TaxFreq="Quarterly",IF(MOD($D47,3)=0,$L47*$N47,0),IF($D47=12,$K47*$N47,0))) | P47: =IF($A47>NYears*12,"",IF($D47=1,$O47,$P46+$O47)) | Q47: =IF($A47>NYears*12,"",IF($D47=12,MIN(WdrPct*IF(WdrBase="Post-tax profit",$K47-$P47,$K47),WdrCap),0)) | R47: =IF($A47>NYears*12,"",$F47+$J47-$O47-$Q47) | S47: =IF($A47>NYears*12,"",INT($R47/$E47))
A48: =44 | B48: =IF($A48>NYears*12,"",EDATE(StartMonth,$A48-1)) | C48: =IF($A48>NYears*12,"",INT(($A48-1)/12)+1) | D48: =IF($A48>NYears*12,"",MOD($A48-1,12)+1) | E48: =IF($A48>NYears*12,"",LotValue0*(1+LotGrowth)^($C48-1)) | F48: =IF($A48>NYears*12,"",IF($A48=1,InitInvest,$R47)) | G48: =IF($A48>NYears*12,"",INT($F48/$E48)) | H48: =IF($A48>NYears*12,"",$G48*$E48) | I48: =IF($A48>NYears*12,"",$F48-$H48) | J48: =IF($A48>NYears*12,"",$H48*RateA) | K48: =IF($A48>NYears*12,"",IF($D48=1,$J48,$K47+$J48)) | L48: =IF($A48>NYears*12,"",IF(MOD($D48,3)=0,SUM($J46:$J48),0)) | M48: =IF($A48>NYears*12,"",IF(TaxFreq="Quarterly",$K48*12/$D48,$K48)) | N48: =IF($A48>NYears*12,"",LOOKUP($M48,TaxLower,TaxRate)) | O48: =IF($A48>NYears*12,"",IF(TaxFreq="Quarterly",IF(MOD($D48,3)=0,$L48*$N48,0),IF($D48=12,$K48*$N48,0))) | P48: =IF($A48>NYears*12,"",IF($D48=1,$O48,$P47+$O48)) | Q48: =IF($A48>NYears*12,"",IF($D48=12,MIN(WdrPct*IF(WdrBase="Post-tax profit",$K48-$P48,$K48),WdrCap),0)) | R48: =IF($A48>NYears*12,"",$F48+$J48-$O48-$Q48) | S48: =IF($A48>NYears*12,"",INT($R48/$E48))
A49: =45 | B49: =IF($A49>NYears*12,"",EDATE(StartMonth,$A49-1)) | C49: =IF($A49>NYears*12,"",INT(($A49-1)/12)+1) | D49: =IF($A49>NYears*12,"",MOD($A49-1,12)+1) | E49: =IF($A49>NYears*12,"",LotValue0*(1+LotGrowth)^($C49-1)) | F49: =IF($A49>NYears*12,"",IF($A49=1,InitInvest,$R48)) | G49: =IF($A49>NYears*12,"",INT($F49/$E49)) | H49: =IF($A49>NYears*12,"",$G49*$E49) | I49: =IF($A49>NYears*12,"",$F49-$H49) | J49: =IF($A49>NYears*12,"",$H49*RateA) | K49: =IF($A49>NYears*12,"",IF($D49=1,$J49,$K48+$J49)) | L49: =IF($A49>NYears*12,"",IF(MOD($D49,3)=0,SUM($J47:$J49),0)) | M49: =IF($A49>NYears*12,"",IF(TaxFreq="Quarterly",$K49*12/$D49,$K49)) | N49: =IF($A49>NYears*12,"",LOOKUP($M49,TaxLower,TaxRate)) | O49: =IF($A49>NYears*12,"",IF(TaxFreq="Quarterly",IF(MOD($D49,3)=0,$L49*$N49,0),IF($D49=12,$K49*$N49,0))) | P49: =IF($A49>NYears*12,"",IF($D49=1,$O49,$P48+$O49)) | Q49: =IF($A49>NYears*12,"",IF($D49=12,MIN(WdrPct*IF(WdrBase="Post-tax profit",$K49-$P49,$K49),WdrCap),0)) | R49: =IF($A49>NYears*12,"",$F49+$J49-$O49-$Q49) | S49: =IF($A49>NYears*12,"",INT($R49/$E49))
A50: =46 | B50: =IF($A50>NYears*12,"",EDATE(StartMonth,$A50-1)) | C50: =IF($A50>NYears*12,"",INT(($A50-1)/12)+1) | D50: =IF($A50>NYears*12,"",MOD($A50-1,12)+1) | E50: =IF($A50>NYears*12,"",LotValue0*(1+LotGrowth)^($C50-1)) | F50: =IF($A50>NYears*12,"",IF($A50=1,InitInvest,$R49)) | G50: =IF($A50>NYears*12,"",INT($F50/$E50)) | H50: =IF($A50>NYears*12,"",$G50*$E50) | I50: =IF($A50>NYears*12,"",$F50-$H50) | J50: =IF($A50>NYears*12,"",$H50*RateA) | K50: =IF($A50>NYears*12,"",IF($D50=1,$J50,$K49+$J50)) | L50: =IF($A50>NYears*12,"",IF(MOD($D50,3)=0,SUM($J48:$J50),0)) | M50: =IF($A50>NYears*12,"",IF(TaxFreq="Quarterly",$K50*12/$D50,$K50)) | N50: =IF($A50>NYears*12,"",LOOKUP($M50,TaxLower,TaxRate)) | O50: =IF($A50>NYears*12,"",IF(TaxFreq="Quarterly",IF(MOD($D50,3)=0,$L50*$N50,0),IF($D50=12,$K50*$N50,0))) | P50: =IF($A50>NYears*12,"",IF($D50=1,$O50,$P49+$O50)) | Q50: =IF($A50>NYears*12,"",IF($D50=12,MIN(WdrPct*IF(WdrBase="Post-tax profit",$K50-$P50,$K50),WdrCap),0)) | R50: =IF($A50>NYears*12,"",$F50+$J50-$O50-$Q50) | S50: =IF($A50>NYears*12,"",INT($R50/$E50))
A51: =47 | B51: =IF($A51>NYears*12,"",EDATE(StartMonth,$A51-1)) | C51: =IF($A51>NYears*12,"",INT(($A51-1)/12)+1) | D51: =IF($A51>NYears*12,"",MOD($A51-1,12)+1) | E51: =IF($A51>NYears*12,"",LotValue0*(1+LotGrowth)^($C51-1)) | F51: =IF($A51>NYears*12,"",IF($A51=1,InitInvest,$R50)) | G51: =IF($A51>NYears*12,"",INT($F51/$E51)) | H51: =IF($A51>NYears*12,"",$G51*$E51) | I51: =IF($A51>NYears*12,"",$F51-$H51) | J51: =IF($A51>NYears*12,"",$H51*RateA) | K51: =IF($A51>NYears*12,"",IF($D51=1,$J51,$K50+$J51)) | L51: =IF($A51>NYears*12,"",IF(MOD($D51,3)=0,SUM($J49:$J51),0)) | M51: =IF($A51>NYears*12,"",IF(TaxFreq="Quarterly",$K51*12/$D51,$K51)) | N51: =IF($A51>NYears*12,"",LOOKUP($M51,TaxLower,TaxRate)) | O51: =IF($A51>NYears*12,"",IF(TaxFreq="Quarterly",IF(MOD($D51,3)=0,$L51*$N51,0),IF($D51=12,$K51*$N51,0))) | P51: =IF($A51>NYears*12,"",IF($D51=1,$O51,$P50+$O51)) | Q51: =IF($A51>NYears*12,"",IF($D51=12,MIN(WdrPct*IF(WdrBase="Post-tax profit",$K51-$P51,$K51),WdrCap),0)) | R51: =IF($A51>NYears*12,"",$F51+$J51-$O51-$Q51) | S51: =IF($A51>NYears*12,"",INT($R51/$E51))
A52: =48 | B52: =IF($A52>NYears*12,"",EDATE(StartMonth,$A52-1)) | C52: =IF($A52>NYears*12,"",INT(($A52-1)/12)+1) | D52: =IF($A52>NYears*12,"",MOD($A52-1,12)+1) | E52: =IF($A52>NYears*12,"",LotValue0*(1+LotGrowth)^($C52-1)) | F52: =IF($A52>NYears*12,"",IF($A52=1,InitInvest,$R51)) | G52: =IF($A52>NYears*12,"",INT($F52/$E52)) | H52: =IF($A52>NYears*12,"",$G52*$E52) | I52: =IF($A52>NYears*12,"",$F52-$H52) | J52: =IF($A52>NYears*12,"",$H52*RateA) | K52: =IF($A52>NYears*12,"",IF($D52=1,$J52,$K51+$J52)) | L52: =IF($A52>NYears*12,"",IF(MOD($D52,3)=0,SUM($J50:$J52),0)) | M52: =IF($A52>NYears*12,"",IF(TaxFreq="Quarterly",$K52*12/$D52,$K52)) | N52: =IF($A52>NYears*12,"",LOOKUP($M52,TaxLower,TaxRate)) | O52: =IF($A52>NYears*12,"",IF(TaxFreq="Quarterly",IF(MOD($D52,3)=0,$L52*$N52,0),IF($D52=12,$K52*$N52,0))) | P52: =IF($A52>NYears*12,"",IF($D52=1,$O52,$P51+$O52)) | Q52: =IF($A52>NYears*12,"",IF($D52=12,MIN(WdrPct*IF(WdrBase="Post-tax profit",$K52-$P52,$K52),WdrCap),0)) | R52: =IF($A52>NYears*12,"",$F52+$J52-$O52-$Q52) | S52: =IF($A52>NYears*12,"",INT($R52/$E52))
A53: =49 | B53: =IF($A53>NYears*12,"",EDATE(StartMonth,$A53-1)) | C53: =IF($A53>NYears*12,"",INT(($A53-1)/12)+1) | D53: =IF($A53>NYears*12,"",MOD($A53-1,12)+1) | E53: =IF($A53>NYears*12,"",LotValue0*(1+LotGrowth)^($C53-1)) | F53: =IF($A53>NYears*12,"",IF($A53=1,InitInvest,$R52)) | G53: =IF($A53>NYears*12,"",INT($F53/$E53)) | H53: =IF($A53>NYears*12,"",$G53*$E53) | I53: =IF($A53>NYears*12,"",$F53-$H53) | J53: =IF($A53>NYears*12,"",$H53*RateA) | K53: =IF($A53>NYears*12,"",IF($D53=1,$J53,$K52+$J53)) | L53: =IF($A53>NYears*12,"",IF(MOD($D53,3)=0,SUM($J51:$J53),0)) | M53: =IF($A53>NYears*12,"",IF(TaxFreq="Quarterly",$K53*12/$D53,$K53)) | N53: =IF($A53>NYears*12,"",LOOKUP($M53,TaxLower,TaxRate)) | O53: =IF($A53>NYears*12,"",IF(TaxFreq="Quarterly",IF(MOD($D53,3)=0,$L53*$N53,0),IF($D53=12,$K53*$N53,0))) | P53: =IF($A53>NYears*12,"",IF($D53=1,$O53,$P52+$O53)) | Q53: =IF($A53>NYears*12,"",IF($D53=12,MIN(WdrPct*IF(WdrBase="Post-tax profit",$K53-$P53,$K53),WdrCap),0)) | R53: =IF($A53>NYears*12,"",$F53+$J53-$O53-$Q53) | S53: =IF($A53>NYears*12,"",INT($R53/$E53))
A54: =50 | B54: =IF($A54>NYears*12,"",EDATE(StartMonth,$A54-1)) | C54: =IF($A54>NYears*12,"",INT(($A54-1)/12)+1) | D54: =IF($A54>NYears*12,"",MOD($A54-1,12)+1) | E54: =IF($A54>NYears*12,"",LotValue0*(1+LotGrowth)^($C54-1)) | F54: =IF($A54>NYears*12,"",IF($A54=1,InitInvest,$R53)) | G54: =IF($A54>NYears*12,"",INT($F54/$E54)) | H54: =IF($A54>NYears*12,"",$G54*$E54) | I54: =IF($A54>NYears*12,"",$F54-$H54) | J54: =IF($A54>NYears*12,"",$H54*RateA) | K54: =IF($A54>NYears*12,"",IF($D54=1,$J54,$K53+$J54)) | L54: =IF($A54>NYears*12,"",IF(MOD($D54,3)=0,SUM($J52:$J54),0)) | M54: =IF($A54>NYears*12,"",IF(TaxFreq="Quarterly",$K54*12/$D54,$K54)) | N54: =IF($A54>NYears*12,"",LOOKUP($M54,TaxLower,TaxRate)) | O54: =IF($A54>NYears*12,"",IF(TaxFreq="Quarterly",IF(MOD($D54,3)=0,$L54*$N54,0),IF($D54=12,$K54*$N54,0))) | P54: =IF($A54>NYears*12,"",IF($D54=1,$O54,$P53+$O54)) | Q54: =IF($A54>NYears*12,"",IF($D54=12,MIN(WdrPct*IF(WdrBase="Post-tax profit",$K54-$P54,$K54),WdrCap),0)) | R54: =IF($A54>NYears*12,"",$F54+$J54-$O54-$Q54) | S54: =IF($A54>NYears*12,"",INT($R54/$E54))
A55: =51 | B55: =IF($A55>NYears*12,"",EDATE(StartMonth,$A55-1)) | C55: =IF($A55>NYears*12,"",INT(($A55-1)/12)+1) | D55: =IF($A55>NYears*12,"",MOD($A55-1,12)+1) | E55: =IF($A55>NYears*12,"",LotValue0*(1+LotGrowth)^($C55-1)) | F55: =IF($A55>NYears*12,"",IF($A55=1,InitInvest,$R54)) | G55: =IF($A55>NYears*12,"",INT($F55/$E55)) | H55: =IF($A55>NYears*12,"",$G55*$E55) | I55: =IF($A55>NYears*12,"",$F55-$H55) | J55: =IF($A55>NYears*12,"",$H55*RateA) | K55: =IF($A55>NYears*12,"",IF($D55=1,$J55,$K54+$J55)) | L55: =IF($A55>NYears*12,"",IF(MOD($D55,3)=0,SUM($J53:$J55),0)) | M55: =IF($A55>NYears*12,"",IF(TaxFreq="Quarterly",$K55*12/$D55,$K55)) | N55: =IF($A55>NYears*12,"",LOOKUP($M55,TaxLower,TaxRate)) | O55: =IF($A55>NYears*12,"",IF(TaxFreq="Quarterly",IF(MOD($D55,3)=0,$L55*$N55,0),IF($D55=12,$K55*$N55,0))) | P55: =IF($A55>NYears*12,"",IF($D55=1,$O55,$P54+$O55)) | Q55: =IF($A55>NYears*12,"",IF($D55=12,MIN(WdrPct*IF(WdrBase="Post-tax profit",$K55-$P55,$K55),WdrCap),0)) | R55: =IF($A55>NYears*12,"",$F55+$J55-$O55-$Q55) | S55: =IF($A55>NYears*12,"",INT($R55/$E55))
A56: =52 | B56: =IF($A56>NYears*12,"",EDATE(StartMonth,$A56-1)) | C56: =IF($A56>NYears*12,"",INT(($A56-1)/12)+1) | D56: =IF($A56>NYears*12,"",MOD($A56-1,12)+1) | E56: =IF($A56>NYears*12,"",LotValue0*(1+LotGrowth)^($C56-1)) | F56: =IF($A56>NYears*12,"",IF($A56=1,InitInvest,$R55)) | G56: =IF($A56>NYears*12,"",INT($F56/$E56)) | H56: =IF($A56>NYears*12,"",$G56*$E56) | I56: =IF($A56>NYears*12,"",$F56-$H56) | J56: =IF($A56>NYears*12,"",$H56*RateA) | K56: =IF($A56>NYears*12,"",IF($D56=1,$J56,$K55+$J56)) | L56: =IF($A56>NYears*12,"",IF(MOD($D56,3)=0,SUM($J54:$J56),0)) | M56: =IF($A56>NYears*12,"",IF(TaxFreq="Quarterly",$K56*12/$D56,$K56)) | N56: =IF($A56>NYears*12,"",LOOKUP($M56,TaxLower,TaxRate)) | O56: =IF($A56>NYears*12,"",IF(TaxFreq="Quarterly",IF(MOD($D56,3)=0,$L56*$N56,0),IF($D56=12,$K56*$N56,0))) | P56: =IF($A56>NYears*12,"",IF($D56=1,$O56,$P55+$O56)) | Q56: =IF($A56>NYears*12,"",IF($D56=12,MIN(WdrPct*IF(WdrBase="Post-tax profit",$K56-$P56,$K56),WdrCap),0)) | R56: =IF($A56>NYears*12,"",$F56+$J56-$O56-$Q56) | S56: =IF($A56>NYears*12,"",INT($R56/$E56))
A57: =53 | B57: =IF($A57>NYears*12,"",EDATE(StartMonth,$A57-1)) | C57: =IF($A57>NYears*12,"",INT(($A57-1)/12)+1) | D57: =IF($A57>NYears*12,"",MOD($A57-1,12)+1) | E57: =IF($A57>NYears*12,"",LotValue0*(1+LotGrowth)^($C57-1)) | F57: =IF($A57>NYears*12,"",IF($A57=1,InitInvest,$R56)) | G57: =IF($A57>NYears*12,"",INT($F57/$E57)) | H57: =IF($A57>NYears*12,"",$G57*$E57) | I57: =IF($A57>NYears*12,"",$F57-$H57) | J57: =IF($A57>NYears*12,"",$H57*RateA) | K57: =IF($A57>NYears*12,"",IF($D57=1,$J57,$K56+$J57)) | L57: =IF($A57>NYears*12,"",IF(MOD($D57,3)=0,SUM($J55:$J57),0)) | M57: =IF($A57>NYears*12,"",IF(TaxFreq="Quarterly",$K57*12/$D57,$K57)) | N57: =IF($A57>NYears*12,"",LOOKUP($M57,TaxLower,TaxRate)) | O57: =IF($A57>NYears*12,"",IF(TaxFreq="Quarterly",IF(MOD($D57,3)=0,$L57*$N57,0),IF($D57=12,$K57*$N57,0))) | P57: =IF($A57>NYears*12,"",IF($D57=1,$O57,$P56+$O57)) | Q57: =IF($A57>NYears*12,"",IF($D57=12,MIN(WdrPct*IF(WdrBase="Post-tax profit",$K57-$P57,$K57),WdrCap),0)) | R57: =IF($A57>NYears*12,"",$F57+$J57-$O57-$Q57) | S57: =IF($A57>NYears*12,"",INT($R57/$E57))
A58: =54 | B58: =IF($A58>NYears*12,"",EDATE(StartMonth,$A58-1)) | C58: =IF($A58>NYears*12,"",INT(($A58-1)/12)+1) | D58: =IF($A58>NYears*12,"",MOD($A58-1,12)+1) | E58: =IF($A58>NYears*12,"",LotValue0*(1+LotGrowth)^($C58-1)) | F58: =IF($A58>NYears*12,"",IF($A58=1,InitInvest,$R57)) | G58: =IF($A58>NYears*12,"",INT($F58/$E58)) | H58: =IF($A58>NYears*12,"",$G58*$E58) | I58: =IF($A58>NYears*12,"",$F58-$H58) | J58: =IF($A58>NYears*12,"",$H58*RateA) | K58: =IF($A58>NYears*12,"",IF($D58=1,$J58,$K57+$J58)) | L58: =IF($A58>NYears*12,"",IF(MOD($D58,3)=0,SUM($J56:$J58),0)) | M58: =IF($A58>NYears*12,"",IF(TaxFreq="Quarterly",$K58*12/$D58,$K58)) | N58: =IF($A58>NYears*12,"",LOOKUP($M58,TaxLower,TaxRate)) | O58: =IF($A58>NYears*12,"",IF(TaxFreq="Quarterly",IF(MOD($D58,3)=0,$L58*$N58,0),IF($D58=12,$K58*$N58,0))) | P58: =IF($A58>NYears*12,"",IF($D58=1,$O58,$P57+$O58)) | Q58: =IF($A58>NYears*12,"",IF($D58=12,MIN(WdrPct*IF(WdrBase="Post-tax profit",$K58-$P58,$K58),WdrCap),0)) | R58: =IF($A58>NYears*12,"",$F58+$J58-$O58-$Q58) | S58: =IF($A58>NYears*12,"",INT($R58/$E58))
A59: =55 | B59: =IF($A59>NYears*12,"",EDATE(StartMonth,$A59-1)) | C59: =IF($A59>NYears*12,"",INT(($A59-1)/12)+1) | D59: =IF($A59>NYears*12,"",MOD($A59-1,12)+1) | E59: =IF($A59>NYears*12,"",LotValue0*(1+LotGrowth)^($C59-1)) | F59: =IF($A59>NYears*12,"",IF($A59=1,InitInvest,$R58)) | G59: =IF($A59>NYears*12,"",INT($F59/$E59)) | H59: =IF($A59>NYears*12,"",$G59*$E59) | I59: =IF($A59>NYears*12,"",$F59-$H59) | J59: =IF($A59>NYears*12,"",$H59*RateA) | K59: =IF($A59>NYears*12,"",IF($D59=1,$J59,$K58+$J59)) | L59: =IF($A59>NYears*12,"",IF(MOD($D59,3)=0,SUM($J57:$J59),0)) | M59: =IF($A59>NYears*12,"",IF(TaxFreq="Quarterly",$K59*12/$D59,$K59)) | N59: =IF($A59>NYears*12,"",LOOKUP($M59,TaxLower,TaxRate)) | O59: =IF($A59>NYears*12,"",IF(TaxFreq="Quarterly",IF(MOD($D59,3)=0,$L59*$N59,0),IF($D59=12,$K59*$N59,0))) | P59: =IF($A59>NYears*12,"",IF($D59=1,$O59,$P58+$O59)) | Q59: =IF($A59>NYears*12,"",IF($D59=12,MIN(WdrPct*IF(WdrBase="Post-tax profit",$K59-$P59,$K59),WdrCap),0)) | R59: =IF($A59>NYears*12,"",$F59+$J59-$O59-$Q59) | S59: =IF($A59>NYears*12,"",INT($R59/$E59))
A60: =56 | B60: =IF($A60>NYears*12,"",EDATE(StartMonth,$A60-1)) | C60: =IF($A60>NYears*12,"",INT(($A60-1)/12)+1) | D60: =IF($A60>NYears*12,"",MOD($A60-1,12)+1) | E60: =IF($A60>NYears*12,"",LotValue0*(1+LotGrowth)^($C60-1)) | F60: =IF($A60>NYears*12,"",IF($A60=1,InitInvest,$R59)) | G60: =IF($A60>NYears*12,"",INT($F60/$E60)) | H60: =IF($A60>NYears*12,"",$G60*$E60) | I60: =IF($A60>NYears*12,"",$F60-$H60) | J60: =IF($A60>NYears*12,"",$H60*RateA) | K60: =IF($A60>NYears*12,"",IF($D60=1,$J60,$K59+$J60)) | L60: =IF($A60>NYears*12,"",IF(MOD($D60,3)=0,SUM($J58:$J60),0)) | M60: =IF($A60>NYears*12,"",IF(TaxFreq="Quarterly",$K60*12/$D60,$K60)) | N60: =IF($A60>NYears*12,"",LOOKUP($M60,TaxLower,TaxRate)) | O60: =IF($A60>NYears*12,"",IF(TaxFreq="Quarterly",IF(MOD($D60,3)=0,$L60*$N60,0),IF($D60=12,$K60*$N60,0))) | P60: =IF($A60>NYears*12,"",IF($D60=1,$O60,$P59+$O60)) | Q60: =IF($A60>NYears*12,"",IF($D60=12,MIN(WdrPct*IF(WdrBase="Post-tax profit",$K60-$P60,$K60),WdrCap),0)) | R60: =IF($A60>NYears*12,"",$F60+$J60-$O60-$Q60) | S60: =IF($A60>NYears*12,"",INT($R60/$E60))
A61: =57 | B61: =IF($A61>NYears*12,"",EDATE(StartMonth,$A61-1)) | C61: =IF($A61>NYears*12,"",INT(($A61-1)/12)+1) | D61: =IF($A61>NYears*12,"",MOD($A61-1,12)+1) | E61: =IF($A61>NYears*12,"",LotValue0*(1+LotGrowth)^($C61-1)) | F61: =IF($A61>NYears*12,"",IF($A61=1,InitInvest,$R60)) | G61: =IF($A61>NYears*12,"",INT($F61/$E61)) | H61: =IF($A61>NYears*12,"",$G61*$E61) | I61: =IF($A61>NYears*12,"",$F61-$H61) | J61: =IF($A61>NYears*12,"",$H61*RateA) | K61: =IF($A61>NYears*12,"",IF($D61=1,$J61,$K60+$J61)) | L61: =IF($A61>NYears*12,"",IF(MOD($D61,3)=0,SUM($J59:$J61),0)) | M61: =IF($A61>NYears*12,"",IF(TaxFreq="Quarterly",$K61*12/$D61,$K61)) | N61: =IF($A61>NYears*12,"",LOOKUP($M61,TaxLower,TaxRate)) | O61: =IF($A61>NYears*12,"",IF(TaxFreq="Quarterly",IF(MOD($D61,3)=0,$L61*$N61,0),IF($D61=12,$K61*$N61,0))) | P61: =IF($A61>NYears*12,"",IF($D61=1,$O61,$P60+$O61)) | Q61: =IF($A61>NYears*12,"",IF($D61=12,MIN(WdrPct*IF(WdrBase="Post-tax profit",$K61-$P61,$K61),WdrCap),0)) | R61: =IF($A61>NYears*12,"",$F61+$J61-$O61-$Q61) | S61: =IF($A61>NYears*12,"",INT($R61/$E61))
A62: =58 | B62: =IF($A62>NYears*12,"",EDATE(StartMonth,$A62-1)) | C62: =IF($A62>NYears*12,"",INT(($A62-1)/12)+1) | D62: =IF($A62>NYears*12,"",MOD($A62-1,12)+1) | E62: =IF($A62>NYears*12,"",LotValue0*(1+LotGrowth)^($C62-1)) | F62: =IF($A62>NYears*12,"",IF($A62=1,InitInvest,$R61)) | G62: =IF($A62>NYears*12,"",INT($F62/$E62)) | H62: =IF($A62>NYears*12,"",$G62*$E62) | I62: =IF($A62>NYears*12,"",$F62-$H62) | J62: =IF($A62>NYears*12,"",$H62*RateA) | K62: =IF($A62>NYears*12,"",IF($D62=1,$J62,$K61+$J62)) | L62: =IF($A62>NYears*12,"",IF(MOD($D62,3)=0,SUM($J60:$J62),0)) | M62: =IF($A62>NYears*12,"",IF(TaxFreq="Quarterly",$K62*12/$D62,$K62)) | N62: =IF($A62>NYears*12,"",LOOKUP($M62,TaxLower,TaxRate)) | O62: =IF($A62>NYears*12,"",IF(TaxFreq="Quarterly",IF(MOD($D62,3)=0,$L62*$N62,0),IF($D62=12,$K62*$N62,0))) | P62: =IF($A62>NYears*12,"",IF($D62=1,$O62,$P61+$O62)) | Q62: =IF($A62>NYears*12,"",IF($D62=12,MIN(WdrPct*IF(WdrBase="Post-tax profit",$K62-$P62,$K62),WdrCap),0)) | R62: =IF($A62>NYears*12,"",$F62+$J62-$O62-$Q62) | S62: =IF($A62>NYears*12,"",INT($R62/$E62))
A63: =59 | B63: =IF($A63>NYears*12,"",EDATE(StartMonth,$A63-1)) | C63: =IF($A63>NYears*12,"",INT(($A63-1)/12)+1) | D63: =IF($A63>NYears*12,"",MOD($A63-1,12)+1) | E63: =IF($A63>NYears*12,"",LotValue0*(1+LotGrowth)^($C63-1)) | F63: =IF($A63>NYears*12,"",IF($A63=1,InitInvest,$R62)) | G63: =IF($A63>NYears*12,"",INT($F63/$E63)) | H63: =IF($A63>NYears*12,"",$G63*$E63) | I63: =IF($A63>NYears*12,"",$F63-$H63) | J63: =IF($A63>NYears*12,"",$H63*RateA) | K63: =IF($A63>NYears*12,"",IF($D63=1,$J63,$K62+$J63)) | L63: =IF($A63>NYears*12,"",IF(MOD($D63,3)=0,SUM($J61:$J63),0)) | M63: =IF($A63>NYears*12,"",IF(TaxFreq="Quarterly",$K63*12/$D63,$K63)) | N63: =IF($A63>NYears*12,"",LOOKUP($M63,TaxLower,TaxRate)) | O63: =IF($A63>NYears*12,"",IF(TaxFreq="Quarterly",IF(MOD($D63,3)=0,$L63*$N63,0),IF($D63=12,$K63*$N63,0))) | P63: =IF($A63>NYears*12,"",IF($D63=1,$O63,$P62+$O63)) | Q63: =IF($A63>NYears*12,"",IF($D63=12,MIN(WdrPct*IF(WdrBase="Post-tax profit",$K63-$P63,$K63),WdrCap),0)) | R63: =IF($A63>NYears*12,"",$F63+$J63-$O63-$Q63) | S63: =IF($A63>NYears*12,"",INT($R63/$E63))
A64: =60 | B64: =IF($A64>NYears*12,"",EDATE(StartMonth,$A64-1)) | C64: =IF($A64>NYears*12,"",INT(($A64-1)/12)+1) | D64: =IF($A64>NYears*12,"",MOD($A64-1,12)+1) | E64: =IF($A64>NYears*12,"",LotValue0*(1+LotGrowth)^($C64-1)) | F64: =IF($A64>NYears*12,"",IF($A64=1,InitInvest,$R63)) | G64: =IF($A64>NYears*12,"",INT($F64/$E64)) | H64: =IF($A64>NYears*12,"",$G64*$E64) | I64: =IF($A64>NYears*12,"",$F64-$H64) | J64: =IF($A64>NYears*12,"",$H64*RateA) | K64: =IF($A64>NYears*12,"",IF($D64=1,$J64,$K63+$J64)) | L64: =IF($A64>NYears*12,"",IF(MOD($D64,3)=0,SUM($J62:$J64),0)) | M64: =IF($A64>NYears*12,"",IF(TaxFreq="Quarterly",$K64*12/$D64,$K64)) | N64: =IF($A64>NYears*12,"",LOOKUP($M64,TaxLower,TaxRate)) | O64: =IF($A64>NYears*12,"",IF(TaxFreq="Quarterly",IF(MOD($D64,3)=0,$L64*$N64,0),IF($D64=12,$K64*$N64,0))) | P64: =IF($A64>NYears*12,"",IF($D64=1,$O64,$P63+$O64)) | Q64: =IF($A64>NYears*12,"",IF($D64=12,MIN(WdrPct*IF(WdrBase="Post-tax profit",$K64-$P64,$K64),WdrCap),0)) | R64: =IF($A64>NYears*12,"",$F64+$J64-$O64-$Q64) | S64: =IF($A64>NYears*12,"",INT($R64/$E64))
A65: =61 | B65: =IF($A65>NYears*12,"",EDATE(StartMonth,$A65-1)) | C65: =IF($A65>NYears*12,"",INT(($A65-1)/12)+1) | D65: =IF($A65>NYears*12,"",MOD($A65-1,12)+1) | E65: =IF($A65>NYears*12,"",LotValue0*(1+LotGrowth)^($C65-1)) | F65: =IF($A65>NYears*12,"",IF($A65=1,InitInvest,$R64)) | G65: =IF($A65>NYears*12,"",INT($F65/$E65)) | H65: =IF($A65>NYears*12,"",$G65*$E65) | I65: =IF($A65>NYears*12,"",$F65-$H65) | J65: =IF($A65>NYears*12,"",$H65*RateA) | K65: =IF($A65>NYears*12,"",IF($D65=1,$J65,$K64+$J65)) | L65: =IF($A65>NYears*12,"",IF(MOD($D65,3)=0,SUM($J63:$J65),0)) | M65: =IF($A65>NYears*12,"",IF(TaxFreq="Quarterly",$K65*12/$D65,$K65)) | N65: =IF($A65>NYears*12,"",LOOKUP($M65,TaxLower,TaxRate)) | O65: =IF($A65>NYears*12,"",IF(TaxFreq="Quarterly",IF(MOD($D65,3)=0,$L65*$N65,0),IF($D65=12,$K65*$N65,0))) | P65: =IF($A65>NYears*12,"",IF($D65=1,$O65,$P64+$O65)) | Q65: =IF($A65>NYears*12,"",IF($D65=12,MIN(WdrPct*IF(WdrBase="Post-tax profit",$K65-$P65,$K65),WdrCap),0)) | R65: =IF($A65>NYears*12,"",$F65+$J65-$O65-$Q65) | S65: =IF($A65>NYears*12,"",INT($R65/$E65))
A66: =62 | B66: =IF($A66>NYears*12,"",EDATE(StartMonth,$A66-1)) | C66: =IF($A66>NYears*12,"",INT(($A66-1)/12)+1) | D66: =IF($A66>NYears*12,"",MOD($A66-1,12)+1) | E66: =IF($A66>NYears*12,"",LotValue0*(1+LotGrowth)^($C66-1)) | F66: =IF($A66>NYears*12,"",IF($A66=1,InitInvest,$R65)) | G66: =IF($A66>NYears*12,"",INT($F66/$E66)) | H66: =IF($A66>NYears*12,"",$G66*$E66) | I66: =IF($A66>NYears*12,"",$F66-$H66) | J66: =IF($A66>NYears*12,"",$H66*RateA) | K66: =IF($A66>NYears*12,"",IF($D66=1,$J66,$K65+$J66)) | L66: =IF($A66>NYears*12,"",IF(MOD($D66,3)=0,SUM($J64:$J66),0)) | M66: =IF($A66>NYears*12,"",IF(TaxFreq="Quarterly",$K66*12/$D66,$K66)) | N66: =IF($A66>NYears*12,"",LOOKUP($M66,TaxLower,TaxRate)) | O66: =IF($A66>NYears*12,"",IF(TaxFreq="Quarterly",IF(MOD($D66,3)=0,$L66*$N66,0),IF($D66=12,$K66*$N66,0))) | P66: =IF($A66>NYears*12,"",IF($D66=1,$O66,$P65+$O66)) | Q66: =IF($A66>NYears*12,"",IF($D66=12,MIN(WdrPct*IF(WdrBase="Post-tax profit",$K66-$P66,$K66),WdrCap),0)) | R66: =IF($A66>NYears*12,"",$F66+$J66-$O66-$Q66) | S66: =IF($A66>NYears*12,"",INT($R66/$E66))
A67: =63 | B67: =IF($A67>NYears*12,"",EDATE(StartMonth,$A67-1)) | C67: =IF($A67>NYears*12,"",INT(($A67-1)/12)+1) | D67: =IF($A67>NYears*12,"",MOD($A67-1,12)+1) | E67: =IF($A67>NYears*12,"",LotValue0*(1+LotGrowth)^($C67-1)) | F67: =IF($A67>NYears*12,"",IF($A67=1,InitInvest,$R66)) | G67: =IF($A67>NYears*12,"",INT($F67/$E67)) | H67: =IF($A67>NYears*12,"",$G67*$E67) | I67: =IF($A67>NYears*12,"",$F67-$H67) | J67: =IF($A67>NYears*12,"",$H67*RateA) | K67: =IF($A67>NYears*12,"",IF($D67=1,$J67,$K66+$J67)) | L67: =IF($A67>NYears*12,"",IF(MOD($D67,3)=0,SUM($J65:$J67),0)) | M67: =IF($A67>NYears*12,"",IF(TaxFreq="Quarterly",$K67*12/$D67,$K67)) | N67: =IF($A67>NYears*12,"",LOOKUP($M67,TaxLower,TaxRate)) | O67: =IF($A67>NYears*12,"",IF(TaxFreq="Quarterly",IF(MOD($D67,3)=0,$L67*$N67,0),IF($D67=12,$K67*$N67,0))) | P67: =IF($A67>NYears*12,"",IF($D67=1,$O67,$P66+$O67)) | Q67: =IF($A67>NYears*12,"",IF($D67=12,MIN(WdrPct*IF(WdrBase="Post-tax profit",$K67-$P67,$K67),WdrCap),0)) | R67: =IF($A67>NYears*12,"",$F67+$J67-$O67-$Q67) | S67: =IF($A67>NYears*12,"",INT($R67/$E67))
A68: =64 | B68: =IF($A68>NYears*12,"",EDATE(StartMonth,$A68-1)) | C68: =IF($A68>NYears*12,"",INT(($A68-1)/12)+1) | D68: =IF($A68>NYears*12,"",MOD($A68-1,12)+1) | E68: =IF($A68>NYears*12,"",LotValue0*(1+LotGrowth)^($C68-1)) | F68: =IF($A68>NYears*12,"",IF($A68=1,InitInvest,$R67)) | G68: =IF($A68>NYears*12,"",INT($F68/$E68)) | H68: =IF($A68>NYears*12,"",$G68*$E68) | I68: =IF($A68>NYears*12,"",$F68-$H68) | J68: =IF($A68>NYears*12,"",$H68*RateA) | K68: =IF($A68>NYears*12,"",IF($D68=1,$J68,$K67+$J68)) | L68: =IF($A68>NYears*12,"",IF(MOD($D68,3)=0,SUM($J66:$J68),0)) | M68: =IF($A68>NYears*12,"",IF(TaxFreq="Quarterly",$K68*12/$D68,$K68)) | N68: =IF($A68>NYears*12,"",LOOKUP($M68,TaxLower,TaxRate)) | O68: =IF($A68>NYears*12,"",IF(TaxFreq="Quarterly",IF(MOD($D68,3)=0,$L68*$N68,0),IF($D68=12,$K68*$N68,0))) | P68: =IF($A68>NYears*12,"",IF($D68=1,$O68,$P67+$O68)) | Q68: =IF($A68>NYears*12,"",IF($D68=12,MIN(WdrPct*IF(WdrBase="Post-tax profit",$K68-$P68,$K68),WdrCap),0)) | R68: =IF($A68>NYears*12,"",$F68+$J68-$O68-$Q68) | S68: =IF($A68>NYears*12,"",INT($R68/$E68))
A69: =65 | B69: =IF($A69>NYears*12,"",EDATE(StartMonth,$A69-1)) | C69: =IF($A69>NYears*12,"",INT(($A69-1)/12)+1) | D69: =IF($A69>NYears*12,"",MOD($A69-1,12)+1) | E69: =IF($A69>NYears*12,"",LotValue0*(1+LotGrowth)^($C69-1)) | F69: =IF($A69>NYears*12,"",IF($A69=1,InitInvest,$R68)) | G69: =IF($A69>NYears*12,"",INT($F69/$E69)) | H69: =IF($A69>NYears*12,"",$G69*$E69) | I69: =IF($A69>NYears*12,"",$F69-$H69) | J69: =IF($A69>NYears*12,"",$H69*RateA) | K69: =IF($A69>NYears*12,"",IF($D69=1,$J69,$K68+$J69)) | L69: =IF($A69>NYears*12,"",IF(MOD($D69,3)=0,SUM($J67:$J69),0)) | M69: =IF($A69>NYears*12,"",IF(TaxFreq="Quarterly",$K69*12/$D69,$K69)) | N69: =IF($A69>NYears*12,"",LOOKUP($M69,TaxLower,TaxRate)) | O69: =IF($A69>NYears*12,"",IF(TaxFreq="Quarterly",IF(MOD($D69,3)=0,$L69*$N69,0),IF($D69=12,$K69*$N69,0))) | P69: =IF($A69>NYears*12,"",IF($D69=1,$O69,$P68+$O69)) | Q69: =IF($A69>NYears*12,"",IF($D69=12,MIN(WdrPct*IF(WdrBase="Post-tax profit",$K69-$P69,$K69),WdrCap),0)) | R69: =IF($A69>NYears*12,"",$F69+$J69-$O69-$Q69) | S69: =IF($A69>NYears*12,"",INT($R69/$E69))
A70: =66 | B70: =IF($A70>NYears*12,"",EDATE(StartMonth,$A70-1)) | C70: =IF($A70>NYears*12,"",INT(($A70-1)/12)+1) | D70: =IF($A70>NYears*12,"",MOD($A70-1,12)+1) | E70: =IF($A70>NYears*12,"",LotValue0*(1+LotGrowth)^($C70-1)) | F70: =IF($A70>NYears*12,"",IF($A70=1,InitInvest,$R69)) | G70: =IF($A70>NYears*12,"",INT($F70/$E70)) | H70: =IF($A70>NYears*12,"",$G70*$E70) | I70: =IF($A70>NYears*12,"",$F70-$H70) | J70: =IF($A70>NYears*12,"",$H70*RateA) | K70: =IF($A70>NYears*12,"",IF($D70=1,$J70,$K69+$J70)) | L70: =IF($A70>NYears*12,"",IF(MOD($D70,3)=0,SUM($J68:$J70),0)) | M70: =IF($A70>NYears*12,"",IF(TaxFreq="Quarterly",$K70*12/$D70,$K70)) | N70: =IF($A70>NYears*12,"",LOOKUP($M70,TaxLower,TaxRate)) | O70: =IF($A70>NYears*12,"",IF(TaxFreq="Quarterly",IF(MOD($D70,3)=0,$L70*$N70,0),IF($D70=12,$K70*$N70,0))) | P70: =IF($A70>NYears*12,"",IF($D70=1,$O70,$P69+$O70)) | Q70: =IF($A70>NYears*12,"",IF($D70=12,MIN(WdrPct*IF(WdrBase="Post-tax profit",$K70-$P70,$K70),WdrCap),0)) | R70: =IF($A70>NYears*12,"",$F70+$J70-$O70-$Q70) | S70: =IF($A70>NYears*12,"",INT($R70/$E70))
A71: =67 | B71: =IF($A71>NYears*12,"",EDATE(StartMonth,$A71-1)) | C71: =IF($A71>NYears*12,"",INT(($A71-1)/12)+1) | D71: =IF($A71>NYears*12,"",MOD($A71-1,12)+1) | E71: =IF($A71>NYears*12,"",LotValue0*(1+LotGrowth)^($C71-1)) | F71: =IF($A71>NYears*12,"",IF($A71=1,InitInvest,$R70)) | G71: =IF($A71>NYears*12,"",INT($F71/$E71)) | H71: =IF($A71>NYears*12,"",$G71*$E71) | I71: =IF($A71>NYears*12,"",$F71-$H71) | J71: =IF($A71>NYears*12,"",$H71*RateA) | K71: =IF($A71>NYears*12,"",IF($D71=1,$J71,$K70+$J71)) | L71: =IF($A71>NYears*12,"",IF(MOD($D71,3)=0,SUM($J69:$J71),0)) | M71: =IF($A71>NYears*12,"",IF(TaxFreq="Quarterly",$K71*12/$D71,$K71)) | N71: =IF($A71>NYears*12,"",LOOKUP($M71,TaxLower,TaxRate)) | O71: =IF($A71>NYears*12,"",IF(TaxFreq="Quarterly",IF(MOD($D71,3)=0,$L71*$N71,0),IF($D71=12,$K71*$N71,0))) | P71: =IF($A71>NYears*12,"",IF($D71=1,$O71,$P70+$O71)) | Q71: =IF($A71>NYears*12,"",IF($D71=12,MIN(WdrPct*IF(WdrBase="Post-tax profit",$K71-$P71,$K71),WdrCap),0)) | R71: =IF($A71>NYears*12,"",$F71+$J71-$O71-$Q71) | S71: =IF($A71>NYears*12,"",INT($R71/$E71))
A72: =68 | B72: =IF($A72>NYears*12,"",EDATE(StartMonth,$A72-1)) | C72: =IF($A72>NYears*12,"",INT(($A72-1)/12)+1) | D72: =IF($A72>NYears*12,"",MOD($A72-1,12)+1) | E72: =IF($A72>NYears*12,"",LotValue0*(1+LotGrowth)^($C72-1)) | F72: =IF($A72>NYears*12,"",IF($A72=1,InitInvest,$R71)) | G72: =IF($A72>NYears*12,"",INT($F72/$E72)) | H72: =IF($A72>NYears*12,"",$G72*$E72) | I72: =IF($A72>NYears*12,"",$F72-$H72) | J72: =IF($A72>NYears*12,"",$H72*RateA) | K72: =IF($A72>NYears*12,"",IF($D72=1,$J72,$K71+$J72)) | L72: =IF($A72>NYears*12,"",IF(MOD($D72,3)=0,SUM($J70:$J72),0)) | M72: =IF($A72>NYears*12,"",IF(TaxFreq="Quarterly",$K72*12/$D72,$K72)) | N72: =IF($A72>NYears*12,"",LOOKUP($M72,TaxLower,TaxRate)) | O72: =IF($A72>NYears*12,"",IF(TaxFreq="Quarterly",IF(MOD($D72,3)=0,$L72*$N72,0),IF($D72=12,$K72*$N72,0))) | P72: =IF($A72>NYears*12,"",IF($D72=1,$O72,$P71+$O72)) | Q72: =IF($A72>NYears*12,"",IF($D72=12,MIN(WdrPct*IF(WdrBase="Post-tax profit",$K72-$P72,$K72),WdrCap),0)) | R72: =IF($A72>NYears*12,"",$F72+$J72-$O72-$Q72) | S72: =IF($A72>NYears*12,"",INT($R72/$E72))
A73: =69 | B73: =IF($A73>NYears*12,"",EDATE(StartMonth,$A73-1)) | C73: =IF($A73>NYears*12,"",INT(($A73-1)/12)+1) | D73: =IF($A73>NYears*12,"",MOD($A73-1,12)+1) | E73: =IF($A73>NYears*12,"",LotValue0*(1+LotGrowth)^($C73-1)) | F73: =IF($A73>NYears*12,"",IF($A73=1,InitInvest,$R72)) | G73: =IF($A73>NYears*12,"",INT($F73/$E73)) | H73: =IF($A73>NYears*12,"",$G73*$E73) | I73: =IF($A73>NYears*12,"",$F73-$H73) | J73: =IF($A73>NYears*12,"",$H73*RateA) | K73: =IF($A73>NYears*12,"",IF($D73=1,$J73,$K72+$J73)) | L73: =IF($A73>NYears*12,"",IF(MOD($D73,3)=0,SUM($J71:$J73),0)) | M73: =IF($A73>NYears*12,"",IF(TaxFreq="Quarterly",$K73*12/$D73,$K73)) | N73: =IF($A73>NYears*12,"",LOOKUP($M73,TaxLower,TaxRate)) | O73: =IF($A73>NYears*12,"",IF(TaxFreq="Quarterly",IF(MOD($D73,3)=0,$L73*$N73,0),IF($D73=12,$K73*$N73,0))) | P73: =IF($A73>NYears*12,"",IF($D73=1,$O73,$P72+$O73)) | Q73: =IF($A73>NYears*12,"",IF($D73=12,MIN(WdrPct*IF(WdrBase="Post-tax profit",$K73-$P73,$K73),WdrCap),0)) | R73: =IF($A73>NYears*12,"",$F73+$J73-$O73-$Q73) | S73: =IF($A73>NYears*12,"",INT($R73/$E73))
A74: =70 | B74: =IF($A74>NYears*12,"",EDATE(StartMonth,$A74-1)) | C74: =IF($A74>NYears*12,"",INT(($A74-1)/12)+1) | D74: =IF($A74>NYears*12,"",MOD($A74-1,12)+1) | E74: =IF($A74>NYears*12,"",LotValue0*(1+LotGrowth)^($C74-1)) | F74: =IF($A74>NYears*12,"",IF($A74=1,InitInvest,$R73)) | G74: =IF($A74>NYears*12,"",INT($F74/$E74)) | H74: =IF($A74>NYears*12,"",$G74*$E74) | I74: =IF($A74>NYears*12,"",$F74-$H74) | J74: =IF($A74>NYears*12,"",$H74*RateA) | K74: =IF($A74>NYears*12,"",IF($D74=1,$J74,$K73+$J74)) | L74: =IF($A74>NYears*12,"",IF(MOD($D74,3)=0,SUM($J72:$J74),0)) | M74: =IF($A74>NYears*12,"",IF(TaxFreq="Quarterly",$K74*12/$D74,$K74)) | N74: =IF($A74>NYears*12,"",LOOKUP($M74,TaxLower,TaxRate)) | O74: =IF($A74>NYears*12,"",IF(TaxFreq="Quarterly",IF(MOD($D74,3)=0,$L74*$N74,0),IF($D74=12,$K74*$N74,0))) | P74: =IF($A74>NYears*12,"",IF($D74=1,$O74,$P73+$O74)) | Q74: =IF($A74>NYears*12,"",IF($D74=12,MIN(WdrPct*IF(WdrBase="Post-tax profit",$K74-$P74,$K74),WdrCap),0)) | R74: =IF($A74>NYears*12,"",$F74+$J74-$O74-$Q74) | S74: =IF($A74>NYears*12,"",INT($R74/$E74))
A75: =71 | B75: =IF($A75>NYears*12,"",EDATE(StartMonth,$A75-1)) | C75: =IF($A75>NYears*12,"",INT(($A75-1)/12)+1) | D75: =IF($A75>NYears*12,"",MOD($A75-1,12)+1) | E75: =IF($A75>NYears*12,"",LotValue0*(1+LotGrowth)^($C75-1)) | F75: =IF($A75>NYears*12,"",IF($A75=1,InitInvest,$R74)) | G75: =IF($A75>NYears*12,"",INT($F75/$E75)) | H75: =IF($A75>NYears*12,"",$G75*$E75) | I75: =IF($A75>NYears*12,"",$F75-$H75) | J75: =IF($A75>NYears*12,"",$H75*RateA) | K75: =IF($A75>NYears*12,"",IF($D75=1,$J75,$K74+$J75)) | L75: =IF($A75>NYears*12,"",IF(MOD($D75,3)=0,SUM($J73:$J75),0)) | M75: =IF($A75>NYears*12,"",IF(TaxFreq="Quarterly",$K75*12/$D75,$K75)) | N75: =IF($A75>NYears*12,"",LOOKUP($M75,TaxLower,TaxRate)) | O75: =IF($A75>NYears*12,"",IF(TaxFreq="Quarterly",IF(MOD($D75,3)=0,$L75*$N75,0),IF($D75=12,$K75*$N75,0))) | P75: =IF($A75>NYears*12,"",IF($D75=1,$O75,$P74+$O75)) | Q75: =IF($A75>NYears*12,"",IF($D75=12,MIN(WdrPct*IF(WdrBase="Post-tax profit",$K75-$P75,$K75),WdrCap),0)) | R75: =IF($A75>NYears*12,"",$F75+$J75-$O75-$Q75) | S75: =IF($A75>NYears*12,"",INT($R75/$E75))
A76: =72 | B76: =IF($A76>NYears*12,"",EDATE(StartMonth,$A76-1)) | C76: =IF($A76>NYears*12,"",INT(($A76-1)/12)+1) | D76: =IF($A76>NYears*12,"",MOD($A76-1,12)+1) | E76: =IF($A76>NYears*12,"",LotValue0*(1+LotGrowth)^($C76-1)) | F76: =IF($A76>NYears*12,"",IF($A76=1,InitInvest,$R75)) | G76: =IF($A76>NYears*12,"",INT($F76/$E76)) | H76: =IF($A76>NYears*12,"",$G76*$E76) | I76: =IF($A76>NYears*12,"",$F76-$H76) | J76: =IF($A76>NYears*12,"",$H76*RateA) | K76: =IF($A76>NYears*12,"",IF($D76=1,$J76,$K75+$J76)) | L76: =IF($A76>NYears*12,"",IF(MOD($D76,3)=0,SUM($J74:$J76),0)) | M76: =IF($A76>NYears*12,"",IF(TaxFreq="Quarterly",$K76*12/$D76,$K76)) | N76: =IF($A76>NYears*12,"",LOOKUP($M76,TaxLower,TaxRate)) | O76: =IF($A76>NYears*12,"",IF(TaxFreq="Quarterly",IF(MOD($D76,3)=0,$L76*$N76,0),IF($D76=12,$K76*$N76,0))) | P76: =IF($A76>NYears*12,"",IF($D76=1,$O76,$P75+$O76)) | Q76: =IF($A76>NYears*12,"",IF($D76=12,MIN(WdrPct*IF(WdrBase="Post-tax profit",$K76-$P76,$K76),WdrCap),0)) | R76: =IF($A76>NYears*12,"",$F76+$J76-$O76-$Q76) | S76: =IF($A76>NYears*12,"",INT($R76/$E76))
A77: =73 | B77: =IF($A77>NYears*12,"",EDATE(StartMonth,$A77-1)) | C77: =IF($A77>NYears*12,"",INT(($A77-1)/12)+1) | D77: =IF($A77>NYears*12,"",MOD($A77-1,12)+1) | E77: =IF($A77>NYears*12,"",LotValue0*(1+LotGrowth)^($C77-1)) | F77: =IF($A77>NYears*12,"",IF($A77=1,InitInvest,$R76)) | G77: =IF($A77>NYears*12,"",INT($F77/$E77)) | H77: =IF($A77>NYears*12,"",$G77*$E77) | I77: =IF($A77>NYears*12,"",$F77-$H77) | J77: =IF($A77>NYears*12,"",$H77*RateA) | K77: =IF($A77>NYears*12,"",IF($D77=1,$J77,$K76+$J77)) | L77: =IF($A77>NYears*12,"",IF(MOD($D77,3)=0,SUM($J75:$J77),0)) | M77: =IF($A77>NYears*12,"",IF(TaxFreq="Quarterly",$K77*12/$D77,$K77)) | N77: =IF($A77>NYears*12,"",LOOKUP($M77,TaxLower,TaxRate)) | O77: =IF($A77>NYears*12,"",IF(TaxFreq="Quarterly",IF(MOD($D77,3)=0,$L77*$N77,0),IF($D77=12,$K77*$N77,0))) | P77: =IF($A77>NYears*12,"",IF($D77=1,$O77,$P76+$O77)) | Q77: =IF($A77>NYears*12,"",IF($D77=12,MIN(WdrPct*IF(WdrBase="Post-tax profit",$K77-$P77,$K77),WdrCap),0)) | R77: =IF($A77>NYears*12,"",$F77+$J77-$O77-$Q77) | S77: =IF($A77>NYears*12,"",INT($R77/$E77))
A78: =74 | B78: =IF($A78>NYears*12,"",EDATE(StartMonth,$A78-1)) | C78: =IF($A78>NYears*12,"",INT(($A78-1)/12)+1) | D78: =IF($A78>NYears*12,"",MOD($A78-1,12)+1) | E78: =IF($A78>NYears*12,"",LotValue0*(1+LotGrowth)^($C78-1)) | F78: =IF($A78>NYears*12,"",IF($A78=1,InitInvest,$R77)) | G78: =IF($A78>NYears*12,"",INT($F78/$E78)) | H78: =IF($A78>NYears*12,"",$G78*$E78) | I78: =IF($A78>NYears*12,"",$F78-$H78) | J78: =IF($A78>NYears*12,"",$H78*RateA) | K78: =IF($A78>NYears*12,"",IF($D78=1,$J78,$K77+$J78)) | L78: =IF($A78>NYears*12,"",IF(MOD($D78,3)=0,SUM($J76:$J78),0)) | M78: =IF($A78>NYears*12,"",IF(TaxFreq="Quarterly",$K78*12/$D78,$K78)) | N78: =IF($A78>NYears*12,"",LOOKUP($M78,TaxLower,TaxRate)) | O78: =IF($A78>NYears*12,"",IF(TaxFreq="Quarterly",IF(MOD($D78,3)=0,$L78*$N78,0),IF($D78=12,$K78*$N78,0))) | P78: =IF($A78>NYears*12,"",IF($D78=1,$O78,$P77+$O78)) | Q78: =IF($A78>NYears*12,"",IF($D78=12,MIN(WdrPct*IF(WdrBase="Post-tax profit",$K78-$P78,$K78),WdrCap),0)) | R78: =IF($A78>NYears*12,"",$F78+$J78-$O78-$Q78) | S78: =IF($A78>NYears*12,"",INT($R78/$E78))
A79: =75 | B79: =IF($A79>NYears*12,"",EDATE(StartMonth,$A79-1)) | C79: =IF($A79>NYears*12,"",INT(($A79-1)/12)+1) | D79: =IF($A79>NYears*12,"",MOD($A79-1,12)+1) | E79: =IF($A79>NYears*12,"",LotValue0*(1+LotGrowth)^($C79-1)) | F79: =IF($A79>NYears*12,"",IF($A79=1,InitInvest,$R78)) | G79: =IF($A79>NYears*12,"",INT($F79/$E79)) | H79: =IF($A79>NYears*12,"",$G79*$E79) | I79: =IF($A79>NYears*12,"",$F79-$H79) | J79: =IF($A79>NYears*12,"",$H79*RateA) | K79: =IF($A79>NYears*12,"",IF($D79=1,$J79,$K78+$J79)) | L79: =IF($A79>NYears*12,"",IF(MOD($D79,3)=0,SUM($J77:$J79),0)) | M79: =IF($A79>NYears*12,"",IF(TaxFreq="Quarterly",$K79*12/$D79,$K79)) | N79: =IF($A79>NYears*12,"",LOOKUP($M79,TaxLower,TaxRate)) | O79: =IF($A79>NYears*12,"",IF(TaxFreq="Quarterly",IF(MOD($D79,3)=0,$L79*$N79,0),IF($D79=12,$K79*$N79,0))) | P79: =IF($A79>NYears*12,"",IF($D79=1,$O79,$P78+$O79)) | Q79: =IF($A79>NYears*12,"",IF($D79=12,MIN(WdrPct*IF(WdrBase="Post-tax profit",$K79-$P79,$K79),WdrCap),0)) | R79: =IF($A79>NYears*12,"",$F79+$J79-$O79-$Q79) | S79: =IF($A79>NYears*12,"",INT($R79/$E79))
A80: =76 | B80: =IF($A80>NYears*12,"",EDATE(StartMonth,$A80-1)) | C80: =IF($A80>NYears*12,"",INT(($A80-1)/12)+1) | D80: =IF($A80>NYears*12,"",MOD($A80-1,12)+1) | E80: =IF($A80>NYears*12,"",LotValue0*(1+LotGrowth)^($C80-1)) | F80: =IF($A80>NYears*12,"",IF($A80=1,InitInvest,$R79)) | G80: =IF($A80>NYears*12,"",INT($F80/$E80)) | H80: =IF($A80>NYears*12,"",$G80*$E80) | I80: =IF($A80>NYears*12,"",$F80-$H80) | J80: =IF($A80>NYears*12,"",$H80*RateA) | K80: =IF($A80>NYears*12,"",IF($D80=1,$J80,$K79+$J80)) | L80: =IF($A80>NYears*12,"",IF(MOD($D80,3)=0,SUM($J78:$J80),0)) | M80: =IF($A80>NYears*12,"",IF(TaxFreq="Quarterly",$K80*12/$D80,$K80)) | N80: =IF($A80>NYears*12,"",LOOKUP($M80,TaxLower,TaxRate)) | O80: =IF($A80>NYears*12,"",IF(TaxFreq="Quarterly",IF(MOD($D80,3)=0,$L80*$N80,0),IF($D80=12,$K80*$N80,0))) | P80: =IF($A80>NYears*12,"",IF($D80=1,$O80,$P79+$O80)) | Q80: =IF($A80>NYears*12,"",IF($D80=12,MIN(WdrPct*IF(WdrBase="Post-tax profit",$K80-$P80,$K80),WdrCap),0)) | R80: =IF($A80>NYears*12,"",$F80+$J80-$O80-$Q80) | S80: =IF($A80>NYears*12,"",INT($R80/$E80))
A81: =77 | B81: =IF($A81>NYears*12,"",EDATE(StartMonth,$A81-1)) | C81: =IF($A81>NYears*12,"",INT(($A81-1)/12)+1) | D81: =IF($A81>NYears*12,"",MOD($A81-1,12)+1) | E81: =IF($A81>NYears*12,"",LotValue0*(1+LotGrowth)^($C81-1)) | F81: =IF($A81>NYears*12,"",IF($A81=1,InitInvest,$R80)) | G81: =IF($A81>NYears*12,"",INT($F81/$E81)) | H81: =IF($A81>NYears*12,"",$G81*$E81) | I81: =IF($A81>NYears*12,"",$F81-$H81) | J81: =IF($A81>NYears*12,"",$H81*RateA) | K81: =IF($A81>NYears*12,"",IF($D81=1,$J81,$K80+$J81)) | L81: =IF($A81>NYears*12,"",IF(MOD($D81,3)=0,SUM($J79:$J81),0)) | M81: =IF($A81>NYears*12,"",IF(TaxFreq="Quarterly",$K81*12/$D81,$K81)) | N81: =IF($A81>NYears*12,"",LOOKUP($M81,TaxLower,TaxRate)) | O81: =IF($A81>NYears*12,"",IF(TaxFreq="Quarterly",IF(MOD($D81,3)=0,$L81*$N81,0),IF($D81=12,$K81*$N81,0))) | P81: =IF($A81>NYears*12,"",IF($D81=1,$O81,$P80+$O81)) | Q81: =IF($A81>NYears*12,"",IF($D81=12,MIN(WdrPct*IF(WdrBase="Post-tax profit",$K81-$P81,$K81),WdrCap),0)) | R81: =IF($A81>NYears*12,"",$F81+$J81-$O81-$Q81) | S81: =IF($A81>NYears*12,"",INT($R81/$E81))
A82: =78 | B82: =IF($A82>NYears*12,"",EDATE(StartMonth,$A82-1)) | C82: =IF($A82>NYears*12,"",INT(($A82-1)/12)+1) | D82: =IF($A82>NYears*12,"",MOD($A82-1,12)+1) | E82: =IF($A82>NYears*12,"",LotValue0*(1+LotGrowth)^($C82-1)) | F82: =IF($A82>NYears*12,"",IF($A82=1,InitInvest,$R81)) | G82: =IF($A82>NYears*12,"",INT($F82/$E82)) | H82: =IF($A82>NYears*12,"",$G82*$E82) | I82: =IF($A82>NYears*12,"",$F82-$H82) | J82: =IF($A82>NYears*12,"",$H82*RateA) | K82: =IF($A82>NYears*12,"",IF($D82=1,$J82,$K81+$J82)) | L82: =IF($A82>NYears*12,"",IF(MOD($D82,3)=0,SUM($J80:$J82),0)) | M82: =IF($A82>NYears*12,"",IF(TaxFreq="Quarterly",$K82*12/$D82,$K82)) | N82: =IF($A82>NYears*12,"",LOOKUP($M82,TaxLower,TaxRate)) | O82: =IF($A82>NYears*12,"",IF(TaxFreq="Quarterly",IF(MOD($D82,3)=0,$L82*$N82,0),IF($D82=12,$K82*$N82,0))) | P82: =IF($A82>NYears*12,"",IF($D82=1,$O82,$P81+$O82)) | Q82: =IF($A82>NYears*12,"",IF($D82=12,MIN(WdrPct*IF(WdrBase="Post-tax profit",$K82-$P82,$K82),WdrCap),0)) | R82: =IF($A82>NYears*12,"",$F82+$J82-$O82-$Q82) | S82: =IF($A82>NYears*12,"",INT($R82/$E82))
A83: =79 | B83: =IF($A83>NYears*12,"",EDATE(StartMonth,$A83-1)) | C83: =IF($A83>NYears*12,"",INT(($A83-1)/12)+1) | D83: =IF($A83>NYears*12,"",MOD($A83-1,12)+1) | E83: =IF($A83>NYears*12,"",LotValue0*(1+LotGrowth)^($C83-1)) | F83: =IF($A83>NYears*12,"",IF($A83=1,InitInvest,$R82)) | G83: =IF($A83>NYears*12,"",INT($F83/$E83)) | H83: =IF($A83>NYears*12,"",$G83*$E83) | I83: =IF($A83>NYears*12,"",$F83-$H83) | J83: =IF($A83>NYears*12,"",$H83*RateA) | K83: =IF($A83>NYears*12,"",IF($D83=1,$J83,$K82+$J83)) | L83: =IF($A83>NYears*12,"",IF(MOD($D83,3)=0,SUM($J81:$J83),0)) | M83: =IF($A83>NYears*12,"",IF(TaxFreq="Quarterly",$K83*12/$D83,$K83)) | N83: =IF($A83>NYears*12,"",LOOKUP($M83,TaxLower,TaxRate)) | O83: =IF($A83>NYears*12,"",IF(TaxFreq="Quarterly",IF(MOD($D83,3)=0,$L83*$N83,0),IF($D83=12,$K83*$N83,0))) | P83: =IF($A83>NYears*12,"",IF($D83=1,$O83,$P82+$O83)) | Q83: =IF($A83>NYears*12,"",IF($D83=12,MIN(WdrPct*IF(WdrBase="Post-tax profit",$K83-$P83,$K83),WdrCap),0)) | R83: =IF($A83>NYears*12,"",$F83+$J83-$O83-$Q83) | S83: =IF($A83>NYears*12,"",INT($R83/$E83))
A84: =80 | B84: =IF($A84>NYears*12,"",EDATE(StartMonth,$A84-1)) | C84: =IF($A84>NYears*12,"",INT(($A84-1)/12)+1) | D84: =IF($A84>NYears*12,"",MOD($A84-1,12)+1) | E84: =IF($A84>NYears*12,"",LotValue0*(1+LotGrowth)^($C84-1)) | F84: =IF($A84>NYears*12,"",IF($A84=1,InitInvest,$R83)) | G84: =IF($A84>NYears*12,"",INT($F84/$E84)) | H84: =IF($A84>NYears*12,"",$G84*$E84) | I84: =IF($A84>NYears*12,"",$F84-$H84) | J84: =IF($A84>NYears*12,"",$H84*RateA) | K84: =IF($A84>NYears*12,"",IF($D84=1,$J84,$K83+$J84)) | L84: =IF($A84>NYears*12,"",IF(MOD($D84,3)=0,SUM($J82:$J84),0)) | M84: =IF($A84>NYears*12,"",IF(TaxFreq="Quarterly",$K84*12/$D84,$K84)) | N84: =IF($A84>NYears*12,"",LOOKUP($M84,TaxLower,TaxRate)) | O84: =IF($A84>NYears*12,"",IF(TaxFreq="Quarterly",IF(MOD($D84,3)=0,$L84*$N84,0),IF($D84=12,$K84*$N84,0))) | P84: =IF($A84>NYears*12,"",IF($D84=1,$O84,$P83+$O84)) | Q84: =IF($A84>NYears*12,"",IF($D84=12,MIN(WdrPct*IF(WdrBase="Post-tax profit",$K84-$P84,$K84),WdrCap),0)) | R84: =IF($A84>NYears*12,"",$F84+$J84-$O84-$Q84) | S84: =IF($A84>NYears*12,"",INT($R84/$E84))
A85: =81 | B85: =IF($A85>NYears*12,"",EDATE(StartMonth,$A85-1)) | C85: =IF($A85>NYears*12,"",INT(($A85-1)/12)+1) | D85: =IF($A85>NYears*12,"",MOD($A85-1,12)+1) | E85: =IF($A85>NYears*12,"",LotValue0*(1+LotGrowth)^($C85-1)) | F85: =IF($A85>NYears*12,"",IF($A85=1,InitInvest,$R84)) | G85: =IF($A85>NYears*12,"",INT($F85/$E85)) | H85: =IF($A85>NYears*12,"",$G85*$E85) | I85: =IF($A85>NYears*12,"",$F85-$H85) | J85: =IF($A85>NYears*12,"",$H85*RateA) | K85: =IF($A85>NYears*12,"",IF($D85=1,$J85,$K84+$J85)) | L85: =IF($A85>NYears*12,"",IF(MOD($D85,3)=0,SUM($J83:$J85),0)) | M85: =IF($A85>NYears*12,"",IF(TaxFreq="Quarterly",$K85*12/$D85,$K85)) | N85: =IF($A85>NYears*12,"",LOOKUP($M85,TaxLower,TaxRate)) | O85: =IF($A85>NYears*12,"",IF(TaxFreq="Quarterly",IF(MOD($D85,3)=0,$L85*$N85,0),IF($D85=12,$K85*$N85,0))) | P85: =IF($A85>NYears*12,"",IF($D85=1,$O85,$P84+$O85)) | Q85: =IF($A85>NYears*12,"",IF($D85=12,MIN(WdrPct*IF(WdrBase="Post-tax profit",$K85-$P85,$K85),WdrCap),0)) | R85: =IF($A85>NYears*12,"",$F85+$J85-$O85-$Q85) | S85: =IF($A85>NYears*12,"",INT($R85/$E85))
A86: =82 | B86: =IF($A86>NYears*12,"",EDATE(StartMonth,$A86-1)) | C86: =IF($A86>NYears*12,"",INT(($A86-1)/12)+1) | D86: =IF($A86>NYears*12,"",MOD($A86-1,12)+1) | E86: =IF($A86>NYears*12,"",LotValue0*(1+LotGrowth)^($C86-1)) | F86: =IF($A86>NYears*12,"",IF($A86=1,InitInvest,$R85)) | G86: =IF($A86>NYears*12,"",INT($F86/$E86)) | H86: =IF($A86>NYears*12,"",$G86*$E86) | I86: =IF($A86>NYears*12,"",$F86-$H86) | J86: =IF($A86>NYears*12,"",$H86*RateA) | K86: =IF($A86>NYears*12,"",IF($D86=1,$J86,$K85+$J86)) | L86: =IF($A86>NYears*12,"",IF(MOD($D86,3)=0,SUM($J84:$J86),0)) | M86: =IF($A86>NYears*12,"",IF(TaxFreq="Quarterly",$K86*12/$D86,$K86)) | N86: =IF($A86>NYears*12,"",LOOKUP($M86,TaxLower,TaxRate)) | O86: =IF($A86>NYears*12,"",IF(TaxFreq="Quarterly",IF(MOD($D86,3)=0,$L86*$N86,0),IF($D86=12,$K86*$N86,0))) | P86: =IF($A86>NYears*12,"",IF($D86=1,$O86,$P85+$O86)) | Q86: =IF($A86>NYears*12,"",IF($D86=12,MIN(WdrPct*IF(WdrBase="Post-tax profit",$K86-$P86,$K86),WdrCap),0)) | R86: =IF($A86>NYears*12,"",$F86+$J86-$O86-$Q86) | S86: =IF($A86>NYears*12,"",INT($R86/$E86))
A87: =83 | B87: =IF($A87>NYears*12,"",EDATE(StartMonth,$A87-1)) | C87: =IF($A87>NYears*12,"",INT(($A87-1)/12)+1) | D87: =IF($A87>NYears*12,"",MOD($A87-1,12)+1) | E87: =IF($A87>NYears*12,"",LotValue0*(1+LotGrowth)^($C87-1)) | F87: =IF($A87>NYears*12,"",IF($A87=1,InitInvest,$R86)) | G87: =IF($A87>NYears*12,"",INT($F87/$E87)) | H87: =IF($A87>NYears*12,"",$G87*$E87) | I87: =IF($A87>NYears*12,"",$F87-$H87) | J87: =IF($A87>NYears*12,"",$H87*RateA) | K87: =IF($A87>NYears*12,"",IF($D87=1,$J87,$K86+$J87)) | L87: =IF($A87>NYears*12,"",IF(MOD($D87,3)=0,SUM($J85:$J87),0)) | M87: =IF($A87>NYears*12,"",IF(TaxFreq="Quarterly",$K87*12/$D87,$K87)) | N87: =IF($A87>NYears*12,"",LOOKUP($M87,TaxLower,TaxRate)) | O87: =IF($A87>NYears*12,"",IF(TaxFreq="Quarterly",IF(MOD($D87,3)=0,$L87*$N87,0),IF($D87=12,$K87*$N87,0))) | P87: =IF($A87>NYears*12,"",IF($D87=1,$O87,$P86+$O87)) | Q87: =IF($A87>NYears*12,"",IF($D87=12,MIN(WdrPct*IF(WdrBase="Post-tax profit",$K87-$P87,$K87),WdrCap),0)) | R87: =IF($A87>NYears*12,"",$F87+$J87-$O87-$Q87) | S87: =IF($A87>NYears*12,"",INT($R87/$E87))
A88: =84 | B88: =IF($A88>NYears*12,"",EDATE(StartMonth,$A88-1)) | C88: =IF($A88>NYears*12,"",INT(($A88-1)/12)+1) | D88: =IF($A88>NYears*12,"",MOD($A88-1,12)+1) | E88: =IF($A88>NYears*12,"",LotValue0*(1+LotGrowth)^($C88-1)) | F88: =IF($A88>NYears*12,"",IF($A88=1,InitInvest,$R87)) | G88: =IF($A88>NYears*12,"",INT($F88/$E88)) | H88: =IF($A88>NYears*12,"",$G88*$E88) | I88: =IF($A88>NYears*12,"",$F88-$H88) | J88: =IF($A88>NYears*12,"",$H88*RateA) | K88: =IF($A88>NYears*12,"",IF($D88=1,$J88,$K87+$J88)) | L88: =IF($A88>NYears*12,"",IF(MOD($D88,3)=0,SUM($J86:$J88),0)) | M88: =IF($A88>NYears*12,"",IF(TaxFreq="Quarterly",$K88*12/$D88,$K88)) | N88: =IF($A88>NYears*12,"",LOOKUP($M88,TaxLower,TaxRate)) | O88: =IF($A88>NYears*12,"",IF(TaxFreq="Quarterly",IF(MOD($D88,3)=0,$L88*$N88,0),IF($D88=12,$K88*$N88,0))) | P88: =IF($A88>NYears*12,"",IF($D88=1,$O88,$P87+$O88)) | Q88: =IF($A88>NYears*12,"",IF($D88=12,MIN(WdrPct*IF(WdrBase="Post-tax profit",$K88-$P88,$K88),WdrCap),0)) | R88: =IF($A88>NYears*12,"",$F88+$J88-$O88-$Q88) | S88: =IF($A88>NYears*12,"",INT($R88/$E88))
A89: =85 | B89: =IF($A89>NYears*12,"",EDATE(StartMonth,$A89-1)) | C89: =IF($A89>NYears*12,"",INT(($A89-1)/12)+1) | D89: =IF($A89>NYears*12,"",MOD($A89-1,12)+1) | E89: =IF($A89>NYears*12,"",LotValue0*(1+LotGrowth)^($C89-1)) | F89: =IF($A89>NYears*12,"",IF($A89=1,InitInvest,$R88)) | G89: =IF($A89>NYears*12,"",INT($F89/$E89)) | H89: =IF($A89>NYears*12,"",$G89*$E89) | I89: =IF($A89>NYears*12,"",$F89-$H89) | J89: =IF($A89>NYears*12,"",$H89*RateA) | K89: =IF($A89>NYears*12,"",IF($D89=1,$J89,$K88+$J89)) | L89: =IF($A89>NYears*12,"",IF(MOD($D89,3)=0,SUM($J87:$J89),0)) | M89: =IF($A89>NYears*12,"",IF(TaxFreq="Quarterly",$K89*12/$D89,$K89)) | N89: =IF($A89>NYears*12,"",LOOKUP($M89,TaxLower,TaxRate)) | O89: =IF($A89>NYears*12,"",IF(TaxFreq="Quarterly",IF(MOD($D89,3)=0,$L89*$N89,0),IF($D89=12,$K89*$N89,0))) | P89: =IF($A89>NYears*12,"",IF($D89=1,$O89,$P88+$O89)) | Q89: =IF($A89>NYears*12,"",IF($D89=12,MIN(WdrPct*IF(WdrBase="Post-tax profit",$K89-$P89,$K89),WdrCap),0)) | R89: =IF($A89>NYears*12,"",$F89+$J89-$O89-$Q89) | S89: =IF($A89>NYears*12,"",INT($R89/$E89))
A90: =86 | B90: =IF($A90>NYears*12,"",EDATE(StartMonth,$A90-1)) | C90: =IF($A90>NYears*12,"",INT(($A90-1)/12)+1) | D90: =IF($A90>NYears*12,"",MOD($A90-1,12)+1) | E90: =IF($A90>NYears*12,"",LotValue0*(1+LotGrowth)^($C90-1)) | F90: =IF($A90>NYears*12,"",IF($A90=1,InitInvest,$R89)) | G90: =IF($A90>NYears*12,"",INT($F90/$E90)) | H90: =IF($A90>NYears*12,"",$G90*$E90) | I90: =IF($A90>NYears*12,"",$F90-$H90) | J90: =IF($A90>NYears*12,"",$H90*RateA) | K90: =IF($A90>NYears*12,"",IF($D90=1,$J90,$K89+$J90)) | L90: =IF($A90>NYears*12,"",IF(MOD($D90,3)=0,SUM($J88:$J90),0)) | M90: =IF($A90>NYears*12,"",IF(TaxFreq="Quarterly",$K90*12/$D90,$K90)) | N90: =IF($A90>NYears*12,"",LOOKUP($M90,TaxLower,TaxRate)) | O90: =IF($A90>NYears*12,"",IF(TaxFreq="Quarterly",IF(MOD($D90,3)=0,$L90*$N90,0),IF($D90=12,$K90*$N90,0))) | P90: =IF($A90>NYears*12,"",IF($D90=1,$O90,$P89+$O90)) | Q90: =IF($A90>NYears*12,"",IF($D90=12,MIN(WdrPct*IF(WdrBase="Post-tax profit",$K90-$P90,$K90),WdrCap),0)) | R90: =IF($A90>NYears*12,"",$F90+$J90-$O90-$Q90) | S90: =IF($A90>NYears*12,"",INT($R90/$E90))
A91: =87 | B91: =IF($A91>NYears*12,"",EDATE(StartMonth,$A91-1)) | C91: =IF($A91>NYears*12,"",INT(($A91-1)/12)+1) | D91: =IF($A91>NYears*12,"",MOD($A91-1,12)+1) | E91: =IF($A91>NYears*12,"",LotValue0*(1+LotGrowth)^($C91-1)) | F91: =IF($A91>NYears*12,"",IF($A91=1,InitInvest,$R90)) | G91: =IF($A91>NYears*12,"",INT($F91/$E91)) | H91: =IF($A91>NYears*12,"",$G91*$E91) | I91: =IF($A91>NYears*12,"",$F91-$H91) | J91: =IF($A91>NYears*12,"",$H91*RateA) | K91: =IF($A91>NYears*12,"",IF($D91=1,$J91,$K90+$J91)) | L91: =IF($A91>NYears*12,"",IF(MOD($D91,3)=0,SUM($J89:$J91),0)) | M91: =IF($A91>NYears*12,"",IF(TaxFreq="Quarterly",$K91*12/$D91,$K91)) | N91: =IF($A91>NYears*12,"",LOOKUP($M91,TaxLower,TaxRate)) | O91: =IF($A91>NYears*12,"",IF(TaxFreq="Quarterly",IF(MOD($D91,3)=0,$L91*$N91,0),IF($D91=12,$K91*$N91,0))) | P91: =IF($A91>NYears*12,"",IF($D91=1,$O91,$P90+$O91)) | Q91: =IF($A91>NYears*12,"",IF($D91=12,MIN(WdrPct*IF(WdrBase="Post-tax profit",$K91-$P91,$K91),WdrCap),0)) | R91: =IF($A91>NYears*12,"",$F91+$J91-$O91-$Q91) | S91: =IF($A91>NYears*12,"",INT($R91/$E91))
A92: =88 | B92: =IF($A92>NYears*12,"",EDATE(StartMonth,$A92-1)) | C92: =IF($A92>NYears*12,"",INT(($A92-1)/12)+1) | D92: =IF($A92>NYears*12,"",MOD($A92-1,12)+1) | E92: =IF($A92>NYears*12,"",LotValue0*(1+LotGrowth)^($C92-1)) | F92: =IF($A92>NYears*12,"",IF($A92=1,InitInvest,$R91)) | G92: =IF($A92>NYears*12,"",INT($F92/$E92)) | H92: =IF($A92>NYears*12,"",$G92*$E92) | I92: =IF($A92>NYears*12,"",$F92-$H92) | J92: =IF($A92>NYears*12,"",$H92*RateA) | K92: =IF($A92>NYears*12,"",IF($D92=1,$J92,$K91+$J92)) | L92: =IF($A92>NYears*12,"",IF(MOD($D92,3)=0,SUM($J90:$J92),0)) | M92: =IF($A92>NYears*12,"",IF(TaxFreq="Quarterly",$K92*12/$D92,$K92)) | N92: =IF($A92>NYears*12,"",LOOKUP($M92,TaxLower,TaxRate)) | O92: =IF($A92>NYears*12,"",IF(TaxFreq="Quarterly",IF(MOD($D92,3)=0,$L92*$N92,0),IF($D92=12,$K92*$N92,0))) | P92: =IF($A92>NYears*12,"",IF($D92=1,$O92,$P91+$O92)) | Q92: =IF($A92>NYears*12,"",IF($D92=12,MIN(WdrPct*IF(WdrBase="Post-tax profit",$K92-$P92,$K92),WdrCap),0)) | R92: =IF($A92>NYears*12,"",$F92+$J92-$O92-$Q92) | S92: =IF($A92>NYears*12,"",INT($R92/$E92))
A93: =89 | B93: =IF($A93>NYears*12,"",EDATE(StartMonth,$A93-1)) | C93: =IF($A93>NYears*12,"",INT(($A93-1)/12)+1) | D93: =IF($A93>NYears*12,"",MOD($A93-1,12)+1) | E93: =IF($A93>NYears*12,"",LotValue0*(1+LotGrowth)^($C93-1)) | F93: =IF($A93>NYears*12,"",IF($A93=1,InitInvest,$R92)) | G93: =IF($A93>NYears*12,"",INT($F93/$E93)) | H93: =IF($A93>NYears*12,"",$G93*$E93) | I93: =IF($A93>NYears*12,"",$F93-$H93) | J93: =IF($A93>NYears*12,"",$H93*RateA) | K93: =IF($A93>NYears*12,"",IF($D93=1,$J93,$K92+$J93)) | L93: =IF($A93>NYears*12,"",IF(MOD($D93,3)=0,SUM($J91:$J93),0)) | M93: =IF($A93>NYears*12,"",IF(TaxFreq="Quarterly",$K93*12/$D93,$K93)) | N93: =IF($A93>NYears*12,"",LOOKUP($M93,TaxLower,TaxRate)) | O93: =IF($A93>NYears*12,"",IF(TaxFreq="Quarterly",IF(MOD($D93,3)=0,$L93*$N93,0),IF($D93=12,$K93*$N93,0))) | P93: =IF($A93>NYears*12,"",IF($D93=1,$O93,$P92+$O93)) | Q93: =IF($A93>NYears*12,"",IF($D93=12,MIN(WdrPct*IF(WdrBase="Post-tax profit",$K93-$P93,$K93),WdrCap),0)) | R93: =IF($A93>NYears*12,"",$F93+$J93-$O93-$Q93) | S93: =IF($A93>NYears*12,"",INT($R93/$E93))
A94: =90 | B94: =IF($A94>NYears*12,"",EDATE(StartMonth,$A94-1)) | C94: =IF($A94>NYears*12,"",INT(($A94-1)/12)+1) | D94: =IF($A94>NYears*12,"",MOD($A94-1,12)+1) | E94: =IF($A94>NYears*12,"",LotValue0*(1+LotGrowth)^($C94-1)) | F94: =IF($A94>NYears*12,"",IF($A94=1,InitInvest,$R93)) | G94: =IF($A94>NYears*12,"",INT($F94/$E94)) | H94: =IF($A94>NYears*12,"",$G94*$E94) | I94: =IF($A94>NYears*12,"",$F94-$H94) | J94: =IF($A94>NYears*12,"",$H94*RateA) | K94: =IF($A94>NYears*12,"",IF($D94=1,$J94,$K93+$J94)) | L94: =IF($A94>NYears*12,"",IF(MOD($D94,3)=0,SUM($J92:$J94),0)) | M94: =IF($A94>NYears*12,"",IF(TaxFreq="Quarterly",$K94*12/$D94,$K94)) | N94: =IF($A94>NYears*12,"",LOOKUP($M94,TaxLower,TaxRate)) | O94: =IF($A94>NYears*12,"",IF(TaxFreq="Quarterly",IF(MOD($D94,3)=0,$L94*$N94,0),IF($D94=12,$K94*$N94,0))) | P94: =IF($A94>NYears*12,"",IF($D94=1,$O94,$P93+$O94)) | Q94: =IF($A94>NYears*12,"",IF($D94=12,MIN(WdrPct*IF(WdrBase="Post-tax profit",$K94-$P94,$K94),WdrCap),0)) | R94: =IF($A94>NYears*12,"",$F94+$J94-$O94-$Q94) | S94: =IF($A94>NYears*12,"",INT($R94/$E94))
A95: =91 | B95: =IF($A95>NYears*12,"",EDATE(StartMonth,$A95-1)) | C95: =IF($A95>NYears*12,"",INT(($A95-1)/12)+1) | D95: =IF($A95>NYears*12,"",MOD($A95-1,12)+1) | E95: =IF($A95>NYears*12,"",LotValue0*(1+LotGrowth)^($C95-1)) | F95: =IF($A95>NYears*12,"",IF($A95=1,InitInvest,$R94)) | G95: =IF($A95>NYears*12,"",INT($F95/$E95)) | H95: =IF($A95>NYears*12,"",$G95*$E95) | I95: =IF($A95>NYears*12,"",$F95-$H95) | J95: =IF($A95>NYears*12,"",$H95*RateA) | K95: =IF($A95>NYears*12,"",IF($D95=1,$J95,$K94+$J95)) | L95: =IF($A95>NYears*12,"",IF(MOD($D95,3)=0,SUM($J93:$J95),0)) | M95: =IF($A95>NYears*12,"",IF(TaxFreq="Quarterly",$K95*12/$D95,$K95)) | N95: =IF($A95>NYears*12,"",LOOKUP($M95,TaxLower,TaxRate)) | O95: =IF($A95>NYears*12,"",IF(TaxFreq="Quarterly",IF(MOD($D95,3)=0,$L95*$N95,0),IF($D95=12,$K95*$N95,0))) | P95: =IF($A95>NYears*12,"",IF($D95=1,$O95,$P94+$O95)) | Q95: =IF($A95>NYears*12,"",IF($D95=12,MIN(WdrPct*IF(WdrBase="Post-tax profit",$K95-$P95,$K95),WdrCap),0)) | R95: =IF($A95>NYears*12,"",$F95+$J95-$O95-$Q95) | S95: =IF($A95>NYears*12,"",INT($R95/$E95))
A96: =92 | B96: =IF($A96>NYears*12,"",EDATE(StartMonth,$A96-1)) | C96: =IF($A96>NYears*12,"",INT(($A96-1)/12)+1) | D96: =IF($A96>NYears*12,"",MOD($A96-1,12)+1) | E96: =IF($A96>NYears*12,"",LotValue0*(1+LotGrowth)^($C96-1)) | F96: =IF($A96>NYears*12,"",IF($A96=1,InitInvest,$R95)) | G96: =IF($A96>NYears*12,"",INT($F96/$E96)) | H96: =IF($A96>NYears*12,"",$G96*$E96) | I96: =IF($A96>NYears*12,"",$F96-$H96) | J96: =IF($A96>NYears*12,"",$H96*RateA) | K96: =IF($A96>NYears*12,"",IF($D96=1,$J96,$K95+$J96)) | L96: =IF($A96>NYears*12,"",IF(MOD($D96,3)=0,SUM($J94:$J96),0)) | M96: =IF($A96>NYears*12,"",IF(TaxFreq="Quarterly",$K96*12/$D96,$K96)) | N96: =IF($A96>NYears*12,"",LOOKUP($M96,TaxLower,TaxRate)) | O96: =IF($A96>NYears*12,"",IF(TaxFreq="Quarterly",IF(MOD($D96,3)=0,$L96*$N96,0),IF($D96=12,$K96*$N96,0))) | P96: =IF($A96>NYears*12,"",IF($D96=1,$O96,$P95+$O96)) | Q96: =IF($A96>NYears*12,"",IF($D96=12,MIN(WdrPct*IF(WdrBase="Post-tax profit",$K96-$P96,$K96),WdrCap),0)) | R96: =IF($A96>NYears*12,"",$F96+$J96-$O96-$Q96) | S96: =IF($A96>NYears*12,"",INT($R96/$E96))
A97: =93 | B97: =IF($A97>NYears*12,"",EDATE(StartMonth,$A97-1)) | C97: =IF($A97>NYears*12,"",INT(($A97-1)/12)+1) | D97: =IF($A97>NYears*12,"",MOD($A97-1,12)+1) | E97: =IF($A97>NYears*12,"",LotValue0*(1+LotGrowth)^($C97-1)) | F97: =IF($A97>NYears*12,"",IF($A97=1,InitInvest,$R96)) | G97: =IF($A97>NYears*12,"",INT($F97/$E97)) | H97: =IF($A97>NYears*12,"",$G97*$E97) | I97: =IF($A97>NYears*12,"",$F97-$H97) | J97: =IF($A97>NYears*12,"",$H97*RateA) | K97: =IF($A97>NYears*12,"",IF($D97=1,$J97,$K96+$J97)) | L97: =IF($A97>NYears*12,"",IF(MOD($D97,3)=0,SUM($J95:$J97),0)) | M97: =IF($A97>NYears*12,"",IF(TaxFreq="Quarterly",$K97*12/$D97,$K97)) | N97: =IF($A97>NYears*12,"",LOOKUP($M97,TaxLower,TaxRate)) | O97: =IF($A97>NYears*12,"",IF(TaxFreq="Quarterly",IF(MOD($D97,3)=0,$L97*$N97,0),IF($D97=12,$K97*$N97,0))) | P97: =IF($A97>NYears*12,"",IF($D97=1,$O97,$P96+$O97)) | Q97: =IF($A97>NYears*12,"",IF($D97=12,MIN(WdrPct*IF(WdrBase="Post-tax profit",$K97-$P97,$K97),WdrCap),0)) | R97: =IF($A97>NYears*12,"",$F97+$J97-$O97-$Q97) | S97: =IF($A97>NYears*12,"",INT($R97/$E97))
A98: =94 | B98: =IF($A98>NYears*12,"",EDATE(StartMonth,$A98-1)) | C98: =IF($A98>NYears*12,"",INT(($A98-1)/12)+1) | D98: =IF($A98>NYears*12,"",MOD($A98-1,12)+1) | E98: =IF($A98>NYears*12,"",LotValue0*(1+LotGrowth)^($C98-1)) | F98: =IF($A98>NYears*12,"",IF($A98=1,InitInvest,$R97)) | G98: =IF($A98>NYears*12,"",INT($F98/$E98)) | H98: =IF($A98>NYears*12,"",$G98*$E98) | I98: =IF($A98>NYears*12,"",$F98-$H98) | J98: =IF($A98>NYears*12,"",$H98*RateA) | K98: =IF($A98>NYears*12,"",IF($D98=1,$J98,$K97+$J98)) | L98: =IF($A98>NYears*12,"",IF(MOD($D98,3)=0,SUM($J96:$J98),0)) | M98: =IF($A98>NYears*12,"",IF(TaxFreq="Quarterly",$K98*12/$D98,$K98)) | N98: =IF($A98>NYears*12,"",LOOKUP($M98,TaxLower,TaxRate)) | O98: =IF($A98>NYears*12,"",IF(TaxFreq="Quarterly",IF(MOD($D98,3)=0,$L98*$N98,0),IF($D98=12,$K98*$N98,0))) | P98: =IF($A98>NYears*12,"",IF($D98=1,$O98,$P97+$O98)) | Q98: =IF($A98>NYears*12,"",IF($D98=12,MIN(WdrPct*IF(WdrBase="Post-tax profit",$K98-$P98,$K98),WdrCap),0)) | R98: =IF($A98>NYears*12,"",$F98+$J98-$O98-$Q98) | S98: =IF($A98>NYears*12,"",INT($R98/$E98))
A99: =95 | B99: =IF($A99>NYears*12,"",EDATE(StartMonth,$A99-1)) | C99: =IF($A99>NYears*12,"",INT(($A99-1)/12)+1) | D99: =IF($A99>NYears*12,"",MOD($A99-1,12)+1) | E99: =IF($A99>NYears*12,"",LotValue0*(1+LotGrowth)^($C99-1)) | F99: =IF($A99>NYears*12,"",IF($A99=1,InitInvest,$R98)) | G99: =IF($A99>NYears*12,"",INT($F99/$E99)) | H99: =IF($A99>NYears*12,"",$G99*$E99) | I99: =IF($A99>NYears*12,"",$F99-$H99) | J99: =IF($A99>NYears*12,"",$H99*RateA) | K99: =IF($A99>NYears*12,"",IF($D99=1,$J99,$K98+$J99)) | L99: =IF($A99>NYears*12,"",IF(MOD($D99,3)=0,SUM($J97:$J99),0)) | M99: =IF($A99>NYears*12,"",IF(TaxFreq="Quarterly",$K99*12/$D99,$K99)) | N99: =IF($A99>NYears*12,"",LOOKUP($M99,TaxLower,TaxRate)) | O99: =IF($A99>NYears*12,"",IF(TaxFreq="Quarterly",IF(MOD($D99,3)=0,$L99*$N99,0),IF($D99=12,$K99*$N99,0))) | P99: =IF($A99>NYears*12,"",IF($D99=1,$O99,$P98+$O99)) | Q99: =IF($A99>NYears*12,"",IF($D99=12,MIN(WdrPct*IF(WdrBase="Post-tax profit",$K99-$P99,$K99),WdrCap),0)) | R99: =IF($A99>NYears*12,"",$F99+$J99-$O99-$Q99) | S99: =IF($A99>NYears*12,"",INT($R99/$E99))
A100: =96 | B100: =IF($A100>NYears*12,"",EDATE(StartMonth,$A100-1)) | C100: =IF($A100>NYears*12,"",INT(($A100-1)/12)+1) | D100: =IF($A100>NYears*12,"",MOD($A100-1,12)+1) | E100: =IF($A100>NYears*12,"",LotValue0*(1+LotGrowth)^($C100-1)) | F100: =IF($A100>NYears*12,"",IF($A100=1,InitInvest,$R99)) | G100: =IF($A100>NYears*12,"",INT($F100/$E100)) | H100: =IF($A100>NYears*12,"",$G100*$E100) | I100: =IF($A100>NYears*12,"",$F100-$H100) | J100: =IF($A100>NYears*12,"",$H100*RateA) | K100: =IF($A100>NYears*12,"",IF($D100=1,$J100,$K99+$J100)) | L100: =IF($A100>NYears*12,"",IF(MOD($D100,3)=0,SUM($J98:$J100),0)) | M100: =IF($A100>NYears*12,"",IF(TaxFreq="Quarterly",$K100*12/$D100,$K100)) | N100: =IF($A100>NYears*12,"",LOOKUP($M100,TaxLower,TaxRate)) | O100: =IF($A100>NYears*12,"",IF(TaxFreq="Quarterly",IF(MOD($D100,3)=0,$L100*$N100,0),IF($D100=12,$K100*$N100,0))) | P100: =IF($A100>NYears*12,"",IF($D100=1,$O100,$P99+$O100)) | Q100: =IF($A100>NYears*12,"",IF($D100=12,MIN(WdrPct*IF(WdrBase="Post-tax profit",$K100-$P100,$K100),WdrCap),0)) | R100: =IF($A100>NYears*12,"",$F100+$J100-$O100-$Q100) | S100: =IF($A100>NYears*12,"",INT($R100/$E100))
A101: =97 | B101: =IF($A101>NYears*12,"",EDATE(StartMonth,$A101-1)) | C101: =IF($A101>NYears*12,"",INT(($A101-1)/12)+1) | D101: =IF($A101>NYears*12,"",MOD($A101-1,12)+1) | E101: =IF($A101>NYears*12,"",LotValue0*(1+LotGrowth)^($C101-1)) | F101: =IF($A101>NYears*12,"",IF($A101=1,InitInvest,$R100)) | G101: =IF($A101>NYears*12,"",INT($F101/$E101)) | H101: =IF($A101>NYears*12,"",$G101*$E101) | I101: =IF($A101>NYears*12,"",$F101-$H101) | J101: =IF($A101>NYears*12,"",$H101*RateA) | K101: =IF($A101>NYears*12,"",IF($D101=1,$J101,$K100+$J101)) | L101: =IF($A101>NYears*12,"",IF(MOD($D101,3)=0,SUM($J99:$J101),0)) | M101: =IF($A101>NYears*12,"",IF(TaxFreq="Quarterly",$K101*12/$D101,$K101)) | N101: =IF($A101>NYears*12,"",LOOKUP($M101,TaxLower,TaxRate)) | O101: =IF($A101>NYears*12,"",IF(TaxFreq="Quarterly",IF(MOD($D101,3)=0,$L101*$N101,0),IF($D101=12,$K101*$N101,0))) | P101: =IF($A101>NYears*12,"",IF($D101=1,$O101,$P100+$O101)) | Q101: =IF($A101>NYears*12,"",IF($D101=12,MIN(WdrPct*IF(WdrBase="Post-tax profit",$K101-$P101,$K101),WdrCap),0)) | R101: =IF($A101>NYears*12,"",$F101+$J101-$O101-$Q101) | S101: =IF($A101>NYears*12,"",INT($R101/$E101))
...

Sheet Engine B
A1: Monthly engine — Scenario B
A2: Monthly return: | B2: =RateB | D2: One row per month. Returns accrue on DEPLOYED capital only; idle cash earns nothing until it funds a whole lot.
A4: Month # | B4: Month | C4: Yr | D4: M-in-yr | E4: Lot value | F4: Opening corpus | G4: Lots | H4: Deployed capital | I4: Idle cash | J4: Profit (month) | K4: Profit YTD | L4: Profit this qtr | M4: Slab income | N4: Tax rate | O4: Tax deducted | P4: Tax YTD | Q4: Withdrawal | R4: Closing corpus | S4: Lots at close
A5: =1 | B5: =IF($A5>NYears*12,"",EDATE(StartMonth,$A5-1)) | C5: =IF($A5>NYears*12,"",INT(($A5-1)/12)+1) | D5: =IF($A5>NYears*12,"",MOD($A5-1,12)+1) | E5: =IF($A5>NYears*12,"",LotValue0*(1+LotGrowth)^($C5-1)) | F5: =IF($A5>NYears*12,"",IF($A5=1,InitInvest,$R4)) | G5: =IF($A5>NYears*12,"",INT($F5/$E5)) | H5: =IF($A5>NYears*12,"",$G5*$E5) | I5: =IF($A5>NYears*12,"",$F5-$H5) | J5: =IF($A5>NYears*12,"",$H5*RateB) | K5: =IF($A5>NYears*12,"",IF($D5=1,$J5,$K4+$J5)) | L5: =IF($A5>NYears*12,"",IF(MOD($D5,3)=0,SUM($J3:$J5),0)) | M5: =IF($A5>NYears*12,"",IF(TaxFreq="Quarterly",$K5*12/$D5,$K5)) | N5: =IF($A5>NYears*12,"",LOOKUP($M5,TaxLower,TaxRate)) | O5: =IF($A5>NYears*12,"",IF(TaxFreq="Quarterly",IF(MOD($D5,3)=0,$L5*$N5,0),IF($D5=12,$K5*$N5,0))) | P5: =IF($A5>NYears*12,"",IF($D5=1,$O5,$P4+$O5)) | Q5: =IF($A5>NYears*12,"",IF($D5=12,MIN(WdrPct*IF(WdrBase="Post-tax profit",$K5-$P5,$K5),WdrCap),0)) | R5: =IF($A5>NYears*12,"",$F5+$J5-$O5-$Q5) | S5: =IF($A5>NYears*12,"",INT($R5/$E5))
A6: =2 | B6: =IF($A6>NYears*12,"",EDATE(StartMonth,$A6-1)) | C6: =IF($A6>NYears*12,"",INT(($A6-1)/12)+1) | D6: =IF($A6>NYears*12,"",MOD($A6-1,12)+1) | E6: =IF($A6>NYears*12,"",LotValue0*(1+LotGrowth)^($C6-1)) | F6: =IF($A6>NYears*12,"",IF($A6=1,InitInvest,$R5)) | G6: =IF($A6>NYears*12,"",INT($F6/$E6)) | H6: =IF($A6>NYears*12,"",$G6*$E6) | I6: =IF($A6>NYears*12,"",$F6-$H6) | J6: =IF($A6>NYears*12,"",$H6*RateB) | K6: =IF($A6>NYears*12,"",IF($D6=1,$J6,$K5+$J6)) | L6: =IF($A6>NYears*12,"",IF(MOD($D6,3)=0,SUM($J4:$J6),0)) | M6: =IF($A6>NYears*12,"",IF(TaxFreq="Quarterly",$K6*12/$D6,$K6)) | N6: =IF($A6>NYears*12,"",LOOKUP($M6,TaxLower,TaxRate)) | O6: =IF($A6>NYears*12,"",IF(TaxFreq="Quarterly",IF(MOD($D6,3)=0,$L6*$N6,0),IF($D6=12,$K6*$N6,0))) | P6: =IF($A6>NYears*12,"",IF($D6=1,$O6,$P5+$O6)) | Q6: =IF($A6>NYears*12,"",IF($D6=12,MIN(WdrPct*IF(WdrBase="Post-tax profit",$K6-$P6,$K6),WdrCap),0)) | R6: =IF($A6>NYears*12,"",$F6+$J6-$O6-$Q6) | S6: =IF($A6>NYears*12,"",INT($R6/$E6))
A7: =3 | B7: =IF($A7>NYears*12,"",EDATE(StartMonth,$A7-1)) | C7: =IF($A7>NYears*12,"",INT(($A7-1)/12)+1) | D7: =IF($A7>NYears*12,"",MOD($A7-1,12)+1) | E7: =IF($A7>NYears*12,"",LotValue0*(1+LotGrowth)^($C7-1)) | F7: =IF($A7>NYears*12,"",IF($A7=1,InitInvest,$R6)) | G7: =IF($A7>NYears*12,"",INT($F7/$E7)) | H7: =IF($A7>NYears*12,"",$G7*$E7) | I7: =IF($A7>NYears*12,"",$F7-$H7) | J7: =IF($A7>NYears*12,"",$H7*RateB) | K7: =IF($A7>NYears*12,"",IF($D7=1,$J7,$K6+$J7)) | L7: =IF($A7>NYears*12,"",IF(MOD($D7,3)=0,SUM($J5:$J7),0)) | M7: =IF($A7>NYears*12,"",IF(TaxFreq="Quarterly",$K7*12/$D7,$K7)) | N7: =IF($A7>NYears*12,"",LOOKUP($M7,TaxLower,TaxRate)) | O7: =IF($A7>NYears*12,"",IF(TaxFreq="Quarterly",IF(MOD($D7,3)=0,$L7*$N7,0),IF($D7=12,$K7*$N7,0))) | P7: =IF($A7>NYears*12,"",IF($D7=1,$O7,$P6+$O7)) | Q7: =IF($A7>NYears*12,"",IF($D7=12,MIN(WdrPct*IF(WdrBase="Post-tax profit",$K7-$P7,$K7),WdrCap),0)) | R7: =IF($A7>NYears*12,"",$F7+$J7-$O7-$Q7) | S7: =IF($A7>NYears*12,"",INT($R7/$E7))
A8: =4 | B8: =IF($A8>NYears*12,"",EDATE(StartMonth,$A8-1)) | C8: =IF($A8>NYears*12,"",INT(($A8-1)/12)+1) | D8: =IF($A8>NYears*12,"",MOD($A8-1,12)+1) | E8: =IF($A8>NYears*12,"",LotValue0*(1+LotGrowth)^($C8-1)) | F8: =IF($A8>NYears*12,"",IF($A8=1,InitInvest,$R7)) | G8: =IF($A8>NYears*12,"",INT($F8/$E8)) | H8: =IF($A8>NYears*12,"",$G8*$E8) | I8: =IF($A8>NYears*12,"",$F8-$H8) | J8: =IF($A8>NYears*12,"",$H8*RateB) | K8: =IF($A8>NYears*12,"",IF($D8=1,$J8,$K7+$J8)) | L8: =IF($A8>NYears*12,"",IF(MOD($D8,3)=0,SUM($J6:$J8),0)) | M8: =IF($A8>NYears*12,"",IF(TaxFreq="Quarterly",$K8*12/$D8,$K8)) | N8: =IF($A8>NYears*12,"",LOOKUP($M8,TaxLower,TaxRate)) | O8: =IF($A8>NYears*12,"",IF(TaxFreq="Quarterly",IF(MOD($D8,3)=0,$L8*$N8,0),IF($D8=12,$K8*$N8,0))) | P8: =IF($A8>NYears*12,"",IF($D8=1,$O8,$P7+$O8)) | Q8: =IF($A8>NYears*12,"",IF($D8=12,MIN(WdrPct*IF(WdrBase="Post-tax profit",$K8-$P8,$K8),WdrCap),0)) | R8: =IF($A8>NYears*12,"",$F8+$J8-$O8-$Q8) | S8: =IF($A8>NYears*12,"",INT($R8/$E8))
A9: =5 | B9: =IF($A9>NYears*12,"",EDATE(StartMonth,$A9-1)) | C9: =IF($A9>NYears*12,"",INT(($A9-1)/12)+1) | D9: =IF($A9>NYears*12,"",MOD($A9-1,12)+1) | E9: =IF($A9>NYears*12,"",LotValue0*(1+LotGrowth)^($C9-1)) | F9: =IF($A9>NYears*12,"",IF($A9=1,InitInvest,$R8)) | G9: =IF($A9>NYears*12,"",INT($F9/$E9)) | H9: =IF($A9>NYears*12,"",$G9*$E9) | I9: =IF($A9>NYears*12,"",$F9-$H9) | J9: =IF($A9>NYears*12,"",$H9*RateB) | K9: =IF($A9>NYears*12,"",IF($D9=1,$J9,$K8+$J9)) | L9: =IF($A9>NYears*12,"",IF(MOD($D9,3)=0,SUM($J7:$J9),0)) | M9: =IF($A9>NYears*12,"",IF(TaxFreq="Quarterly",$K9*12/$D9,$K9)) | N9: =IF($A9>NYears*12,"",LOOKUP($M9,TaxLower,TaxRate)) | O9: =IF($A9>NYears*12,"",IF(TaxFreq="Quarterly",IF(MOD($D9,3)=0,$L9*$N9,0),IF($D9=12,$K9*$N9,0))) | P9: =IF($A9>NYears*12,"",IF($D9=1,$O9,$P8+$O9)) | Q9: =IF($A9>NYears*12,"",IF($D9=12,MIN(WdrPct*IF(WdrBase="Post-tax profit",$K9-$P9,$K9),WdrCap),0)) | R9: =IF($A9>NYears*12,"",$F9+$J9-$O9-$Q9) | S9: =IF($A9>NYears*12,"",INT($R9/$E9))
A10: =6 | B10: =IF($A10>NYears*12,"",EDATE(StartMonth,$A10-1)) | C10: =IF($A10>NYears*12,"",INT(($A10-1)/12)+1) | D10: =IF($A10>NYears*12,"",MOD($A10-1,12)+1) | E10: =IF($A10>NYears*12,"",LotValue0*(1+LotGrowth)^($C10-1)) | F10: =IF($A10>NYears*12,"",IF($A10=1,InitInvest,$R9)) | G10: =IF($A10>NYears*12,"",INT($F10/$E10)) | H10: =IF($A10>NYears*12,"",$G10*$E10) | I10: =IF($A10>NYears*12,"",$F10-$H10) | J10: =IF($A10>NYears*12,"",$H10*RateB) | K10: =IF($A10>NYears*12,"",IF($D10=1,$J10,$K9+$J10)) | L10: =IF($A10>NYears*12,"",IF(MOD($D10,3)=0,SUM($J8:$J10),0)) | M10: =IF($A10>NYears*12,"",IF(TaxFreq="Quarterly",$K10*12/$D10,$K10)) | N10: =IF($A10>NYears*12,"",LOOKUP($M10,TaxLower,TaxRate)) | O10: =IF($A10>NYears*12,"",IF(TaxFreq="Quarterly",IF(MOD($D10,3)=0,$L10*$N10,0),IF($D10=12,$K10*$N10,0))) | P10: =IF($A10>NYears*12,"",IF($D10=1,$O10,$P9+$O10)) | Q10: =IF($A10>NYears*12,"",IF($D10=12,MIN(WdrPct*IF(WdrBase="Post-tax profit",$K10-$P10,$K10),WdrCap),0)) | R10: =IF($A10>NYears*12,"",$F10+$J10-$O10-$Q10) | S10: =IF($A10>NYears*12,"",INT($R10/$E10))
A11: =7 | B11: =IF($A11>NYears*12,"",EDATE(StartMonth,$A11-1)) | C11: =IF($A11>NYears*12,"",INT(($A11-1)/12)+1) | D11: =IF($A11>NYears*12,"",MOD($A11-1,12)+1) | E11: =IF($A11>NYears*12,"",LotValue0*(1+LotGrowth)^($C11-1)) | F11: =IF($A11>NYears*12,"",IF($A11=1,InitInvest,$R10)) | G11: =IF($A11>NYears*12,"",INT($F11/$E11)) | H11: =IF($A11>NYears*12,"",$G11*$E11) | I11: =IF($A11>NYears*12,"",$F11-$H11) | J11: =IF($A11>NYears*12,"",$H11*RateB) | K11: =IF($A11>NYears*12,"",IF($D11=1,$J11,$K10+$J11)) | L11: =IF($A11>NYears*12,"",IF(MOD($D11,3)=0,SUM($J9:$J11),0)) | M11: =IF($A11>NYears*12,"",IF(TaxFreq="Quarterly",$K11*12/$D11,$K11)) | N11: =IF($A11>NYears*12,"",LOOKUP($M11,TaxLower,TaxRate)) | O11: =IF($A11>NYears*12,"",IF(TaxFreq="Quarterly",IF(MOD($D11,3)=0,$L11*$N11,0),IF($D11=12,$K11*$N11,0))) | P11: =IF($A11>NYears*12,"",IF($D11=1,$O11,$P10+$O11)) | Q11: =IF($A11>NYears*12,"",IF($D11=12,MIN(WdrPct*IF(WdrBase="Post-tax profit",$K11-$P11,$K11),WdrCap),0)) | R11: =IF($A11>NYears*12,"",$F11+$J11-$O11-$Q11) | S11: =IF($A11>NYears*12,"",INT($R11/$E11))
A12: =8 | B12: =IF($A12>NYears*12,"",EDATE(StartMonth,$A12-1)) | C12: =IF($A12>NYears*12,"",INT(($A12-1)/12)+1) | D12: =IF($A12>NYears*12,"",MOD($A12-1,12)+1) | E12: =IF($A12>NYears*12,"",LotValue0*(1+LotGrowth)^($C12-1)) | F12: =IF($A12>NYears*12,"",IF($A12=1,InitInvest,$R11)) | G12: =IF($A12>NYears*12,"",INT($F12/$E12)) | H12: =IF($A12>NYears*12,"",$G12*$E12) | I12: =IF($A12>NYears*12,"",$F12-$H12) | J12: =IF($A12>NYears*12,"",$H12*RateB) | K12: =IF($A12>NYears*12,"",IF($D12=1,$J12,$K11+$J12)) | L12: =IF($A12>NYears*12,"",IF(MOD($D12,3)=0,SUM($J10:$J12),0)) | M12: =IF($A12>NYears*12,"",IF(TaxFreq="Quarterly",$K12*12/$D12,$K12)) | N12: =IF($A12>NYears*12,"",LOOKUP($M12,TaxLower,TaxRate)) | O12: =IF($A12>NYears*12,"",IF(TaxFreq="Quarterly",IF(MOD($D12,3)=0,$L12*$N12,0),IF($D12=12,$K12*$N12,0))) | P12: =IF($A12>NYears*12,"",IF($D12=1,$O12,$P11+$O12)) | Q12: =IF($A12>NYears*12,"",IF($D12=12,MIN(WdrPct*IF(WdrBase="Post-tax profit",$K12-$P12,$K12),WdrCap),0)) | R12: =IF($A12>NYears*12,"",$F12+$J12-$O12-$Q12) | S12: =IF($A12>NYears*12,"",INT($R12/$E12))
A13: =9 | B13: =IF($A13>NYears*12,"",EDATE(StartMonth,$A13-1)) | C13: =IF($A13>NYears*12,"",INT(($A13-1)/12)+1) | D13: =IF($A13>NYears*12,"",MOD($A13-1,12)+1) | E13: =IF($A13>NYears*12,"",LotValue0*(1+LotGrowth)^($C13-1)) | F13: =IF($A13>NYears*12,"",IF($A13=1,InitInvest,$R12)) | G13: =IF($A13>NYears*12,"",INT($F13/$E13)) | H13: =IF($A13>NYears*12,"",$G13*$E13) | I13: =IF($A13>NYears*12,"",$F13-$H13) | J13: =IF($A13>NYears*12,"",$H13*RateB) | K13: =IF($A13>NYears*12,"",IF($D13=1,$J13,$K12+$J13)) | L13: =IF($A13>NYears*12,"",IF(MOD($D13,3)=0,SUM($J11:$J13),0)) | M13: =IF($A13>NYears*12,"",IF(TaxFreq="Quarterly",$K13*12/$D13,$K13)) | N13: =IF($A13>NYears*12,"",LOOKUP($M13,TaxLower,TaxRate)) | O13: =IF($A13>NYears*12,"",IF(TaxFreq="Quarterly",IF(MOD($D13,3)=0,$L13*$N13,0),IF($D13=12,$K13*$N13,0))) | P13: =IF($A13>NYears*12,"",IF($D13=1,$O13,$P12+$O13)) | Q13: =IF($A13>NYears*12,"",IF($D13=12,MIN(WdrPct*IF(WdrBase="Post-tax profit",$K13-$P13,$K13),WdrCap),0)) | R13: =IF($A13>NYears*12,"",$F13+$J13-$O13-$Q13) | S13: =IF($A13>NYears*12,"",INT($R13/$E13))
A14: =10 | B14: =IF($A14>NYears*12,"",EDATE(StartMonth,$A14-1)) | C14: =IF($A14>NYears*12,"",INT(($A14-1)/12)+1) | D14: =IF($A14>NYears*12,"",MOD($A14-1,12)+1) | E14: =IF($A14>NYears*12,"",LotValue0*(1+LotGrowth)^($C14-1)) | F14: =IF($A14>NYears*12,"",IF($A14=1,InitInvest,$R13)) | G14: =IF($A14>NYears*12,"",INT($F14/$E14)) | H14: =IF($A14>NYears*12,"",$G14*$E14) | I14: =IF($A14>NYears*12,"",$F14-$H14) | J14: =IF($A14>NYears*12,"",$H14*RateB) | K14: =IF($A14>NYears*12,"",IF($D14=1,$J14,$K13+$J14)) | L14: =IF($A14>NYears*12,"",IF(MOD($D14,3)=0,SUM($J12:$J14),0)) | M14: =IF($A14>NYears*12,"",IF(TaxFreq="Quarterly",$K14*12/$D14,$K14)) | N14: =IF($A14>NYears*12,"",LOOKUP($M14,TaxLower,TaxRate)) | O14: =IF($A14>NYears*12,"",IF(TaxFreq="Quarterly",IF(MOD($D14,3)=0,$L14*$N14,0),IF($D14=12,$K14*$N14,0))) | P14: =IF($A14>NYears*12,"",IF($D14=1,$O14,$P13+$O14)) | Q14: =IF($A14>NYears*12,"",IF($D14=12,MIN(WdrPct*IF(WdrBase="Post-tax profit",$K14-$P14,$K14),WdrCap),0)) | R14: =IF($A14>NYears*12,"",$F14+$J14-$O14-$Q14) | S14: =IF($A14>NYears*12,"",INT($R14/$E14))
A15: =11 | B15: =IF($A15>NYears*12,"",EDATE(StartMonth,$A15-1)) | C15: =IF($A15>NYears*12,"",INT(($A15-1)/12)+1) | D15: =IF($A15>NYears*12,"",MOD($A15-1,12)+1) | E15: =IF($A15>NYears*12,"",LotValue0*(1+LotGrowth)^($C15-1)) | F15: =IF($A15>NYears*12,"",IF($A15=1,InitInvest,$R14)) | G15: =IF($A15>NYears*12,"",INT($F15/$E15)) | H15: =IF($A15>NYears*12,"",$G15*$E15) | I15: =IF($A15>NYears*12,"",$F15-$H15) | J15: =IF($A15>NYears*12,"",$H15*RateB) | K15: =IF($A15>NYears*12,"",IF($D15=1,$J15,$K14+$J15)) | L15: =IF($A15>NYears*12,"",IF(MOD($D15,3)=0,SUM($J13:$J15),0)) | M15: =IF($A15>NYears*12,"",IF(TaxFreq="Quarterly",$K15*12/$D15,$K15)) | N15: =IF($A15>NYears*12,"",LOOKUP($M15,TaxLower,TaxRate)) | O15: =IF($A15>NYears*12,"",IF(TaxFreq="Quarterly",IF(MOD($D15,3)=0,$L15*$N15,0),IF($D15=12,$K15*$N15,0))) | P15: =IF($A15>NYears*12,"",IF($D15=1,$O15,$P14+$O15)) | Q15: =IF($A15>NYears*12,"",IF($D15=12,MIN(WdrPct*IF(WdrBase="Post-tax profit",$K15-$P15,$K15),WdrCap),0)) | R15: =IF($A15>NYears*12,"",$F15+$J15-$O15-$Q15) | S15: =IF($A15>NYears*12,"",INT($R15/$E15))
A16: =12 | B16: =IF($A16>NYears*12,"",EDATE(StartMonth,$A16-1)) | C16: =IF($A16>NYears*12,"",INT(($A16-1)/12)+1) | D16: =IF($A16>NYears*12,"",MOD($A16-1,12)+1) | E16: =IF($A16>NYears*12,"",LotValue0*(1+LotGrowth)^($C16-1)) | F16: =IF($A16>NYears*12,"",IF($A16=1,InitInvest,$R15)) | G16: =IF($A16>NYears*12,"",INT($F16/$E16)) | H16: =IF($A16>NYears*12,"",$G16*$E16) | I16: =IF($A16>NYears*12,"",$F16-$H16) | J16: =IF($A16>NYears*12,"",$H16*RateB) | K16: =IF($A16>NYears*12,"",IF($D16=1,$J16,$K15+$J16)) | L16: =IF($A16>NYears*12,"",IF(MOD($D16,3)=0,SUM($J14:$J16),0)) | M16: =IF($A16>NYears*12,"",IF(TaxFreq="Quarterly",$K16*12/$D16,$K16)) | N16: =IF($A16>NYears*12,"",LOOKUP($M16,TaxLower,TaxRate)) | O16: =IF($A16>NYears*12,"",IF(TaxFreq="Quarterly",IF(MOD($D16,3)=0,$L16*$N16,0),IF($D16=12,$K16*$N16,0))) | P16: =IF($A16>NYears*12,"",IF($D16=1,$O16,$P15+$O16)) | Q16: =IF($A16>NYears*12,"",IF($D16=12,MIN(WdrPct*IF(WdrBase="Post-tax profit",$K16-$P16,$K16),WdrCap),0)) | R16: =IF($A16>NYears*12,"",$F16+$J16-$O16-$Q16) | S16: =IF($A16>NYears*12,"",INT($R16/$E16))
A17: =13 | B17: =IF($A17>NYears*12,"",EDATE(StartMonth,$A17-1)) | C17: =IF($A17>NYears*12,"",INT(($A17-1)/12)+1) | D17: =IF($A17>NYears*12,"",MOD($A17-1,12)+1) | E17: =IF($A17>NYears*12,"",LotValue0*(1+LotGrowth)^($C17-1)) | F17: =IF($A17>NYears*12,"",IF($A17=1,InitInvest,$R16)) | G17: =IF($A17>NYears*12,"",INT($F17/$E17)) | H17: =IF($A17>NYears*12,"",$G17*$E17) | I17: =IF($A17>NYears*12,"",$F17-$H17) | J17: =IF($A17>NYears*12,"",$H17*RateB) | K17: =IF($A17>NYears*12,"",IF($D17=1,$J17,$K16+$J17)) | L17: =IF($A17>NYears*12,"",IF(MOD($D17,3)=0,SUM($J15:$J17),0)) | M17: =IF($A17>NYears*12,"",IF(TaxFreq="Quarterly",$K17*12/$D17,$K17)) | N17: =IF($A17>NYears*12,"",LOOKUP($M17,TaxLower,TaxRate)) | O17: =IF($A17>NYears*12,"",IF(TaxFreq="Quarterly",IF(MOD($D17,3)=0,$L17*$N17,0),IF($D17=12,$K17*$N17,0))) | P17: =IF($A17>NYears*12,"",IF($D17=1,$O17,$P16+$O17)) | Q17: =IF($A17>NYears*12,"",IF($D17=12,MIN(WdrPct*IF(WdrBase="Post-tax profit",$K17-$P17,$K17),WdrCap),0)) | R17: =IF($A17>NYears*12,"",$F17+$J17-$O17-$Q17) | S17: =IF($A17>NYears*12,"",INT($R17/$E17))
A18: =14 | B18: =IF($A18>NYears*12,"",EDATE(StartMonth,$A18-1)) | C18: =IF($A18>NYears*12,"",INT(($A18-1)/12)+1) | D18: =IF($A18>NYears*12,"",MOD($A18-1,12)+1) | E18: =IF($A18>NYears*12,"",LotValue0*(1+LotGrowth)^($C18-1)) | F18: =IF($A18>NYears*12,"",IF($A18=1,InitInvest,$R17)) | G18: =IF($A18>NYears*12,"",INT($F18/$E18)) | H18: =IF($A18>NYears*12,"",$G18*$E18) | I18: =IF($A18>NYears*12,"",$F18-$H18) | J18: =IF($A18>NYears*12,"",$H18*RateB) | K18: =IF($A18>NYears*12,"",IF($D18=1,$J18,$K17+$J18)) | L18: =IF($A18>NYears*12,"",IF(MOD($D18,3)=0,SUM($J16:$J18),0)) | M18: =IF($A18>NYears*12,"",IF(TaxFreq="Quarterly",$K18*12/$D18,$K18)) | N18: =IF($A18>NYears*12,"",LOOKUP($M18,TaxLower,TaxRate)) | O18: =IF($A18>NYears*12,"",IF(TaxFreq="Quarterly",IF(MOD($D18,3)=0,$L18*$N18,0),IF($D18=12,$K18*$N18,0))) | P18: =IF($A18>NYears*12,"",IF($D18=1,$O18,$P17+$O18)) | Q18: =IF($A18>NYears*12,"",IF($D18=12,MIN(WdrPct*IF(WdrBase="Post-tax profit",$K18-$P18,$K18),WdrCap),0)) | R18: =IF($A18>NYears*12,"",$F18+$J18-$O18-$Q18) | S18: =IF($A18>NYears*12,"",INT($R18/$E18))
A19: =15 | B19: =IF($A19>NYears*12,"",EDATE(StartMonth,$A19-1)) | C19: =IF($A19>NYears*12,"",INT(($A19-1)/12)+1) | D19: =IF($A19>NYears*12,"",MOD($A19-1,12)+1) | E19: =IF($A19>NYears*12,"",LotValue0*(1+LotGrowth)^($C19-1)) | F19: =IF($A19>NYears*12,"",IF($A19=1,InitInvest,$R18)) | G19: =IF($A19>NYears*12,"",INT($F19/$E19)) | H19: =IF($A19>NYears*12,"",$G19*$E19) | I19: =IF($A19>NYears*12,"",$F19-$H19) | J19: =IF($A19>NYears*12,"",$H19*RateB) | K19: =IF($A19>NYears*12,"",IF($D19=1,$J19,$K18+$J19)) | L19: =IF($A19>NYears*12,"",IF(MOD($D19,3)=0,SUM($J17:$J19),0)) | M19: =IF($A19>NYears*12,"",IF(TaxFreq="Quarterly",$K19*12/$D19,$K19)) | N19: =IF($A19>NYears*12,"",LOOKUP($M19,TaxLower,TaxRate)) | O19: =IF($A19>NYears*12,"",IF(TaxFreq="Quarterly",IF(MOD($D19,3)=0,$L19*$N19,0),IF($D19=12,$K19*$N19,0))) | P19: =IF($A19>NYears*12,"",IF($D19=1,$O19,$P18+$O19)) | Q19: =IF($A19>NYears*12,"",IF($D19=12,MIN(WdrPct*IF(WdrBase="Post-tax profit",$K19-$P19,$K19),WdrCap),0)) | R19: =IF($A19>NYears*12,"",$F19+$J19-$O19-$Q19) | S19: =IF($A19>NYears*12,"",INT($R19/$E19))
A20: =16 | B20: =IF($A20>NYears*12,"",EDATE(StartMonth,$A20-1)) | C20: =IF($A20>NYears*12,"",INT(($A20-1)/12)+1) | D20: =IF($A20>NYears*12,"",MOD($A20-1,12)+1) | E20: =IF($A20>NYears*12,"",LotValue0*(1+LotGrowth)^($C20-1)) | F20: =IF($A20>NYears*12,"",IF($A20=1,InitInvest,$R19)) | G20: =IF($A20>NYears*12,"",INT($F20/$E20)) | H20: =IF($A20>NYears*12,"",$G20*$E20) | I20: =IF($A20>NYears*12,"",$F20-$H20) | J20: =IF($A20>NYears*12,"",$H20*RateB) | K20: =IF($A20>NYears*12,"",IF($D20=1,$J20,$K19+$J20)) | L20: =IF($A20>NYears*12,"",IF(MOD($D20,3)=0,SUM($J18:$J20),0)) | M20: =IF($A20>NYears*12,"",IF(TaxFreq="Quarterly",$K20*12/$D20,$K20)) | N20: =IF($A20>NYears*12,"",LOOKUP($M20,TaxLower,TaxRate)) | O20: =IF($A20>NYears*12,"",IF(TaxFreq="Quarterly",IF(MOD($D20,3)=0,$L20*$N20,0),IF($D20=12,$K20*$N20,0))) | P20: =IF($A20>NYears*12,"",IF($D20=1,$O20,$P19+$O20)) | Q20: =IF($A20>NYears*12,"",IF($D20=12,MIN(WdrPct*IF(WdrBase="Post-tax profit",$K20-$P20,$K20),WdrCap),0)) | R20: =IF($A20>NYears*12,"",$F20+$J20-$O20-$Q20) | S20: =IF($A20>NYears*12,"",INT($R20/$E20))
A21: =17 | B21: =IF($A21>NYears*12,"",EDATE(StartMonth,$A21-1)) | C21: =IF($A21>NYears*12,"",INT(($A21-1)/12)+1) | D21: =IF($A21>NYears*12,"",MOD($A21-1,12)+1) | E21: =IF($A21>NYears*12,"",LotValue0*(1+LotGrowth)^($C21-1)) | F21: =IF($A21>NYears*12,"",IF($A21=1,InitInvest,$R20)) | G21: =IF($A21>NYears*12,"",INT($F21/$E21)) | H21: =IF($A21>NYears*12,"",$G21*$E21) | I21: =IF($A21>NYears*12,"",$F21-$H21) | J21: =IF($A21>NYears*12,"",$H21*RateB) | K21: =IF($A21>NYears*12,"",IF($D21=1,$J21,$K20+$J21)) | L21: =IF($A21>NYears*12,"",IF(MOD($D21,3)=0,SUM($J19:$J21),0)) | M21: =IF($A21>NYears*12,"",IF(TaxFreq="Quarterly",$K21*12/$D21,$K21)) | N21: =IF($A21>NYears*12,"",LOOKUP($M21,TaxLower,TaxRate)) | O21: =IF($A21>NYears*12,"",IF(TaxFreq="Quarterly",IF(MOD($D21,3)=0,$L21*$N21,0),IF($D21=12,$K21*$N21,0))) | P21: =IF($A21>NYears*12,"",IF($D21=1,$O21,$P20+$O21)) | Q21: =IF($A21>NYears*12,"",IF($D21=12,MIN(WdrPct*IF(WdrBase="Post-tax profit",$K21-$P21,$K21),WdrCap),0)) | R21: =IF($A21>NYears*12,"",$F21+$J21-$O21-$Q21) | S21: =IF($A21>NYears*12,"",INT($R21/$E21))
A22: =18 | B22: =IF($A22>NYears*12,"",EDATE(StartMonth,$A22-1)) | C22: =IF($A22>NYears*12,"",INT(($A22-1)/12)+1) | D22: =IF($A22>NYears*12,"",MOD($A22-1,12)+1) | E22: =IF($A22>NYears*12,"",LotValue0*(1+LotGrowth)^($C22-1)) | F22: =IF($A22>NYears*12,"",IF($A22=1,InitInvest,$R21)) | G22: =IF($A22>NYears*12,"",INT($F22/$E22)) | H22: =IF($A22>NYears*12,"",$G22*$E22) | I22: =IF($A22>NYears*12,"",$F22-$H22) | J22: =IF($A22>NYears*12,"",$H22*RateB) | K22: =IF($A22>NYears*12,"",IF($D22=1,$J22,$K21+$J22)) | L22: =IF($A22>NYears*12,"",IF(MOD($D22,3)=0,SUM($J20:$J22),0)) | M22: =IF($A22>NYears*12,"",IF(TaxFreq="Quarterly",$K22*12/$D22,$K22)) | N22: =IF($A22>NYears*12,"",LOOKUP($M22,TaxLower,TaxRate)) | O22: =IF($A22>NYears*12,"",IF(TaxFreq="Quarterly",IF(MOD($D22,3)=0,$L22*$N22,0),IF($D22=12,$K22*$N22,0))) | P22: =IF($A22>NYears*12,"",IF($D22=1,$O22,$P21+$O22)) | Q22: =IF($A22>NYears*12,"",IF($D22=12,MIN(WdrPct*IF(WdrBase="Post-tax profit",$K22-$P22,$K22),WdrCap),0)) | R22: =IF($A22>NYears*12,"",$F22+$J22-$O22-$Q22) | S22: =IF($A22>NYears*12,"",INT($R22/$E22))
A23: =19 | B23: =IF($A23>NYears*12,"",EDATE(StartMonth,$A23-1)) | C23: =IF($A23>NYears*12,"",INT(($A23-1)/12)+1) | D23: =IF($A23>NYears*12,"",MOD($A23-1,12)+1) | E23: =IF($A23>NYears*12,"",LotValue0*(1+LotGrowth)^($C23-1)) | F23: =IF($A23>NYears*12,"",IF($A23=1,InitInvest,$R22)) | G23: =IF($A23>NYears*12,"",INT($F23/$E23)) | H23: =IF($A23>NYears*12,"",$G23*$E23) | I23: =IF($A23>NYears*12,"",$F23-$H23) | J23: =IF($A23>NYears*12,"",$H23*RateB) | K23: =IF($A23>NYears*12,"",IF($D23=1,$J23,$K22+$J23)) | L23: =IF($A23>NYears*12,"",IF(MOD($D23,3)=0,SUM($J21:$J23),0)) | M23: =IF($A23>NYears*12,"",IF(TaxFreq="Quarterly",$K23*12/$D23,$K23)) | N23: =IF($A23>NYears*12,"",LOOKUP($M23,TaxLower,TaxRate)) | O23: =IF($A23>NYears*12,"",IF(TaxFreq="Quarterly",IF(MOD($D23,3)=0,$L23*$N23,0),IF($D23=12,$K23*$N23,0))) | P23: =IF($A23>NYears*12,"",IF($D23=1,$O23,$P22+$O23)) | Q23: =IF($A23>NYears*12,"",IF($D23=12,MIN(WdrPct*IF(WdrBase="Post-tax profit",$K23-$P23,$K23),WdrCap),0)) | R23: =IF($A23>NYears*12,"",$F23+$J23-$O23-$Q23) | S23: =IF($A23>NYears*12,"",INT($R23/$E23))
A24: =20 | B24: =IF($A24>NYears*12,"",EDATE(StartMonth,$A24-1)) | C24: =IF($A24>NYears*12,"",INT(($A24-1)/12)+1) | D24: =IF($A24>NYears*12,"",MOD($A24-1,12)+1) | E24: =IF($A24>NYears*12,"",LotValue0*(1+LotGrowth)^($C24-1)) | F24: =IF($A24>NYears*12,"",IF($A24=1,InitInvest,$R23)) | G24: =IF($A24>NYears*12,"",INT($F24/$E24)) | H24: =IF($A24>NYears*12,"",$G24*$E24) | I24: =IF($A24>NYears*12,"",$F24-$H24) | J24: =IF($A24>NYears*12,"",$H24*RateB) | K24: =IF($A24>NYears*12,"",IF($D24=1,$J24,$K23+$J24)) | L24: =IF($A24>NYears*12,"",IF(MOD($D24,3)=0,SUM($J22:$J24),0)) | M24: =IF($A24>NYears*12,"",IF(TaxFreq="Quarterly",$K24*12/$D24,$K24)) | N24: =IF($A24>NYears*12,"",LOOKUP($M24,TaxLower,TaxRate)) | O24: =IF($A24>NYears*12,"",IF(TaxFreq="Quarterly",IF(MOD($D24,3)=0,$L24*$N24,0),IF($D24=12,$K24*$N24,0))) | P24: =IF($A24>NYears*12,"",IF($D24=1,$O24,$P23+$O24)) | Q24: =IF($A24>NYears*12,"",IF($D24=12,MIN(WdrPct*IF(WdrBase="Post-tax profit",$K24-$P24,$K24),WdrCap),0)) | R24: =IF($A24>NYears*12,"",$F24+$J24-$O24-$Q24) | S24: =IF($A24>NYears*12,"",INT($R24/$E24))
A25: =21 | B25: =IF($A25>NYears*12,"",EDATE(StartMonth,$A25-1)) | C25: =IF($A25>NYears*12,"",INT(($A25-1)/12)+1) | D25: =IF($A25>NYears*12,"",MOD($A25-1,12)+1) | E25: =IF($A25>NYears*12,"",LotValue0*(1+LotGrowth)^($C25-1)) | F25: =IF($A25>NYears*12,"",IF($A25=1,InitInvest,$R24)) | G25: =IF($A25>NYears*12,"",INT($F25/$E25)) | H25: =IF($A25>NYears*12,"",$G25*$E25) | I25: =IF($A25>NYears*12,"",$F25-$H25) | J25: =IF($A25>NYears*12,"",$H25*RateB) | K25: =IF($A25>NYears*12,"",IF($D25=1,$J25,$K24+$J25)) | L25: =IF($A25>NYears*12,"",IF(MOD($D25,3)=0,SUM($J23:$J25),0)) | M25: =IF($A25>NYears*12,"",IF(TaxFreq="Quarterly",$K25*12/$D25,$K25)) | N25: =IF($A25>NYears*12,"",LOOKUP($M25,TaxLower,TaxRate)) | O25: =IF($A25>NYears*12,"",IF(TaxFreq="Quarterly",IF(MOD($D25,3)=0,$L25*$N25,0),IF($D25=12,$K25*$N25,0))) | P25: =IF($A25>NYears*12,"",IF($D25=1,$O25,$P24+$O25)) | Q25: =IF($A25>NYears*12,"",IF($D25=12,MIN(WdrPct*IF(WdrBase="Post-tax profit",$K25-$P25,$K25),WdrCap),0)) | R25: =IF($A25>NYears*12,"",$F25+$J25-$O25-$Q25) | S25: =IF($A25>NYears*12,"",INT($R25/$E25))
A26: =22 | B26: =IF($A26>NYears*12,"",EDATE(StartMonth,$A26-1)) | C26: =IF($A26>NYears*12,"",INT(($A26-1)/12)+1) | D26: =IF($A26>NYears*12,"",MOD($A26-1,12)+1) | E26: =IF($A26>NYears*12,"",LotValue0*(1+LotGrowth)^($C26-1)) | F26: =IF($A26>NYears*12,"",IF($A26=1,InitInvest,$R25)) | G26: =IF($A26>NYears*12,"",INT($F26/$E26)) | H26: =IF($A26>NYears*12,"",$G26*$E26) | I26: =IF($A26>NYears*12,"",$F26-$H26) | J26: =IF($A26>NYears*12,"",$H26*RateB) | K26: =IF($A26>NYears*12,"",IF($D26=1,$J26,$K25+$J26)) | L26: =IF($A26>NYears*12,"",IF(MOD($D26,3)=0,SUM($J24:$J26),0)) | M26: =IF($A26>NYears*12,"",IF(TaxFreq="Quarterly",$K26*12/$D26,$K26)) | N26: =IF($A26>NYears*12,"",LOOKUP($M26,TaxLower,TaxRate)) | O26: =IF($A26>NYears*12,"",IF(TaxFreq="Quarterly",IF(MOD($D26,3)=0,$L26*$N26,0),IF($D26=12,$K26*$N26,0))) | P26: =IF($A26>NYears*12,"",IF($D26=1,$O26,$P25+$O26)) | Q26: =IF($A26>NYears*12,"",IF($D26=12,MIN(WdrPct*IF(WdrBase="Post-tax profit",$K26-$P26,$K26),WdrCap),0)) | R26: =IF($A26>NYears*12,"",$F26+$J26-$O26-$Q26) | S26: =IF($A26>NYears*12,"",INT($R26/$E26))
A27: =23 | B27: =IF($A27>NYears*12,"",EDATE(StartMonth,$A27-1)) | C27: =IF($A27>NYears*12,"",INT(($A27-1)/12)+1) | D27: =IF($A27>NYears*12,"",MOD($A27-1,12)+1) | E27: =IF($A27>NYears*12,"",LotValue0*(1+LotGrowth)^($C27-1)) | F27: =IF($A27>NYears*12,"",IF($A27=1,InitInvest,$R26)) | G27: =IF($A27>NYears*12,"",INT($F27/$E27)) | H27: =IF($A27>NYears*12,"",$G27*$E27) | I27: =IF($A27>NYears*12,"",$F27-$H27) | J27: =IF($A27>NYears*12,"",$H27*RateB) | K27: =IF($A27>NYears*12,"",IF($D27=1,$J27,$K26+$J27)) | L27: =IF($A27>NYears*12,"",IF(MOD($D27,3)=0,SUM($J25:$J27),0)) | M27: =IF($A27>NYears*12,"",IF(TaxFreq="Quarterly",$K27*12/$D27,$K27)) | N27: =IF($A27>NYears*12,"",LOOKUP($M27,TaxLower,TaxRate)) | O27: =IF($A27>NYears*12,"",IF(TaxFreq="Quarterly",IF(MOD($D27,3)=0,$L27*$N27,0),IF($D27=12,$K27*$N27,0))) | P27: =IF($A27>NYears*12,"",IF($D27=1,$O27,$P26+$O27)) | Q27: =IF($A27>NYears*12,"",IF($D27=12,MIN(WdrPct*IF(WdrBase="Post-tax profit",$K27-$P27,$K27),WdrCap),0)) | R27: =IF($A27>NYears*12,"",$F27+$J27-$O27-$Q27) | S27: =IF($A27>NYears*12,"",INT($R27/$E27))
A28: =24 | B28: =IF($A28>NYears*12,"",EDATE(StartMonth,$A28-1)) | C28: =IF($A28>NYears*12,"",INT(($A28-1)/12)+1) | D28: =IF($A28>NYears*12,"",MOD($A28-1,12)+1) | E28: =IF($A28>NYears*12,"",LotValue0*(1+LotGrowth)^($C28-1)) | F28: =IF($A28>NYears*12,"",IF($A28=1,InitInvest,$R27)) | G28: =IF($A28>NYears*12,"",INT($F28/$E28)) | H28: =IF($A28>NYears*12,"",$G28*$E28) | I28: =IF($A28>NYears*12,"",$F28-$H28) | J28: =IF($A28>NYears*12,"",$H28*RateB) | K28: =IF($A28>NYears*12,"",IF($D28=1,$J28,$K27+$J28)) | L28: =IF($A28>NYears*12,"",IF(MOD($D28,3)=0,SUM($J26:$J28),0)) | M28: =IF($A28>NYears*12,"",IF(TaxFreq="Quarterly",$K28*12/$D28,$K28)) | N28: =IF($A28>NYears*12,"",LOOKUP($M28,TaxLower,TaxRate)) | O28: =IF($A28>NYears*12,"",IF(TaxFreq="Quarterly",IF(MOD($D28,3)=0,$L28*$N28,0),IF($D28=12,$K28*$N28,0))) | P28: =IF($A28>NYears*12,"",IF($D28=1,$O28,$P27+$O28)) | Q28: =IF($A28>NYears*12,"",IF($D28=12,MIN(WdrPct*IF(WdrBase="Post-tax profit",$K28-$P28,$K28),WdrCap),0)) | R28: =IF($A28>NYears*12,"",$F28+$J28-$O28-$Q28) | S28: =IF($A28>NYears*12,"",INT($R28/$E28))
A29: =25 | B29: =IF($A29>NYears*12,"",EDATE(StartMonth,$A29-1)) | C29: =IF($A29>NYears*12,"",INT(($A29-1)/12)+1) | D29: =IF($A29>NYears*12,"",MOD($A29-1,12)+1) | E29: =IF($A29>NYears*12,"",LotValue0*(1+LotGrowth)^($C29-1)) | F29: =IF($A29>NYears*12,"",IF($A29=1,InitInvest,$R28)) | G29: =IF($A29>NYears*12,"",INT($F29/$E29)) | H29: =IF($A29>NYears*12,"",$G29*$E29) | I29: =IF($A29>NYears*12,"",$F29-$H29) | J29: =IF($A29>NYears*12,"",$H29*RateB) | K29: =IF($A29>NYears*12,"",IF($D29=1,$J29,$K28+$J29)) | L29: =IF($A29>NYears*12,"",IF(MOD($D29,3)=0,SUM($J27:$J29),0)) | M29: =IF($A29>NYears*12,"",IF(TaxFreq="Quarterly",$K29*12/$D29,$K29)) | N29: =IF($A29>NYears*12,"",LOOKUP($M29,TaxLower,TaxRate)) | O29: =IF($A29>NYears*12,"",IF(TaxFreq="Quarterly",IF(MOD($D29,3)=0,$L29*$N29,0),IF($D29=12,$K29*$N29,0))) | P29: =IF($A29>NYears*12,"",IF($D29=1,$O29,$P28+$O29)) | Q29: =IF($A29>NYears*12,"",IF($D29=12,MIN(WdrPct*IF(WdrBase="Post-tax profit",$K29-$P29,$K29),WdrCap),0)) | R29: =IF($A29>NYears*12,"",$F29+$J29-$O29-$Q29) | S29: =IF($A29>NYears*12,"",INT($R29/$E29))
A30: =26 | B30: =IF($A30>NYears*12,"",EDATE(StartMonth,$A30-1)) | C30: =IF($A30>NYears*12,"",INT(($A30-1)/12)+1) | D30: =IF($A30>NYears*12,"",MOD($A30-1,12)+1) | E30: =IF($A30>NYears*12,"",LotValue0*(1+LotGrowth)^($C30-1)) | F30: =IF($A30>NYears*12,"",IF($A30=1,InitInvest,$R29)) | G30: =IF($A30>NYears*12,"",INT($F30/$E30)) | H30: =IF($A30>NYears*12,"",$G30*$E30) | I30: =IF($A30>NYears*12,"",$F30-$H30) | J30: =IF($A30>NYears*12,"",$H30*RateB) | K30: =IF($A30>NYears*12,"",IF($D30=1,$J30,$K29+$J30)) | L30: =IF($A30>NYears*12,"",IF(MOD($D30,3)=0,SUM($J28:$J30),0)) | M30: =IF($A30>NYears*12,"",IF(TaxFreq="Quarterly",$K30*12/$D30,$K30)) | N30: =IF($A30>NYears*12,"",LOOKUP($M30,TaxLower,TaxRate)) | O30: =IF($A30>NYears*12,"",IF(TaxFreq="Quarterly",IF(MOD($D30,3)=0,$L30*$N30,0),IF($D30=12,$K30*$N30,0))) | P30: =IF($A30>NYears*12,"",IF($D30=1,$O30,$P29+$O30)) | Q30: =IF($A30>NYears*12,"",IF($D30=12,MIN(WdrPct*IF(WdrBase="Post-tax profit",$K30-$P30,$K30),WdrCap),0)) | R30: =IF($A30>NYears*12,"",$F30+$J30-$O30-$Q30) | S30: =IF($A30>NYears*12,"",INT($R30/$E30))
A31: =27 | B31: =IF($A31>NYears*12,"",EDATE(StartMonth,$A31-1)) | C31: =IF($A31>NYears*12,"",INT(($A31-1)/12)+1) | D31: =IF($A31>NYears*12,"",MOD($A31-1,12)+1) | E31: =IF($A31>NYears*12,"",LotValue0*(1+LotGrowth)^($C31-1)) | F31: =IF($A31>NYears*12,"",IF($A31=1,InitInvest,$R30)) | G31: =IF($A31>NYears*12,"",INT($F31/$E31)) | H31: =IF($A31>NYears*12,"",$G31*$E31) | I31: =IF($A31>NYears*12,"",$F31-$H31) | J31: =IF($A31>NYears*12,"",$H31*RateB) | K31: =IF($A31>NYears*12,"",IF($D31=1,$J31,$K30+$J31)) | L31: =IF($A31>NYears*12,"",IF(MOD($D31,3)=0,SUM($J29:$J31),0)) | M31: =IF($A31>NYears*12,"",IF(TaxFreq="Quarterly",$K31*12/$D31,$K31)) | N31: =IF($A31>NYears*12,"",LOOKUP($M31,TaxLower,TaxRate)) | O31: =IF($A31>NYears*12,"",IF(TaxFreq="Quarterly",IF(MOD($D31,3)=0,$L31*$N31,0),IF($D31=12,$K31*$N31,0))) | P31: =IF($A31>NYears*12,"",IF($D31=1,$O31,$P30+$O31)) | Q31: =IF($A31>NYears*12,"",IF($D31=12,MIN(WdrPct*IF(WdrBase="Post-tax profit",$K31-$P31,$K31),WdrCap),0)) | R31: =IF($A31>NYears*12,"",$F31+$J31-$O31-$Q31) | S31: =IF($A31>NYears*12,"",INT($R31/$E31))
A32: =28 | B32: =IF($A32>NYears*12,"",EDATE(StartMonth,$A32-1)) | C32: =IF($A32>NYears*12,"",INT(($A32-1)/12)+1) | D32: =IF($A32>NYears*12,"",MOD($A32-1,12)+1) | E32: =IF($A32>NYears*12,"",LotValue0*(1+LotGrowth)^($C32-1)) | F32: =IF($A32>NYears*12,"",IF($A32=1,InitInvest,$R31)) | G32: =IF($A32>NYears*12,"",INT($F32/$E32)) | H32: =IF($A32>NYears*12,"",$G32*$E32) | I32: =IF($A32>NYears*12,"",$F32-$H32) | J32: =IF($A32>NYears*12,"",$H32*RateB) | K32: =IF($A32>NYears*12,"",IF($D32=1,$J32,$K31+$J32)) | L32: =IF($A32>NYears*12,"",IF(MOD($D32,3)=0,SUM($J30:$J32),0)) | M32: =IF($A32>NYears*12,"",IF(TaxFreq="Quarterly",$K32*12/$D32,$K32)) | N32: =IF($A32>NYears*12,"",LOOKUP($M32,TaxLower,TaxRate)) | O32: =IF($A32>NYears*12,"",IF(TaxFreq="Quarterly",IF(MOD($D32,3)=0,$L32*$N32,0),IF($D32=12,$K32*$N32,0))) | P32: =IF($A32>NYears*12,"",IF($D32=1,$O32,$P31+$O32)) | Q32: =IF($A32>NYears*12,"",IF($D32=12,MIN(WdrPct*IF(WdrBase="Post-tax profit",$K32-$P32,$K32),WdrCap),0)) | R32: =IF($A32>NYears*12,"",$F32+$J32-$O32-$Q32) | S32: =IF($A32>NYears*12,"",INT($R32/$E32))
A33: =29 | B33: =IF($A33>NYears*12,"",EDATE(StartMonth,$A33-1)) | C33: =IF($A33>NYears*12,"",INT(($A33-1)/12)+1) | D33: =IF($A33>NYears*12,"",MOD($A33-1,12)+1) | E33: =IF($A33>NYears*12,"",LotValue0*(1+LotGrowth)^($C33-1)) | F33: =IF($A33>NYears*12,"",IF($A33=1,InitInvest,$R32)) | G33: =IF($A33>NYears*12,"",INT($F33/$E33)) | H33: =IF($A33>NYears*12,"",$G33*$E33) | I33: =IF($A33>NYears*12,"",$F33-$H33) | J33: =IF($A33>NYears*12,"",$H33*RateB) | K33: =IF($A33>NYears*12,"",IF($D33=1,$J33,$K32+$J33)) | L33: =IF($A33>NYears*12,"",IF(MOD($D33,3)=0,SUM($J31:$J33),0)) | M33: =IF($A33>NYears*12,"",IF(TaxFreq="Quarterly",$K33*12/$D33,$K33)) | N33: =IF($A33>NYears*12,"",LOOKUP($M33,TaxLower,TaxRate)) | O33: =IF($A33>NYears*12,"",IF(TaxFreq="Quarterly",IF(MOD($D33,3)=0,$L33*$N33,0),IF($D33=12,$K33*$N33,0))) | P33: =IF($A33>NYears*12,"",IF($D33=1,$O33,$P32+$O33)) | Q33: =IF($A33>NYears*12,"",IF($D33=12,MIN(WdrPct*IF(WdrBase="Post-tax profit",$K33-$P33,$K33),WdrCap),0)) | R33: =IF($A33>NYears*12,"",$F33+$J33-$O33-$Q33) | S33: =IF($A33>NYears*12,"",INT($R33/$E33))
A34: =30 | B34: =IF($A34>NYears*12,"",EDATE(StartMonth,$A34-1)) | C34: =IF($A34>NYears*12,"",INT(($A34-1)/12)+1) | D34: =IF($A34>NYears*12,"",MOD($A34-1,12)+1) | E34: =IF($A34>NYears*12,"",LotValue0*(1+LotGrowth)^($C34-1)) | F34: =IF($A34>NYears*12,"",IF($A34=1,InitInvest,$R33)) | G34: =IF($A34>NYears*12,"",INT($F34/$E34)) | H34: =IF($A34>NYears*12,"",$G34*$E34) | I34: =IF($A34>NYears*12,"",$F34-$H34) | J34: =IF($A34>NYears*12,"",$H34*RateB) | K34: =IF($A34>NYears*12,"",IF($D34=1,$J34,$K33+$J34)) | L34: =IF($A34>NYears*12,"",IF(MOD($D34,3)=0,SUM($J32:$J34),0)) | M34: =IF($A34>NYears*12,"",IF(TaxFreq="Quarterly",$K34*12/$D34,$K34)) | N34: =IF($A34>NYears*12,"",LOOKUP($M34,TaxLower,TaxRate)) | O34: =IF($A34>NYears*12,"",IF(TaxFreq="Quarterly",IF(MOD($D34,3)=0,$L34*$N34,0),IF($D34=12,$K34*$N34,0))) | P34: =IF($A34>NYears*12,"",IF($D34=1,$O34,$P33+$O34)) | Q34: =IF($A34>NYears*12,"",IF($D34=12,MIN(WdrPct*IF(WdrBase="Post-tax profit",$K34-$P34,$K34),WdrCap),0)) | R34: =IF($A34>NYears*12,"",$F34+$J34-$O34-$Q34) | S34: =IF($A34>NYears*12,"",INT($R34/$E34))
A35: =31 | B35: =IF($A35>NYears*12,"",EDATE(StartMonth,$A35-1)) | C35: =IF($A35>NYears*12,"",INT(($A35-1)/12)+1) | D35: =IF($A35>NYears*12,"",MOD($A35-1,12)+1) | E35: =IF($A35>NYears*12,"",LotValue0*(1+LotGrowth)^($C35-1)) | F35: =IF($A35>NYears*12,"",IF($A35=1,InitInvest,$R34)) | G35: =IF($A35>NYears*12,"",INT($F35/$E35)) | H35: =IF($A35>NYears*12,"",$G35*$E35) | I35: =IF($A35>NYears*12,"",$F35-$H35) | J35: =IF($A35>NYears*12,"",$H35*RateB) | K35: =IF($A35>NYears*12,"",IF($D35=1,$J35,$K34+$J35)) | L35: =IF($A35>NYears*12,"",IF(MOD($D35,3)=0,SUM($J33:$J35),0)) | M35: =IF($A35>NYears*12,"",IF(TaxFreq="Quarterly",$K35*12/$D35,$K35)) | N35: =IF($A35>NYears*12,"",LOOKUP($M35,TaxLower,TaxRate)) | O35: =IF($A35>NYears*12,"",IF(TaxFreq="Quarterly",IF(MOD($D35,3)=0,$L35*$N35,0),IF($D35=12,$K35*$N35,0))) | P35: =IF($A35>NYears*12,"",IF($D35=1,$O35,$P34+$O35)) | Q35: =IF($A35>NYears*12,"",IF($D35=12,MIN(WdrPct*IF(WdrBase="Post-tax profit",$K35-$P35,$K35),WdrCap),0)) | R35: =IF($A35>NYears*12,"",$F35+$J35-$O35-$Q35) | S35: =IF($A35>NYears*12,"",INT($R35/$E35))
A36: =32 | B36: =IF($A36>NYears*12,"",EDATE(StartMonth,$A36-1)) | C36: =IF($A36>NYears*12,"",INT(($A36-1)/12)+1) | D36: =IF($A36>NYears*12,"",MOD($A36-1,12)+1) | E36: =IF($A36>NYears*12,"",LotValue0*(1+LotGrowth)^($C36-1)) | F36: =IF($A36>NYears*12,"",IF($A36=1,InitInvest,$R35)) | G36: =IF($A36>NYears*12,"",INT($F36/$E36)) | H36: =IF($A36>NYears*12,"",$G36*$E36) | I36: =IF($A36>NYears*12,"",$F36-$H36) | J36: =IF($A36>NYears*12,"",$H36*RateB) | K36: =IF($A36>NYears*12,"",IF($D36=1,$J36,$K35+$J36)) | L36: =IF($A36>NYears*12,"",IF(MOD($D36,3)=0,SUM($J34:$J36),0)) | M36: =IF($A36>NYears*12,"",IF(TaxFreq="Quarterly",$K36*12/$D36,$K36)) | N36: =IF($A36>NYears*12,"",LOOKUP($M36,TaxLower,TaxRate)) | O36: =IF($A36>NYears*12,"",IF(TaxFreq="Quarterly",IF(MOD($D36,3)=0,$L36*$N36,0),IF($D36=12,$K36*$N36,0))) | P36: =IF($A36>NYears*12,"",IF($D36=1,$O36,$P35+$O36)) | Q36: =IF($A36>NYears*12,"",IF($D36=12,MIN(WdrPct*IF(WdrBase="Post-tax profit",$K36-$P36,$K36),WdrCap),0)) | R36: =IF($A36>NYears*12,"",$F36+$J36-$O36-$Q36) | S36: =IF($A36>NYears*12,"",INT($R36/$E36))
A37: =33 | B37: =IF($A37>NYears*12,"",EDATE(StartMonth,$A37-1)) | C37: =IF($A37>NYears*12,"",INT(($A37-1)/12)+1) | D37: =IF($A37>NYears*12,"",MOD($A37-1,12)+1) | E37: =IF($A37>NYears*12,"",LotValue0*(1+LotGrowth)^($C37-1)) | F37: =IF($A37>NYears*12,"",IF($A37=1,InitInvest,$R36)) | G37: =IF($A37>NYears*12,"",INT($F37/$E37)) | H37: =IF($A37>NYears*12,"",$G37*$E37) | I37: =IF($A37>NYears*12,"",$F37-$H37) | J37: =IF($A37>NYears*12,"",$H37*RateB) | K37: =IF($A37>NYears*12,"",IF($D37=1,$J37,$K36+$J37)) | L37: =IF($A37>NYears*12,"",IF(MOD($D37,3)=0,SUM($J35:$J37),0)) | M37: =IF($A37>NYears*12,"",IF(TaxFreq="Quarterly",$K37*12/$D37,$K37)) | N37: =IF($A37>NYears*12,"",LOOKUP($M37,TaxLower,TaxRate)) | O37: =IF($A37>NYears*12,"",IF(TaxFreq="Quarterly",IF(MOD($D37,3)=0,$L37*$N37,0),IF($D37=12,$K37*$N37,0))) | P37: =IF($A37>NYears*12,"",IF($D37=1,$O37,$P36+$O37)) | Q37: =IF($A37>NYears*12,"",IF($D37=12,MIN(WdrPct*IF(WdrBase="Post-tax profit",$K37-$P37,$K37),WdrCap),0)) | R37: =IF($A37>NYears*12,"",$F37+$J37-$O37-$Q37) | S37: =IF($A37>NYears*12,"",INT($R37/$E37))
A38: =34 | B38: =IF($A38>NYears*12,"",EDATE(StartMonth,$A38-1)) | C38: =IF($A38>NYears*12,"",INT(($A38-1)/12)+1) | D38: =IF($A38>NYears*12,"",MOD($A38-1,12)+1) | E38: =IF($A38>NYears*12,"",LotValue0*(1+LotGrowth)^($C38-1)) | F38: =IF($A38>NYears*12,"",IF($A38=1,InitInvest,$R37)) | G38: =IF($A38>NYears*12,"",INT($F38/$E38)) | H38: =IF($A38>NYears*12,"",$G38*$E38) | I38: =IF($A38>NYears*12,"",$F38-$H38) | J38: =IF($A38>NYears*12,"",$H38*RateB) | K38: =IF($A38>NYears*12,"",IF($D38=1,$J38,$K37+$J38)) | L38: =IF($A38>NYears*12,"",IF(MOD($D38,3)=0,SUM($J36:$J38),0)) | M38: =IF($A38>NYears*12,"",IF(TaxFreq="Quarterly",$K38*12/$D38,$K38)) | N38: =IF($A38>NYears*12,"",LOOKUP($M38,TaxLower,TaxRate)) | O38: =IF($A38>NYears*12,"",IF(TaxFreq="Quarterly",IF(MOD($D38,3)=0,$L38*$N38,0),IF($D38=12,$K38*$N38,0))) | P38: =IF($A38>NYears*12,"",IF($D38=1,$O38,$P37+$O38)) | Q38: =IF($A38>NYears*12,"",IF($D38=12,MIN(WdrPct*IF(WdrBase="Post-tax profit",$K38-$P38,$K38),WdrCap),0)) | R38: =IF($A38>NYears*12,"",$F38+$J38-$O38-$Q38) | S38: =IF($A38>NYears*12,"",INT($R38/$E38))
A39: =35 | B39: =IF($A39>NYears*12,"",EDATE(StartMonth,$A39-1)) | C39: =IF($A39>NYears*12,"",INT(($A39-1)/12)+1) | D39: =IF($A39>NYears*12,"",MOD($A39-1,12)+1) | E39: =IF($A39>NYears*12,"",LotValue0*(1+LotGrowth)^($C39-1)) | F39: =IF($A39>NYears*12,"",IF($A39=1,InitInvest,$R38)) | G39: =IF($A39>NYears*12,"",INT($F39/$E39)) | H39: =IF($A39>NYears*12,"",$G39*$E39) | I39: =IF($A39>NYears*12,"",$F39-$H39) | J39: =IF($A39>NYears*12,"",$H39*RateB) | K39: =IF($A39>NYears*12,"",IF($D39=1,$J39,$K38+$J39)) | L39: =IF($A39>NYears*12,"",IF(MOD($D39,3)=0,SUM($J37:$J39),0)) | M39: =IF($A39>NYears*12,"",IF(TaxFreq="Quarterly",$K39*12/$D39,$K39)) | N39: =IF($A39>NYears*12,"",LOOKUP($M39,TaxLower,TaxRate)) | O39: =IF($A39>NYears*12,"",IF(TaxFreq="Quarterly",IF(MOD($D39,3)=0,$L39*$N39,0),IF($D39=12,$K39*$N39,0))) | P39: =IF($A39>NYears*12,"",IF($D39=1,$O39,$P38+$O39)) | Q39: =IF($A39>NYears*12,"",IF($D39=12,MIN(WdrPct*IF(WdrBase="Post-tax profit",$K39-$P39,$K39),WdrCap),0)) | R39: =IF($A39>NYears*12,"",$F39+$J39-$O39-$Q39) | S39: =IF($A39>NYears*12,"",INT($R39/$E39))
A40: =36 | B40: =IF($A40>NYears*12,"",EDATE(StartMonth,$A40-1)) | C40: =IF($A40>NYears*12,"",INT(($A40-1)/12)+1) | D40: =IF($A40>NYears*12,"",MOD($A40-1,12)+1) | E40: =IF($A40>NYears*12,"",LotValue0*(1+LotGrowth)^($C40-1)) | F40: =IF($A40>NYears*12,"",IF($A40=1,InitInvest,$R39)) | G40: =IF($A40>NYears*12,"",INT($F40/$E40)) | H40: =IF($A40>NYears*12,"",$G40*$E40) | I40: =IF($A40>NYears*12,"",$F40-$H40) | J40: =IF($A40>NYears*12,"",$H40*RateB) | K40: =IF($A40>NYears*12,"",IF($D40=1,$J40,$K39+$J40)) | L40: =IF($A40>NYears*12,"",IF(MOD($D40,3)=0,SUM($J38:$J40),0)) | M40: =IF($A40>NYears*12,"",IF(TaxFreq="Quarterly",$K40*12/$D40,$K40)) | N40: =IF($A40>NYears*12,"",LOOKUP($M40,TaxLower,TaxRate)) | O40: =IF($A40>NYears*12,"",IF(TaxFreq="Quarterly",IF(MOD($D40,3)=0,$L40*$N40,0),IF($D40=12,$K40*$N40,0))) | P40: =IF($A40>NYears*12,"",IF($D40=1,$O40,$P39+$O40)) | Q40: =IF($A40>NYears*12,"",IF($D40=12,MIN(WdrPct*IF(WdrBase="Post-tax profit",$K40-$P40,$K40),WdrCap),0)) | R40: =IF($A40>NYears*12,"",$F40+$J40-$O40-$Q40) | S40: =IF($A40>NYears*12,"",INT($R40/$E40))
